Workbook

Sheet 01-VP_VF
B1: © Escola de Imóveis - www.escoladeimoveis.com.br | Siga no instagram e tenha o melhor conteúdo: @escoladeimoveis
B2: É terminantemente proibida a utilização, acesso, cópia ou divulgação não autorizada das informações presentes nesta planilha.
B3: ATENÇÃO: SOMENTE ALTERAR AS CÉLULAS ROXAS COM A ESCRITA FAÇA VOCÊ
B5: Valor Presente (VP ou PV)
B7: Ex 1.0 | C7: Faça Você | D7: Resposta | F7: Ex 1.1 | G7: Faça Você | H7: Resposta
B8: Valor Futuro | D8: 60000 | F8: Valor Futuro | H8: 19900
B9: Período | D9: 10 | F9: Período | H9: 18
B10: Taxa | D10: 0.05 | F10: Taxa | H10: 0.0115
B11: Valor Presente | D11: =-(PV(D10,D9,,D8)) -> 36834.795 | F11: Valor Presente | H11: =-(PV(H10,H9,,H8)) -> 16198.213
B13: Valor Futuro (VF ou FV)
B15: Ex 2.0 | C15: Faça Você | D15: Resposta | F15: Ex 2.1 | G15: Faça Você | H15: Resposta
B16: Valor Presente | D16: 36834.8 | F16: Valor Presente | H16: 16198.21
B17: Período | D17: 10 | F17: Período | H17: 18
B18: Taxa | D18: 0.05 | F18: Taxa | H18: 0.0115
B19: Valor Futuro | D19: =-(FV(D18,D17,,D16)) -> 60000.008 | F19: Valor Futuro | H19: =-(FV(H18,H17,,H16)) -> 19899.996

Sheet 02-VPL
B1: © Escola de Imóveis - www.escoladeimoveis.com.br | Siga no instagram e tenha o melhor conteúdo: @escoladeimoveis
B2: É terminantemente proibida a utilização, acesso, cópia ou divulgação não autorizada das informações presentes nesta planilha.
B3: ATENÇÃO: SOMENTE ALTERAR AS CÉLULAS ROXAS COM A ESCRITA FAÇA VOCÊ
B5: Valor Presente LÍquido (VPL ou NPV)
B7: Ex 1.0 | C7: Faça Você | D7: Resposta | G7: 2020 | H7: 2021 | I7: 2022 | J7: 2023 | K7: 2025 | L7: 2026 | M7: 2034
B8: Custo de Capital | D8: 0.06 | F8: Investimento | G8: -100000
B9: VPL | D9: {=NPV(D8,H11:M11)+G11} -> 90165.351 | F9: Renda | H9: 10000 | I9: 10000 | J9: 10000 | K9: 10000 | L9: 10000 | M9: 10000
F10: Venda | M10: 200000
G11: =SUM(G8:G10) -> -100000 | H11: =SUM(H8:H10) -> 10000 | I11: =SUM(I8:I10) -> 10000 | J11: =SUM(J8:J10) -> 10000 | K11: =SUM(K8:K10) -> 10000 | L11: =SUM(L8:L10) -> 10000 | M11: =SUM(M8:M10) -> 210000
B15: Ex 2.0 | C15: Faça Você | D15: Resposta | G15: 2020 | H15: 2021 | I15: 2022 | J15: 2023 | K15: 2025 | L15: 2026 | M15: 2027
B16: Custo de Capital | D16: 0.08 | F16: Investimento | G16: -235000
B17: VPL | D17: {=NPV(D16,H19:M19)+G19} -> -4744.4971 | F17: Renda | H17: 8000 | I17: 9000 | J17: 10000 | K17: 11000 | L17: 12000 | M17: 13000
F18: Venda | M18: 290000
G19: =SUM(G16:G18) -> -235000 | H19: =SUM(H16:H18) -> 8000 | I19: =SUM(I16:I18) -> 9000 | J19: =SUM(J16:J18) -> 10000 | K19: =SUM(K16:K18) -> 11000 | L19: =SUM(L16:L18) -> 12000 | M19: =SUM(M16:M18) -> 303000
B23: Ex 2.0 | C23: Faça Você | D23: Resposta | G23: 2020 | H23: 2021 | I23: 2022 | J23: 2023 | K23: 2025 | L23: 2026 | M23: 2027
B24: Custo de Capital | D24: 0.095 | F24: Investimento | G24: -90000
B25: VPL | D25: {=NPV(D24,H27:M27)+G27} -> 7519.4105 | F25: Renda | H25: 5000 | I25: 5500 | J25: 6000 | K25: 8000 | L25: 9000 | M25: 10000
F26: Venda | M26: 115000
G27: =SUM(G24:G26) -> -90000 | H27: =SUM(H24:H26) -> 5000 | I27: =SUM(I24:I26) -> 5500 | J27: =SUM(J24:J26) -> 6000 | K27: =SUM(K24:K26) -> 8000 | L27: =SUM(L24:L26) -> 9000 | M27: =SUM(M24:M26) -> 125000

Sheet 03-TIR
B1: © Escola de Imóveis - www.escoladeimoveis.com.br | Siga no instagram e tenha o melhor conteúdo: @escoladeimoveis
B2: É terminantemente proibida a utilização, acesso, cópia ou divulgação não autorizada das informações presentes nesta planilha.
B3: ATENÇÃO: SOMENTE ALTERAR AS CÉLULAS ROXAS COM A ESCRITA FAÇA VOCÊ
B5: Taxa Interna de Retorno (TIR ou IRR)
B7: Ex 1.0 | C7: Faça Você | D7: Resposta | G7: 2020 | H7: 2021 | I7: 2022 | J7: 2023 | K7: 2025 | L7: 2026 | M7: 2027
B8: Custo de Capital | D8: 0.06 | F8: Investimento | G8: -100000
B9: VPL | D9: {=NPV(D8,H11:M11)+G11} -> 90165.351 | F9: Renda | H9: 10000 | I9: 10000 | J9: 10000 | K9: 10000 | L9: 10000 | M9: 10000
B10: TIR | D10: =IRR(G11:M11) -> 0.20056308 | F10: Venda | M10: 200000
G11: =SUM(G8:G10) -> -100000 | H11: =SUM(H8:H10) -> 10000 | I11: =SUM(I8:I10) -> 10000 | J11: =SUM(J8:J10) -> 10000 | K11: =SUM(K8:K10) -> 10000 | L11: =SUM(L8:L10) -> 10000 | M11: =SUM(M8:M10) -> 210000
B15: Ex 2.0 | C15: Faça Você | D15: Resposta | G15: 2020 | H15: 2021 | I15: 2022 | J15: 2023 | K15: 2025 | L15: 2026 | M15: 2027
B16: Custo de Capital | D16: 0.08 | F16: Investimento | G16: -235000
B17: VPL | D17: {=NPV(D16,H19:M19)+G19} -> -4744.4971 | F17: Renda | H17: 8000 | I17: 9000 | J17: 10000 | K17: 11000 | L17: 12000 | M17: 13000
B18: TIR | D18: =IRR(G19:M19) -> 0.076001586 | F18: Venda | M18: 290000
G19: =SUM(G16:G18) -> -235000 | H19: =SUM(H16:H18) -> 8000 | I19: =SUM(I16:I18) -> 9000 | J19: =SUM(J16:J18) -> 10000 | K19: =SUM(K16:K18) -> 11000 | L19: =SUM(L16:L18) -> 12000 | M19: =SUM(M16:M18) -> 303000
B23: Ex 2.0 | C23: Faça Você | D23: Resposta | G23: 2020 | H23: 2021 | I23: 2022 | J23: 2023 | K23: 2025 | L23: 2026 | M23: 2027
B24: Custo de Capital | D24: 0.095 | F24: Investimento | G24: -90000
B25: VPL | D25: {=NPV(D24,H27:M27)+G27} -> 7519.4105 | F25: Renda | H25: 5000 | I25: 5500 | J25: 6000 | K25: 8000 | L25: 9000 | M25: 10000
B26: TIR | D26: =IRR(G27:M27) -> 0.11187053 | F26: Venda | M26: 115000
G27: =SUM(G24:G26) -> -90000 | H27: =SUM(H24:H26) -> 5000 | I27: =SUM(I24:I26) -> 5500 | J27: =SUM(J24:J26) -> 6000 | K27: =SUM(K24:K26) -> 8000 | L27: =SUM(L24:L26) -> 9000 | M27: =SUM(M24:M26) -> 125000

Sheet 03.1-TIRxVPL
B1: © Escola de Imóveis - www.escoladeimoveis.com.br | Siga no instagram e tenha o melhor conteúdo: @escoladeimoveis
B2: É terminantemente proibida a utilização, acesso, cópia ou divulgação não autorizada das informações presentes nesta planilha.
B3: ATENÇÃO: SOMENTE ALTERAR AS CÉLULAS ROXAS COM A ESCRITA FAÇA VOCÊ
B5: Diferença TIR e VPL
B7: Ex 1.0 | C7: Resposta | F7: 2020 | G7: 2021 | H7: 2022 | I7: 2023 | J7: 2025 | K7: 2026 | L7: 2027
B8: Custo de Capital | C8: 0.06 | E8: Investimento | F8: -50000
B9: VPL | C9: {=NPV(C8,G11:L11)+F11} -> 73599.829 | E9: Renda | G9: 25000 | H9: 0 | I9: 5000 | J9: 5000 | K9: 5000 | L9: 0
B10: TIR | C10: =IRR(F11:L11) -> 0.30336361 | E10: Venda | L10: 125000
B11: Receita Total | C11: =SUM(G11:L11) -> 165000 | F11: =SUM(F8:F10) -> -50000 | G11: =SUM(G8:G10) -> 25000 | H11: =SUM(H8:H10) -> 0 | I11: =SUM(I8:I10) -> 5000 | J11: =SUM(J8:J10) -> 5000 | K11: =SUM(K8:K10) -> 5000 | L11: =SUM(L8:L10) -> 125000
B15: Ex 2.0 | C15: Resposta | F15: 2020 | G15: 2021 | H15: 2022 | I15: 2023 | J15: 2025 | K15: 2026 | L15: 2027
B16: Custo de Capital | C16: 0.06 | E16: Investimento | F16: -50000
B17: VPL | C17: {=NPV(C16,G19:L19)+F19} -> 67203.271 | E17: Renda | G17: 0 | H17: 0 | I17: 5000 | J17: 0 | K17: 5000 | L17: 0
B18: TIR | C18: =IRR(F19:L19) -> 0.22668805 | E18: Venda | L18: 155000
B19: Receita Total | C19: =SUM(G19:L19) -> 165000 | F19: =SUM(F16:F18) -> -50000 | G19: =SUM(G16:G18) -> 0 | H19: =SUM(H16:H18) -> 0 | I19: =SUM(I16:I18) -> 5000 | J19: =SUM(J16:J18) -> 0 | K19: =SUM(K16:K18) -> 5000 | L19: =SUM(L16:L18) -> 155000
B23: Ex 3.0 | C23: Resposta | F23: 2020 | G23: 2021 | H23: 2022 | I23: 2023 | J23: 2025 | K23: 2026 | L23: 2027
B24: Custo de Capital | C24: 0.06 | E24: Investimento | F24: -20000
B25: VPL | C25: {=NPV(C24,G27:L27)+F27} -> 27338.1 | E25: Renda | G25: 0 | H25: 0 | I25: 0 | J25: 0 | K25: 0 | L25: 0
B26: TIR | C26: =IRR(F27:L27) -> 0.22368416 | E26: Venda | L26: 67150
B27: Receita Total | C27: =SUM(G27:L27) -> 67150 | F27: =SUM(F24:F26) -> -20000 | G27: =SUM(G24:G26) -> 0 | H27: =SUM(H24:H26) -> 0 | I27: =SUM(I24:I26) -> 0 | J27: =SUM(J24:J26) -> 0 | K27: =SUM(K24:K26) -> 0 | L27: =SUM(L24:L26) -> 67150
B31: Ex 4.0 | C31: Resposta | F31: 2020 | G31: 2021 | H31: 2022 | I31: 2023 | J31: 2025 | K31: 2026 | L31: 2027
B32: Custo de Capital | C32: 0.06 | E32: Investimento | F32: -20000
B33: VPL | C33: {=NPV(C32,G35:L35)+F35} -> 17293.311 | E33: Renda | G33: 4000 | H33: 4000 | I33: 4000 | J33: 4000 | K33: 4000 | L33: 4000
B34: TIR | C34: =IRR(F35:L35) -> 0.22371844 | E34: Venda | L34: 25000
B35: Receita Total | C35: =SUM(G35:L35) -> 49000 | F35: =SUM(F32:F34) -> -20000 | G35: =SUM(G32:G34) -> 4000 | H35: =SUM(H32:H34) -> 4000 | I35: =SUM(I32:I34) -> 4000 | J35: =SUM(J32:J34) -> 4000 | K35: =SUM(K32:K34) -> 4000 | L35: =SUM(L32:L34) -> 29000

Sheet 04-ROI
B1: © Escola de Imóveis - www.escoladeimoveis.com.br | Siga no instagram e tenha o melhor conteúdo: @escoladeimoveis
B2: É terminantemente proibida a utilização, acesso, cópia ou divulgação não autorizada das informações presentes nesta planilha.
B3: ATENÇÃO: SOMENTE ALTERAR AS CÉLULAS ROXAS COM A ESCRITA FAÇA VOCÊ
B5: Retorno sobre o Investimento (ROI) e Múltiplo
B7: Ex 1.0 | C7: Faça Você | D7: Resposta | G7: 2020 | H7: 2021 | I7: 2022 | J7: 2023 | K7: 2025 | L7: 2026 | M7: 2027
B8: Custo de Capital | D8: 0.06 | F8: Investimento | G8: -100000
B9: VPL | D9: {=NPV(D8,H11:M11)+G11} -> 90165.351 | F9: Renda | H9: 10000 | I9: 10000 | J9: 10000 | K9: 10000 | L9: 10000 | M9: 10000
B10: TIR | D10: =IRR(G11:M11) -> 0.20056308 | F10: Venda | M10: 200000
B11: ROI | D11: =(SUM(H11:M11)+G11)/-G11 -> 1.6 | G11: =SUM(G8:G10) -> -100000 | H11: =SUM(H8:H10) -> 10000 | I11: =SUM(I8:I10) -> 10000 | J11: =SUM(J8:J10) -> 10000 | K11: =SUM(K8:K10) -> 10000 | L11: =SUM(L8:L10) -> 10000 | M11: =SUM(M8:M10) -> 210000
B12: Múltiplo | D12: =SUM(H11:M11)/-G11 -> 2.6
B15: Ex 2.0 | C15: Faça Você | D15: Resposta | G15: 2020 | H15: 2021 | I15: 2022 | J15: 2023 | K15: 2025 | L15: 2026 | M15: 2027
B16: Custo de Capital | D16: 0.08 | F16: Investimento | G16: -235000
B17: VPL | D17: {=NPV(D16,H19:M19)+G19} -> -4744.4971 | F17: Renda | H17: 8000 | I17: 9000 | J17: 10000 | K17: 11000 | L17: 12000 | M17: 13000
B18: TIR | D18: =IRR(G19:M19) -> 0.076001586 | F18: Venda | M18: 290000
B19: ROI | D19: =(SUM(H19:M19)+G19)/-G19 -> 0.50212766 | G19: =SUM(G16:G18) -> -235000 | H19: =SUM(H16:H18) -> 8000 | I19: =SUM(I16:I18) -> 9000 | J19: =SUM(J16:J18) -> 10000 | K19: =SUM(K16:K18) -> 11000 | L19: =SUM(L16:L18) -> 12000 | M19: =SUM(M16:M18) -> 303000
B20: Múltiplo | D20: =SUM(H19:M19)/-G19 -> 1.5021277
B23: Ex 2.0 | C23: Faça Você | D23: Resposta | G23: 2020 | H23: 2021 | I23: 2022 | J23: 2023 | K23: 2025 | L23: 2026 | M23: 2027
B24: Custo de Capital | D24: 0.095 | F24: Investimento | G24: -90000
B25: VPL | D25: {=NPV(D24,H27:M27)+G27} -> 7519.4105 | F25: Renda | H25: 5000 | I25: 5500 | J25: 6000 | K25: 8000 | L25: 9000 | M25: 10000
B26: TIR | D26: =IRR(G27:M27) -> 0.11187053 | F26: Venda | M26: 115000
B27: ROI | D27: =(SUM(H27:M27)+G27)/-G27 -> 0.76111111 | G27: =SUM(G24:G26) -> -90000 | H27: =SUM(H24:H26) -> 5000 | I27: =SUM(I24:I26) -> 5500 | J27: =SUM(J24:J26) -> 6000 | K27: =SUM(K24:K26) -> 8000 | L27: =SUM(L24:L26) -> 9000 | M27: =SUM(M24:M26) -> 125000
B28: Múltiplo | D28: =SUM(H27:M27)/-G27 -> 1.7611111

Sheet 05-Payback
B1: © Escola de Imóveis - www.escoladeimoveis.com.br | Siga no instagram e tenha o melhor conteúdo: @escoladeimoveis
B2: É terminantemente proibida a utilização, acesso, cópia ou divulgação não autorizada das informações presentes nesta planilha.
B3: ATENÇÃO: SOMENTE ALTERAR AS CÉLULAS ROXAS COM A ESCRITA FAÇA VOCÊ
B5: Payback
B7: Ex 1.0 | C7: Faça Você | D7: Resposta | G7: 2020 | H7: 2021 | I7: 2022 | J7: 2023 | K7: 2025 | L7: 2026 | M7: 2027
B8: Payback 1 | D8: 4 | F8: Investimento | G8: -100000
F9: Renda | H9: 25000 | I9: 25000 | J9: 25000 | K9: 25000 | L9: 0 | M9: 0
F10: Venda | M10: 200000
G11: =SUM(G8:G10) -> -100000 | H11: =SUM(H8:H10) -> 25000 | I11: =SUM(I8:I10) -> 25000 | J11: =SUM(J8:J10) -> 25000 | K11: =SUM(K8:K10) -> 25000 | L11: =SUM(L8:L10) -> 0 | M11: =SUM(M8:M10) -> 200000
F12: Payback Saldo | H12: =G11+H11 -> -75000 | I12: =H12+I11 -> -50000 | J12: =I12+J11 -> -25000 | K12: =J12+K11 -> 0 | L12: =K12+L11 -> 0
G13: 0 | H13: 1 | I13: 2 | J13: 3 | K13: 4 | L13: 5
B16: Ex 2.0 | C16: Faça Você | D16: Resposta | G16: 2020 | H16: 2021 | I16: 2022 | J16: 2023 | K16: 2025 | L16: 2026 | M16: 2027
B17: Payback | D17: =J22+(-J21/K20) -> 3.3333333 | F17: Investimento | G17: -60000
F18: Renda | H18: 20000 | I18: 20000 | J18: 15000 | K18: 15000 | L18: 15000 | M18: 15000
F19: Venda | M19: 80000
G20: =SUM(G17:G19) -> -60000 | H20: =SUM(H17:H19) -> 20000 | I20: =SUM(I17:I19) -> 20000 | J20: =SUM(J17:J19) -> 15000 | K20: =SUM(K17:K19) -> 15000 | L20: =SUM(L17:L19) -> 15000 | M20: =SUM(M17:M19) -> 95000
F21: Payback Saldo | H21: =G20+H20 -> -40000 | I21: =H21+I20 -> -20000 | J21: =I21+J20 -> -5000 | K21: =J21+K20 -> 10000 | L21: =K21+L20 -> 25000
G22: 0 | H22: 1 | I22: 2 | J22: 3 | K22: 4 | L22: 5
B25: Ex 3.0 | C25: Faça Você | D25: Resposta | G25: 2020 | H25: 2021 | I25: 2022 | J25: 2023 | K25: 2025 | L25: 2026 | M25: 2027
B26: Payback | D26: =K31+(-K30/L29) -> 4.2857143 | F26: Investimento | G26: -90000
F27: Renda | H27: 16000 | I27: 16000 | J27: 24000 | K27: 26000 | L27: 28000 | M27: 10000
F28: Venda | M28: 115000
G29: =SUM(G26:G28) -> -90000 | H29: =SUM(H26:H28) -> 16000 | I29: =SUM(I26:I28) -> 16000 | J29: =SUM(J26:J28) -> 24000 | K29: =SUM(K26:K28) -> 26000 | L29: =SUM(L26:L28) -> 28000 | M29: =SUM(M26:M28) -> 125000
F30: Payback Saldo | H30: =G29+H29 -> -74000 | I30: =H30+I29 -> -58000 | J30: =I30+J29 -> -34000 | K30: =J30+K29 -> -8000 | L30: =K30+L29 -> 20000
G31: 0 | H31: 1 | I31: 2 | J31: 3 | K31: 4 | L31: 5

Sheet 06-CAPYield
B1: © Escola de Imóveis - www.escoladeimoveis.com.br | Siga no instagram e tenha o melhor conteúdo: @escoladeimoveis
B2: É terminantemente proibida a utilização, acesso, cópia ou divulgação não autorizada das informações presentes nesta planilha.
B3: ATENÇÃO: SOMENTE ALTERAR AS CÉLULAS ROXAS COM A ESCRITA FAÇA VOCÊ
B5: CAP & Yield
B7: Ex 1.0 | C7: Faça Você | D7: Resposta | G7: 2020 | H7: 2021 | I7: 2022 | J7: 2023 | K7: 2025 | L7: 2026 | M7: 2027
B8: CAP 2021 | D8: =H10/-G8 -> 0.1 | F8: À Vista | G8: -100000
B9: Yield 2021 Ala | D9: =(H10-H11)/-G9 -> 0.06 | F9: Alavancado | G9: -50000
B10: Yield Médio Ala | D10: =AVERAGE(G14:M14) -> 0.1 | F10: Renda | G10: 10000 | H10: 10000 | I10: 10000 | J10: 10000 | K10: 10000 | L10: 10000 | M10: 10000
F11: Financiamento | G11: 8000 | H11: 7000 | I11: 6000 | J11: 5000 | K11: 4000 | L11: 3000 | M11: 2000
F13: Cap Rate | G13: =G10/(-$G$8) -> 0.1 | H13: =H10/(-$G$8) -> 0.1 | I13: =I10/(-$G$8) -> 0.1 | J13: =J10/(-$G$8) -> 0.1 | K13: =K10/(-$G$8) -> 0.1 | L13: =L10/(-$G$8) -> 0.1 | M13: =M10/(-$G$8) -> 0.1
F14: Yield Ala | G14: =(G10-G11)/-$G$9 -> 0.04 | H14: =(H10-H11)/-$G$9 -> 0.06 | I14: =(I10-I11)/-$G$9 -> 0.08 | J14: =(J10-J11)/-$G$9 -> 0.1 | K14: =(K10-K11)/-$G$9 -> 0.12 | L14: =(L10-L11)/-$G$9 -> 0.14 | M14: =(M10-M11)/-$G$9 -> 0.16
B17: Ex 2.0 | C17: Faça Você | D17: Resposta | G17: 2020 | H17: 2021 | I17: 2022 | J17: 2023 | K17: 2025 | L17: 2026 | M17: 2027
B18: CAP 2021 | D18: =H20/-G18 -> 0.053333333 | F18: À Vista | G18: -150000
B19: Yield 2021 Ala | D19: =(H20-H21)/-G19 -> 0.025 | F19: Alavancado | G19: -100000
B20: Yield Médio Ala | D20: =AVERAGE(G24:M24) -> 0.056428571 | F20: Renda | G20: 8000 | H20: 8000 | I20: 9000 | J20: 10000 | K20: 11000 | L20: 12000 | M20: 13000
F21: Financiamento | G21: 6000 | H21: 5500 | I21: 5000 | J21: 4500 | K21: 4000 | L21: 3500 | M21: 3000
F23: Cap Rate | G23: =G20/(-$G$18) -> 0.053333333 | H23: =H20/(-$G$18) -> 0.053333333 | I23: =I20/(-$G$18) -> 0.06 | J23: =J20/(-$G$18) -> 0.066666667 | K23: =K20/(-$G$18) -> 0.073333333 | L23: =L20/(-$G$18) -> 0.08 | M23: =M20/(-$G$18) -> 0.086666667
F24: Yield Ala | G24: =(G20-G21)/-$G$19 -> 0.02 | H24: =(H20-H21)/-$G$19 -> 0.025 | I24: =(I20-I21)/-$G$19 -> 0.04 | J24: =(J20-J21)/-$G$19 -> 0.055 | K24: =(K20-K21)/-$G$19 -> 0.07 | L24: =(L20-L21)/-$G$19 -> 0.085 | M24: =(M20-M21)/-$G$19 -> 0.1
B27: Ex 2.0 | C27: Faça Você | D27: Resposta | G27: 2020 | H27: 2021 | I27: 2022 | J27: 2023 | K27: 2025 | L27: 2026 | M27: 2027
B28: CAP 2021 | D28: =H30/-G28 -> 0.04137931 | F28: À Vista | G28: -290000
B29: Yield 2021 Ala | D29: =(H30-H31)/-G29 -> 0.12142857 | F29: Alavancado | G29: -70000
B30: Yield Médio Ala | D30: =AVERAGE(G34:M34) -> 0.10510204 | F30: Renda | G30: 12000 | H30: 12000 | I30: 14000 | J30: 13000 | K30: 14000 | L30: 16000 | M30: 17000
F31: Financiamento | G31: 2500 | H31: 3500 | I31: 4500 | J31: 6500 | K31: 8000 | L31: 9500 | M31: 12000
F33: Cap Rate | G33: =G30/(-$G$28) -> 0.04137931 | H33: =H30/(-$G$28) -> 0.04137931 | I33: =I30/(-$G$28) -> 0.048275862 | J33: =J30/(-$G$28) -> 0.044827586 | K33: =K30/(-$G$28) -> 0.048275862 | L33: =L30/(-$G$28) -> 0.055172414 | M33: =M30/(-$G$28) -> 0.05862069
F34: Yield Ala | G34: =(G30-G31)/-$G$29 -> 0.13571429 | H34: =(H30-H31)/-$G$29 -> 0.12142857 | I34: =(I30-I31)/-$G$29 -> 0.13571429 | J34: =(J30-J31)/-$G$29 -> 0.092857143 | K34: =(K30-K31)/-$G$29 -> 0.085714286 | L34: =(L30-L31)/-$G$29 -> 0.092857143 | M34: =(M30-M31)/-$G$29 -> 0.071428571

Sheet 08-SAC
B1: © Escola de Imóveis - www.escoladeimoveis.com.br | Siga no instagram e tenha o melhor conteúdo: @escoladeimoveis
B2: É terminantemente proibida a utilização, acesso, cópia ou divulgação não autorizada das informações presentes nesta planilha.
B3: ATENÇÃO: SOMENTE ALTERAR AS CÉLULAS ROXAS COM A ESCRITA FAÇA VOCÊ
B5: SAC | E5: Faça Você | G5: Faça Você
D6: Valor Imóvel | E6: 200000 | F6: LTV | G6: 0.8 | M6: Juros Devidos | N6: =D431 -> 203592.87
M7: Principal Devido | N7: =F431 -> 160000
B8: Empréstimo | C8: =E6*G6 -> 160000 | D8: Nº Parcelas | E8: 420 | F8: Taxa Anual | G8: 0.075 | H8: Taxa Mensal | I8: =(1+G8)^(1/12)-1 -> 0.006044919 | J8: Renda Min. | K8: =G11/0.3 -> 4493.7981 | M8: Total Devido | N8: =G431 -> 363592.87
B10: Parcela | C10: Saldo Inicial | D10: Juros | E10: Saldo Atualizado | F10: Amortização | G10: Prestação | H10: Saldo Devedor
A11: =IF(AND(E8>0,E8<421),1,0) -> 1 | B11: =IF(A11>0,1,0) -> 1 | C11: =IF(B11>0,C8,0) -> 160000 | D11: =IF(B11>0,C11*$I$8,0) -> 967.18704 | E11: =IF(B11>0,C11+D11,0) -> 160967.19 | F11: =IF($E$8>0,$C$8/$E$8,0) -> 380.95238 | G11: =IF(B11>0,D11+F11,0) -> 1348.1394 | H11: =IF(B11>0,E11-G11,0) -> 159619.05
B12: =IF(AND(B11>0,B11<$E$8),B11+1,0) -> 2 | C12: =IF(B12>0,H11,0) -> 159619.05 | D12: =IF(B12>0,C12*$I$8,0) -> 964.88422 | E12: =IF(B12>0,C12+D12,0) -> 160583.93 | F12: =IF(B12>0,$C$8/$E$8,0) -> 380.95238 | G12: =IF(B12>0,D12+F12,0) -> 1345.8366 | H12: =IF(B12>0,E12-G12,0) -> 159238.1
B13: =IF(AND(B12>0,B12<$E$8),B12+1,0) -> 3 | C13: =IF(B13>0,H12,0) -> 159238.1 | D13: =IF(B13>0,C13*$I$8,0) -> 962.58139 | E13: =IF(B13>0,C13+D13,0) -> 160200.68 | F13: =IF(B13>0,$C$8/$E$8,0) -> 380.95238 | G13: =IF(B13>0,D13+F13,0) -> 1343.5338 | H13: =IF(B13>0,E13-G13,0) -> 158857.14
B14: =IF(AND(B13>0,B13<$E$8),B13+1,0) -> 4 | C14: =IF(B14>0,H13,0) -> 158857.14 | D14: =IF(B14>0,C14*$I$8,0) -> 960.27857 | E14: =IF(B14>0,C14+D14,0) -> 159817.42 | F14: =IF(B14>0,$C$8/$E$8,0) -> 380.95238 | G14: =IF(B14>0,D14+F14,0) -> 1341.2309 | H14: =IF(B14>0,E14-G14,0) -> 158476.19
B15: =IF(AND(B14>0,B14<$E$8),B14+1,0) -> 5 | C15: =IF(B15>0,H14,0) -> 158476.19 | D15: =IF(B15>0,C15*$I$8,0) -> 957.97574 | E15: =IF(B15>0,C15+D15,0) -> 159434.17 | F15: =IF(B15>0,$C$8/$E$8,0) -> 380.95238 | G15: =IF(B15>0,D15+F15,0) -> 1338.9281 | H15: =IF(B15>0,E15-G15,0) -> 158095.24
B16: =IF(AND(B15>0,B15<$E$8),B15+1,0) -> 6 | C16: =IF(B16>0,H15,0) -> 158095.24 | D16: =IF(B16>0,C16*$I$8,0) -> 955.67291 | E16: =IF(B16>0,C16+D16,0) -> 159050.91 | F16: =IF(B16>0,$C$8/$E$8,0) -> 380.95238 | G16: =IF(B16>0,D16+F16,0) -> 1336.6253 | H16: =IF(B16>0,E16-G16,0) -> 157714.29
B17: =IF(AND(B16>0,B16<$E$8),B16+1,0) -> 7 | C17: =IF(B17>0,H16,0) -> 157714.29 | D17: =IF(B17>0,C17*$I$8,0) -> 953.37009 | E17: =IF(B17>0,C17+D17,0) -> 158667.66 | F17: =IF(B17>0,$C$8/$E$8,0) -> 380.95238 | G17: =IF(B17>0,D17+F17,0) -> 1334.3225 | H17: =IF(B17>0,E17-G17,0) -> 157333.33
B18: =IF(AND(B17>0,B17<$E$8),B17+1,0) -> 8 | C18: =IF(B18>0,H17,0) -> 157333.33 | D18: =IF(B18>0,C18*$I$8,0) -> 951.06726 | E18: =IF(B18>0,C18+D18,0) -> 158284.4 | F18: =IF(B18>0,$C$8/$E$8,0) -> 380.95238 | G18: =IF(B18>0,D18+F18,0) -> 1332.0196 | H18: =IF(B18>0,E18-G18,0) -> 156952.38
B19: =IF(AND(B18>0,B18<$E$8),B18+1,0) -> 9 | C19: =IF(B19>0,H18,0) -> 156952.38 | D19: =IF(B19>0,C19*$I$8,0) -> 948.76443 | E19: =IF(B19>0,C19+D19,0) -> 157901.15 | F19: =IF(B19>0,$C$8/$E$8,0) -> 380.95238 | G19: =IF(B19>0,D19+F19,0) -> 1329.7168 | H19: =IF(B19>0,E19-G19,0) -> 156571.43
B20: =IF(AND(B19>0,B19<$E$8),B19+1,0) -> 10 | C20: =IF(B20>0,H19,0) -> 156571.43 | D20: =IF(B20>0,C20*$I$8,0) -> 946.46161 | E20: =IF(B20>0,C20+D20,0) -> 157517.89 | F20: =IF(B20>0,$C$8/$E$8,0) -> 380.95238 | G20: =IF(B20>0,D20+F20,0) -> 1327.414 | H20: =IF(B20>0,E20-G20,0) -> 156190.48
B21: =IF(AND(B20>0,B20<$E$8),B20+1,0) -> 11 | C21: =IF(B21>0,H20,0) -> 156190.48 | D21: =IF(B21>0,C21*$I$8,0) -> 944.15878 | E21: =IF(B21>0,C21+D21,0) -> 157134.63 | F21: =IF(B21>0,$C$8/$E$8,0) -> 380.95238 | G21: =IF(B21>0,D21+F21,0) -> 1325.1112 | H21: =IF(B21>0,E21-G21,0) -> 155809.52
B22: =IF(AND(B21>0,B21<$E$8),B21+1,0) -> 12 | C22: =IF(B22>0,H21,0) -> 155809.52 | D22: =IF(B22>0,C22*$I$8,0) -> 941.85595 | E22: =IF(B22>0,C22+D22,0) -> 156751.38 | F22: =IF(B22>0,$C$8/$E$8,0) -> 380.95238 | G22: =IF(B22>0,D22+F22,0) -> 1322.8083 | H22: =IF(B22>0,E22-G22,0) -> 155428.57
B23: =IF(AND(B22>0,B22<$E$8),B22+1,0) -> 13 | C23: =IF(B23>0,H22,0) -> 155428.57 | D23: =IF(B23>0,C23*$I$8,0) -> 939.55313 | E23: =IF(B23>0,C23+D23,0) -> 156368.12 | F23: =IF(B23>0,$C$8/$E$8,0) -> 380.95238 | G23: =IF(B23>0,D23+F23,0) -> 1320.5055 | H23: =IF(B23>0,E23-G23,0) -> 155047.62
... B430: =IF(AND(B429>0,B429<$E$8),B429+1,0) -> 420 | C430: =IF(B430>0,H429,0) -> 380.95238 | D430: =IF(B430>0,C430*$I$8,0) -> 2.3028263 | E430: =IF(B430>0,C430+D430,0) -> 383.25521 | F430: =IF(B430>0,$C$8/$E$8,0) -> 380.95238 | G430: =IF(B430>0,D430+F430,0) -> 383.25521 | H430: =IF(B430>0,E430-G430,0) -> -9.7998054e-11
D431: =SUM(D11:D430) -> 203592.87 | F431: =SUM(F11:F430) -> 160000 | G431: =SUM(G11:G430) -> 363592.87

Sheet 09-PRICE
B1: © Escola de Imóveis - www.escoladeimoveis.com.br | Siga no instagram e tenha o melhor conteúdo: @escoladeimoveis
B2: É terminantemente proibida a utilização, acesso, cópia ou divulgação não autorizada das informações presentes nesta planilha.
B3: ATENÇÃO: SOMENTE ALTERAR AS CÉLULAS ROXAS COM A ESCRITA FAÇA VOCÊ
B5: PRICE | E5: Faça Você | G5: Faça Você
D6: Valor Imóvel | E6: 200000 | F6: LTV | G6: 0.8 | M6: Juros Devidos | N6: =D431 -> 281331.63
M7: Principal Devido | N7: =F431 -> 160000
B8: Empréstimo | C8: =E6*G6 -> 160000 | D8: Nº Parcelas | E8: 420 | F8: Taxa Anual | G8: 0.075 | H8: Taxa Mensal | I8: =(1+G8)^(1/12)-1 -> 0.006044919 | J8: Renda Min. | K8: =G11/0.3 -> 3502.632 | M8: Total Devido | N8: =G431 -> 441331.63
B10: Parcela | C10: Saldo Inicial | D10: Juros | E10: Saldo Atualizado | F10: Amortização | G10: Prestação | H10: Saldo Devedor
A11: =IF(AND(E8>0,E8<421),1,0) -> 1 | B11: =IF(A11>0,1,0) -> 1 | C11: =IF(B11>0,C8,0) -> 160000 | D11: =IF(B11>0,C11*$I$8,0) -> 967.18704 | E11: =IF(B11>0,C11+D11,0) -> 160967.19 | F11: =IF($E$8>0,G11-D11,0) -> 83.602548 | G11: =IF(B11>0,-PMT($I$8,$E$8,$C$8),0) -> 1050.7896 | H11: =IF(B11>0,E11-G11,0) -> 159916.4
B12: =IF(AND(B11>0,B11<$E$8),B11+1,0) -> 2 | C12: =IF(B12>0,H11,0) -> 159916.4 | D12: =IF(B12>0,C12*$I$8,0) -> 966.68167 | E12: =IF(B12>0,C12+D12,0) -> 160883.08 | F12: =IF($E$8>0,G12-D12,0) -> 84.107919 | G12: =IF(B12>0,G11,0) -> 1050.7896 | H12: =IF(B12>0,E12-G12,0) -> 159832.29
B13: =IF(AND(B12>0,B12<$E$8),B12+1,0) -> 3 | C13: =IF(B13>0,H12,0) -> 159832.29 | D13: =IF(B13>0,C13*$I$8,0) -> 966.17325 | E13: =IF(B13>0,C13+D13,0) -> 160798.46 | F13: =IF($E$8>0,G13-D13,0) -> 84.616344 | G13: =IF(B13>0,G12,0) -> 1050.7896 | H13: =IF(B13>0,E13-G13,0) -> 159747.67
B14: =IF(AND(B13>0,B13<$E$8),B13+1,0) -> 4 | C14: =IF(B14>0,H13,0) -> 159747.67 | D14: =IF(B14>0,C14*$I$8,0) -> 965.66175 | E14: =IF(B14>0,C14+D14,0) -> 160713.33 | F14: =IF($E$8>0,G14-D14,0) -> 85.127843 | G14: =IF(B14>0,G13,0) -> 1050.7896 | H14: =IF(B14>0,E14-G14,0) -> 159662.55
B15: =IF(AND(B14>0,B14<$E$8),B14+1,0) -> 5 | C15: =IF(B15>0,H14,0) -> 159662.55 | D15: =IF(B15>0,C15*$I$8,0) -> 965.14716 | E15: =IF(B15>0,C15+D15,0) -> 160627.69 | F15: =IF($E$8>0,G15-D15,0) -> 85.642434 | G15: =IF(B15>0,G14,0) -> 1050.7896 | H15: =IF(B15>0,E15-G15,0) -> 159576.9
B16: =IF(AND(B15>0,B15<$E$8),B15+1,0) -> 6 | C16: =IF(B16>0,H15,0) -> 159576.9 | D16: =IF(B16>0,C16*$I$8,0) -> 964.62946 | E16: =IF(B16>0,C16+D16,0) -> 160541.53 | F16: =IF($E$8>0,G16-D16,0) -> 86.160136 | G16: =IF(B16>0,G15,0) -> 1050.7896 | H16: =IF(B16>0,E16-G16,0) -> 159490.74
B17: =IF(AND(B16>0,B16<$E$8),B16+1,0) -> 7 | C17: =IF(B17>0,H16,0) -> 159490.74 | D17: =IF(B17>0,C17*$I$8,0) -> 964.10863 | E17: =IF(B17>0,C17+D17,0) -> 160454.85 | F17: =IF($E$8>0,G17-D17,0) -> 86.680967 | G17: =IF(B17>0,G16,0) -> 1050.7896 | H17: =IF(B17>0,E17-G17,0) -> 159404.06
B18: =IF(AND(B17>0,B17<$E$8),B17+1,0) -> 8 | C18: =IF(B18>0,H17,0) -> 159404.06 | D18: =IF(B18>0,C18*$I$8,0) -> 963.58465 | E18: =IF(B18>0,C18+D18,0) -> 160367.65 | F18: =IF($E$8>0,G18-D18,0) -> 87.204946 | G18: =IF(B18>0,G17,0) -> 1050.7896 | H18: =IF(B18>0,E18-G18,0) -> 159316.86
B19: =IF(AND(B18>0,B18<$E$8),B18+1,0) -> 9 | C19: =IF(B19>0,H18,0) -> 159316.86 | D19: =IF(B19>0,C19*$I$8,0) -> 963.0575 | E19: =IF(B19>0,C19+D19,0) -> 160279.91 | F19: =IF($E$8>0,G19-D19,0) -> 87.732093 | G19: =IF(B19>0,G18,0) -> 1050.7896 | H19: =IF(B19>0,E19-G19,0) -> 159229.12
B20: =IF(AND(B19>0,B19<$E$8),B19+1,0) -> 10 | C20: =IF(B20>0,H19,0) -> 159229.12 | D20: =IF(B20>0,C20*$I$8,0) -> 962.52717 | E20: =IF(B20>0,C20+D20,0) -> 160191.65 | F20: =IF($E$8>0,G20-D20,0) -> 88.262426 | G20: =IF(B20>0,G19,0) -> 1050.7896 | H20: =IF(B20>0,E20-G20,0) -> 159140.86
B21: =IF(AND(B20>0,B20<$E$8),B20+1,0) -> 11 | C21: =IF(B21>0,H20,0) -> 159140.86 | D21: =IF(B21>0,C21*$I$8,0) -> 961.99363 | E21: =IF(B21>0,C21+D21,0) -> 160102.86 | F21: =IF($E$8>0,G21-D21,0) -> 88.795966 | G21: =IF(B21>0,G20,0) -> 1050.7896 | H21: =IF(B21>0,E21-G21,0) -> 159052.07
B22: =IF(AND(B21>0,B21<$E$8),B21+1,0) -> 12 | C22: =IF(B22>0,H21,0) -> 159052.07 | D22: =IF(B22>0,C22*$I$8,0) -> 961.45686 | E22: =IF(B22>0,C22+D22,0) -> 160013.52 | F22: =IF($E$8>0,G22-D22,0) -> 89.33273 | G22: =IF(B22>0,G21,0) -> 1050.7896 | H22: =IF(B22>0,E22-G22,0) -> 158962.73
B23: =IF(AND(B22>0,B22<$E$8),B22+1,0) -> 13 | C23: =IF(B23>0,H22,0) -> 158962.73 | D23: =IF(B23>0,C23*$I$8,0) -> 960.91685 | E23: =IF(B23>0,C23+D23,0) -> 159923.65 | F23: =IF($E$8>0,G23-D23,0) -> 89.872739 | G23: =IF(B23>0,G22,0) -> 1050.7896 | H23: =IF(B23>0,E23-G23,0) -> 158872.86
... B430: =IF(AND(B429>0,B429<$E$8),B429+1,0) -> 420 | C430: =IF(B430>0,H429,0) -> 1044.4758 | D430: =IF(B430>0,C430*$I$8,0) -> 6.3137718 | E430: =IF(B430>0,C430+D430,0) -> 1050.7896 | F430: =IF($E$8>0,G430-D430,0) -> 1044.4758 | G430: =IF(B430>0,G429,0) -> 1050.7896 | H430: =IF(B430>0,E430-G430,0) -> -4.7866706e-09
D431: =SUM(D11:D430) -> 281331.63 | F431: =SUM(F11:F430) -> 160000 | G431: =SUM(G11:G430) -> 441331.63

Sheet 10-Pesquisa Compra
B1: © Escola de Imóveis - www.escoladeimoveis.com.br | Siga no instagram e tenha o melhor conteúdo: @escoladeimoveis
B2: É terminantemente proibida a utilização, acesso, cópia ou divulgação não autorizada das informações presentes nesta planilha.
B3: ATENÇÃO: SOMENTE ALTERAR AS CÉLULAS ROXAS COM A ESCRITA FAÇA VOCÊ
B5: Pesquisa de Mercado Compra
C7: Faça Você | E7: Faça Você | G7: FI | H7: Faça Você | K7: Faça Você | T7: *Ajustar o custo do piso de acordo com o tamanho médio das comparações
B8: Custo Médio | C8: =AVERAGE(AV:AV) -> 309007.5 | D8: M² Médio | E8: =AVERAGE(AT:AT) -> 9633.547 | F8: FIPEZAP - São Paulo | H8: 9242 | I8: SECOVI - Novos República | K8: 9784.16 | T8: Estimativa Custo Adicional Studio
T9: =100*R12 -> 2600 | U9: 4500 | V9: 500 | W9: 1500 | X9: 500 | Y9: 2500 | Z9: 8000 | AA9: 1000 | AB9: 1000 | AC9: 1000
B10: Endereço | H10: Configuração do Apartamento | T10: Características do Apartamento | AD10: Característicad do Condomínio | AM10: Características Financeiras do Imóvel
B11: Av/Rua | C11: Número | D11: Bairro | E11: Metrô | F11: Condomínio | G11: Link | H11: Dormitórios | I11: Banheiros | J11: Suíte | K11: Vaga | L11: Andar | M11: Posição | N11: Vista | O11: Visual | P11: Aspecto | Q11: Ano | R11: M² Privativo | S11: Parede | T11: Piso | U11: Sacada | V11: Box | W11: Chuveiro | X11: Persiana | Y11: Ar Condicionado | Z11: Mar. Cozinha | AA11: Mar. Banheiro | AB11: Mar. Quarto | AC11: Cooktop | AD11: Portaria | AE11: Lavanderia | AF11: Academia | AG11: Salão de Festas | AH11: Coworking | AI11: Piscina | AJ11: Pet Place | AK11: Bicicletário | AL11: Rooftop | AM11: Condomínio | AN11: Cond/M² | AO11: IPTU Mês | AP11: Compra | AQ11: Cartório | AR11: M² Compra | AS11: Adicional | AT11: M² Total | AU11: Var M² Total | AV11: Custo Total
A12: 1 | B12: Av Duque de Caxias | C12: 61 | D12: Centro | E12: 100m | F12: Smart Santa Cecília | H12: 0 | I12: 1 | J12: 0 | K12: 0 | L12: 4 | M12: Norte | N12: Lateral | O12: Livre | P12: Decorado | Q12: 2018 | R12: 26 | S12: Drywall | T12: Porcelanato | U12: Aberta | V12: Vidro | W12: Gás Individual | X12: Interna | Y12: Quarto/Sala | Z12: Sim | AA12: Sim | AB12: Sim | AC12: Não tem | AD12: 24h | AE12: Industrial | AF12: Simples | AG12: Gourmet | AH12: Pequeno | AI12: Externa | AJ12: Sim | AK12: Com bicicletas | AL12: Sim | AM12: 308 | AN12: =IF(R12<>0,AM12/R12,"") -> 11.846154 | AO12: 55 | AP12: 273000 | AQ12: =IF(R12<>0,5.5%*AP12,"") -> 15015 | AR12: =IFERROR(AP12/R12,"") -> 10500 | AS12: =IF(AC12="Não tem",$AC$9)+IF(AB12="Não tem",$AB$9)+IF(AA12="Não tem",$AA$9)+IF(Z12="Não tem",$Z$9)+IF(Y12="Não tem",$Y$9)+IF(X12="Não tem",$X$9)+IF(W12="Não tem",$W$9)+IF(V12="Não tem",$V$9)+IF(U12="Aberta",$U$9)+IF(T12="Contrapiso",$T$9) -> 5500 | AT12: =IF(R12<>0,(AP12+AS12)/R12,0) -> 10711.538 | AU12: =IF(R12<>0,(AT12/AVERAGE(AT:AT))-100%,"") -> 0.11189974 | AV12: =IF(R12<>0,AP12+AQ12+AS12,0) -> 293515
A13: 2 | B13: Rua dos Timbiras | C13: 395 | D13: Centro | E13: 500m | F13: SP New Home | G13: https://www.quintoandar.com.br/imovel/893047060/comprar?search_rank=%7B%22sortMode%22%3A%22relevance%22%2C%22searchMode%22%3A%22list%22%2C%22resultsOrigin%22%3A%22search%22%2C%22rank%22%3A23%2C%22personalization%22%3Atrue%7D&search_id=%22fa0112d01cae11ebaa36ea959c5fd97d%22&from_route=%22search_results%22 | H13: 1 | I13: 1 | J13: 1 | K13: 1 | L13: 10 | M13: Oeste | N13: Frente | O13: Livre | P13: Novo | Q13: 2017 | R13: 36 | S13: Drywall | T13: Porcelanato | U13: Aberta | V13: Vidro | W13: Gás Individual | X13: Embutida Janela | Y13: Não tem | Z13: Sim | AA13: Sim | AB13: Sim | AC13: Não tem | AD13: 24h | AE13: Industrial | AF13: Completa | AG13: Churrasqueira | AH13: Não tem | AI13: Interna | AJ13: Não tem | AK13: Não tem | AL13: Não tem | AM13: 520 | AN13: =IF(R13<>0,AM13/R13,"") -> 14.444444 | AO13: 84 | AP13: 300000 | AQ13: =IF(R13<>0,5.5%*AP13,"") -> 16500 | AR13: =IFERROR(AP13/R13,"") -> 8333.3333 | AS13: =IF(AC13="Não tem",$AC$9)+IF(AB13="Não tem",$AB$9)+IF(AA13="Não tem",$AA$9)+IF(Z13="Não tem",$Z$9)+IF(Y13="Não tem",$Y$9)+IF(X13="Não tem",$X$9)+IF(W13="Não tem",$W$9)+IF(V13="Não tem",$V$9)+IF(U13="Aberta",$U$9)+IF(T13="Contrapiso",$T$9) -> 8000 | AT13: =IF(R13<>0,(AP13+AS13)/R13,"") -> 8555.5556 | AU13: =IF(R13<>0,(AT13/AVERAGE(AT:AT))-100%,"") -> -0.11189974 | AV13: =IF(R13<>0,AP13+AQ13+AS13,"") -> 324500
A14: 3 | AN14: =IF(R14<>0,AM14/R14,"") | AQ14: =IF(R14<>0,5.5%*AP14,"") | AR14: =IFERROR(AP14/R14,"") | AS14: =IF(AC14="Não tem",$AC$9)+IF(AB14="Não tem",$AB$9)+IF(AA14="Não tem",$AA$9)+IF(Z14="Não tem",$Z$9)+IF(Y14="Não tem",$Y$9)+IF(X14="Não tem",$X$9)+IF(W14="Não tem",$W$9)+IF(V14="Não tem",$V$9)+IF(U14="Aberta",$U$9)+IF(T14="Contrapiso",$T$9) -> 0 | AT14: =IF(R14<>0,(AP14+AS14)/R14,"") | AU14: =IF(R14<>0,(AT14/AVERAGE(AT:AT))-100%,"") | AV14: =IF(R14<>0,AP14+AQ14+AS14,"")
A15: 4 | AN15: =IF(R15<>0,AM15/R15,"") | AQ15: =IF(R15<>0,5.5%*AP15,"") | AR15: =IFERROR(AP15/R15,"") | AS15: =IF(AC15="Não tem",$AC$9)+IF(AB15="Não tem",$AB$9)+IF(AA15="Não tem",$AA$9)+IF(Z15="Não tem",$Z$9)+IF(Y15="Não tem",$Y$9)+IF(X15="Não tem",$X$9)+IF(W15="Não tem",$W$9)+IF(V15="Não tem",$V$9)+IF(U15="Aberta",$U$9)+IF(T15="Contrapiso",$T$9) -> 0 | AT15: =IF(R15<>0,(AP15+AS15)/R15,"") | AU15: =IF(R15<>0,(AT15/AVERAGE(AT:AT))-100%,"") | AV15: =IF(R15<>0,AP15+AQ15+AS15,"")
A16: 5 | AN16: =IF(R16<>0,AM16/R16,"") | AQ16: =IF(R16<>0,5.5%*AP16,"") | AR16: =IFERROR(AP16/R16,"") | AS16: =IF(AC16="Não tem",$AC$9)+IF(AB16="Não tem",$AB$9)+IF(AA16="Não tem",$AA$9)+IF(Z16="Não tem",$Z$9)+IF(Y16="Não tem",$Y$9)+IF(X16="Não tem",$X$9)+IF(W16="Não tem",$W$9)+IF(V16="Não tem",$V$9)+IF(U16="Aberta",$U$9)+IF(T16="Contrapiso",$T$9) -> 0 | AT16: =IF(R16<>0,(AP16+AS16)/R16,"") | AU16: =IF(R16<>0,(AT16/AVERAGE(AT:AT))-100%,"") | AV16: =IF(R16<>0,AP16+AQ16+AS16,"")
A17: 6 | AN17: =IF(R17<>0,AM17/R17,"") | AQ17: =IF(R17<>0,5.5%*AP17,"") | AR17: =IFERROR(AP17/R17,"") | AS17: =IF(AC17="Não tem",$AC$9)+IF(AB17="Não tem",$AB$9)+IF(AA17="Não tem",$AA$9)+IF(Z17="Não tem",$Z$9)+IF(Y17="Não tem",$Y$9)+IF(X17="Não tem",$X$9)+IF(W17="Não tem",$W$9)+IF(V17="Não tem",$V$9)+IF(U17="Aberta",$U$9)+IF(T17="Contrapiso",$T$9) -> 0 | AT17: =IF(R17<>0,(AP17+AS17)/R17,"") | AU17: =IF(R17<>0,(AT17/AVERAGE(AT:AT))-100%,"") | AV17: =IF(R17<>0,AP17+AQ17+AS17,"")
A18: 7 | AN18: =IF(R18<>0,AM18/R18,"") | AQ18: =IF(R18<>0,5.5%*AP18,"") | AR18: =IFERROR(AP18/R18,"") | AS18: =IF(AC18="Não tem",$AC$9)+IF(AB18="Não tem",$AB$9)+IF(AA18="Não tem",$AA$9)+IF(Z18="Não tem",$Z$9)+IF(Y18="Não tem",$Y$9)+IF(X18="Não tem",$X$9)+IF(W18="Não tem",$W$9)+IF(V18="Não tem",$V$9)+IF(U18="Aberta",$U$9)+IF(T18="Contrapiso",$T$9) -> 0 | AT18: =IF(R18<>0,(AP18+AS18)/R18,"") | AU18: =IF(R18<>0,(AT18/AVERAGE(AT:AT))-100%,"") | AV18: =IF(R18<>0,AP18+AQ18+AS18,"")
A19: 8 | AN19: =IF(R19<>0,AM19/R19,"") | AQ19: =IF(R19<>0,5.5%*AP19,"") | AR19: =IFERROR(AP19/R19,"") | AS19: =IF(AC19="Não tem",$AC$9)+IF(AB19="Não tem",$AB$9)+IF(AA19="Não tem",$AA$9)+IF(Z19="Não tem",$Z$9)+IF(Y19="Não tem",$Y$9)+IF(X19="Não tem",$X$9)+IF(W19="Não tem",$W$9)+IF(V19="Não tem",$V$9)+IF(U19="Aberta",$U$9)+IF(T19="Contrapiso",$T$9) -> 0 | AT19: =IF(R19<>0,(AP19+AS19)/R19,"") | AU19: =IF(R19<>0,(AT19/AVERAGE(AT:AT))-100%,"") | AV19: =IF(R19<>0,AP19+AQ19+AS19,"")
A20: 9 | AN20: =IF(R20<>0,AM20/R20,"") | AQ20: =IF(R20<>0,5.5%*AP20,"") | AR20: =IFERROR(AP20/R20,"") | AS20: =IF(AC20="Não tem",$AC$9)+IF(AB20="Não tem",$AB$9)+IF(AA20="Não tem",$AA$9)+IF(Z20="Não tem",$Z$9)+IF(Y20="Não tem",$Y$9)+IF(X20="Não tem",$X$9)+IF(W20="Não tem",$W$9)+IF(V20="Não tem",$V$9)+IF(U20="Aberta",$U$9)+IF(T20="Contrapiso",$T$9) -> 0 | AT20: =IF(R20<>0,(AP20+AS20)/R20,"") | AU20: =IF(R20<>0,(AT20/AVERAGE(AT:AT))-100%,"") | AV20: =IF(R20<>0,AP20+AQ20+AS20,"")
A21: 10 | AN21: =IF(R21<>0,AM21/R21,"") | AQ21: =IF(R21<>0,5.5%*AP21,"") | AR21: =IFERROR(AP21/R21,"") | AS21: =IF(AC21="Não tem",$AC$9)+IF(AB21="Não tem",$AB$9)+IF(AA21="Não tem",$AA$9)+IF(Z21="Não tem",$Z$9)+IF(Y21="Não tem",$Y$9)+IF(X21="Não tem",$X$9)+IF(W21="Não tem",$W$9)+IF(V21="Não tem",$V$9)+IF(U21="Aberta",$U$9)+IF(T21="Contrapiso",$T$9) -> 0 | AT21: =IF(R21<>0,(AP21+AS21)/R21,"") | AU21: =IF(R21<>0,(AT21/AVERAGE(AT:AT))-100%,"") | AV21: =IF(R21<>0,AP21+AQ21+AS21,"")
A22: 11 | AN22: =IF(R22<>0,AM22/R22,"") | AQ22: =IF(R22<>0,5.5%*AP22,"") | AR22: =IFERROR(AP22/R22,"") | AS22: =IF(AC22="Não tem",$AC$9)+IF(AB22="Não tem",$AB$9)+IF(AA22="Não tem",$AA$9)+IF(Z22="Não tem",$Z$9)+IF(Y22="Não tem",$Y$9)+IF(X22="Não tem",$X$9)+IF(W22="Não tem",$W$9)+IF(V22="Não tem",$V$9)+IF(U22="Aberta",$U$9)+IF(T22="Contrapiso",$T$9) -> 0 | AT22: =IF(R22<>0,(AP22+AS22)/R22,"") | AU22: =IF(R22<>0,(AT22/AVERAGE(AT:AT))-100%,"") | AV22: =IF(R22<>0,AP22+AQ22+AS22,"")
A23: 12 | AN23: =IF(R23<>0,AM23/R23,"") | AQ23: =IF(R23<>0,5.5%*AP23,"") | AR23: =IFERROR(AP23/R23,"") | AS23: =IF(AC23="Não tem",$AC$9)+IF(AB23="Não tem",$AB$9)+IF(AA23="Não tem",$AA$9)+IF(Z23="Não tem",$Z$9)+IF(Y23="Não tem",$Y$9)+IF(X23="Não tem",$X$9)+IF(W23="Não tem",$W$9)+IF(V23="Não tem",$V$9)+IF(U23="Aberta",$U$9)+IF(T23="Contrapiso",$T$9) -> 0 | AT23: =IF(R23<>0,(AP23+AS23)/R23,"") | AU23: =IF(R23<>0,(AT23/AVERAGE(AT:AT))-100%,"") | AV23: =IF(R23<>0,AP23+AQ23+AS23,"")
A24: 13 | AN24: =IF(R24<>0,AM24/R24,"") | AQ24: =IF(R24<>0,5.5%*AP24,"") | AR24: =IFERROR(AP24/R24,"") | AS24: =IF(AC24="Não tem",$AC$9)+IF(AB24="Não tem",$AB$9)+IF(AA24="Não tem",$AA$9)+IF(Z24="Não tem",$Z$9)+IF(Y24="Não tem",$Y$9)+IF(X24="Não tem",$X$9)+IF(W24="Não tem",$W$9)+IF(V24="Não tem",$V$9)+IF(U24="Aberta",$U$9)+IF(T24="Contrapiso",$T$9) -> 0 | AT24: =IF(R24<>0,(AP24+AS24)/R24,"") | AU24: =IF(R24<>0,(AT24/AVERAGE(AT:AT))-100%,"") | AV24: =IF(R24<>0,AP24+AQ24+AS24,"")
A25: 14 | AN25: =IF(R25<>0,AM25/R25,"") | AQ25: =IF(R25<>0,5.5%*AP25,"") | AR25: =IFERROR(AP25/R25,"") | AS25: =IF(AC25="Não tem",$AC$9)+IF(AB25="Não tem",$AB$9)+IF(AA25="Não tem",$AA$9)+IF(Z25="Não tem",$Z$9)+IF(Y25="Não tem",$Y$9)+IF(X25="Não tem",$X$9)+IF(W25="Não tem",$W$9)+IF(V25="Não tem",$V$9)+IF(U25="Aberta",$U$9)+IF(T25="Contrapiso",$T$9) -> 0 | AT25: =IF(R25<>0,(AP25+AS25)/R25,"") | AU25: =IF(R25<>0,(AT25/AVERAGE(AT:AT))-100%,"") | AV25: =IF(R25<>0,AP25+AQ25+AS25,"")
... A41: 30 | AN41: =IF(R41<>0,AM41/R41,"") | AQ41: =IF(R41<>0,5.5%*AP41,"") | AR41: =IFERROR(AP41/R41,"") | AS41: =IF(AC41="Não tem",$AC$9)+IF(AB41="Não tem",$AB$9)+IF(AA41="Não tem",$AA$9)+IF(Z41="Não tem",$Z$9)+IF(Y41="Não tem",$Y$9)+IF(X41="Não tem",$X$9)+IF(W41="Não tem",$W$9)+IF(V41="Não tem",$V$9)+IF(U41="Aberta",$U$9)+IF(T41="Contrapiso",$T$9) -> 0 | AT41: =IF(R41<>0,(AP41+AS41)/R41,"") | AU41: =IF(R41<>0,(AT41/AVERAGE(AT:AT))-100%,"") | AV41: =IF(R41<>0,AP41+AQ41+AS41,"")

Sheet 10.1-Pesquisa Locação
B1: © Escola de Imóveis - www.escoladeimoveis.com.br | Siga no instagram e tenha o melhor conteúdo: @escoladeimoveis
B2: É terminantemente proibida a utilização, acesso, cópia ou divulgação não autorizada das informações presentes nesta planilha.
B3: ATENÇÃO: SOMENTE ALTERAR AS CÉLULAS ROXAS COM A ESCRITA FAÇA VOCÊ
B5: Pesquisa de Mercado Compra
C7: Faça Você | E7: Faça Você | G7: FI | H7: Faça Você
B8: Pacote Médio | C8: =AVERAGE(AS:AS) -> 2263 | D8: M² Pacote | E8: =AVERAGE(AU:AU) -> 87.038462 | F8: Índice Comparativo | T8: Estimativa Custo Adicional Studio
T9: =100*R12 -> 2600 | U9: 4500 | V9: 500 | W9: 1500 | X9: 500 | Y9: 2500 | Z9: 8000 | AA9: 1000 | AB9: 1000 | AC9: 1000
B10: Endereço | H10: Configuração do Apartamento | T10: Características do Apartamento | AD10: Característicad do Condomínio | AM10: Características Financeiras do Imóvel
B11: Av/Rua | C11: Número | D11: Bairro | E11: Metrô | F11: Condomínio | G11: Link | H11: Dormitórios | I11: Banheiros | J11: Suíte | K11: Vaga | L11: Andar | M11: Posição | N11: Vista | O11: Visual | P11: Aspecto | Q11: Ano Construção | R11: M² Privativo | S11: Parede | T11: Piso | U11: Sacada | V11: Box | W11: Chuveiro | X11: Persiana | Y11: Ar Condicionado | Z11: Mar. Cozinha | AA11: Mar. Banheiro | AB11: Mar. Quarto | AC11: Cooktop | AD11: Portaria | AE11: Lavanderia | AF11: Academia | AG11: Salão de Festas | AH11: Coworking | AI11: Piscina | AJ11: Pet Place | AK11: Bicicletário | AL11: Rooftop | AM11: Condomínio | AN11: Cond/M² | AO11: IPTU Mês | AP11: Seguro | AQ11: Locação | AR11: M² Locação | AS11: Pacote | AT11: Var Pacote | AU11: M² Pacote | AV11: Var M² Pacote
A12: 1 | B12: Av Duque de Caxias | C12: 61 | D12: Centro | E12: 100m | F12: Smart Santa Cecília | H12: 0 | I12: 1 | J12: 0 | K12: 0 | L12: 4 | M12: Norte | N12: Lateral | O12: Livre | P12: Novo | Q12: 2018 | R12: 26 | S12: Drywall | T12: Porcelanato | U12: Aberta | V12: Vidro | W12: Gás Individual | X12: Interna | Y12: Quarto/Sala | Z12: Sim | AA12: Sim | AB12: Sim | AC12: Não tem | AD12: 24h | AE12: Industrial | AF12: Simples | AG12: Gourmet | AH12: Pequeno | AI12: Externa | AJ12: Sim | AK12: Com bicicletas | AL12: Sim | AM12: 308 | AN12: =IF(R12<>0,AM12/R12,"") -> 11.846154 | AO12: 55 | AP12: =IF(R12<>0,1.3%*AQ12,"") -> 24.7 | AQ12: 1900 | AR12: =IF(R12<>0,AQ12/R12,"") -> 73.076923 | AS12: =IF(R12<>0,AM12+AO12+AQ12,"") -> 2263 | AT12: =IF(R12<>0,(AS12/AVERAGE(AS:AS))-100%,"") -> 0 | AU12: =IF(R12<>0,AS12/R12,"") -> 87.038462 | AV12: =IF(R12<>0,(AU12/AVERAGE(AU:AU))-100%,"") -> 0
A13: 2 | AN13: =IF(R13<>0,AM13/R13,"") | AP13: =IF(R13<>0,1.3%*AQ13,"") | AR13: =IF(R13<>0,AQ13/R13,"") | AS13: =IF(R13<>0,AM13+AO13+AQ13,"") | AT13: =IF(R13<>0,(AS13/AVERAGE(AS:AS))-100%,"") | AU13: =IF(R13<>0,AS13/R13,"") | AV13: =IF(R13<>0,(AU13/AVERAGE(AU:AU))-100%,"")
A14: 3 | AN14: =IF(R14<>0,AM14/R14,"") | AP14: =IF(R14<>0,1.3%*AQ14,"") | AR14: =IF(R14<>0,AQ14/R14,"") | AS14: =IF(R14<>0,AM14+AO14+AQ14,"") | AT14: =IF(R14<>0,(AS14/AVERAGE(AS:AS))-100%,"") | AU14: =IF(R14<>0,AS14/R14,"") | AV14: =IF(R14<>0,(AU14/AVERAGE(AU:AU))-100%,"")
A15: 4 | AN15: =IF(R15<>0,AM15/R15,"") | AP15: =IF(R15<>0,1.3%*AQ15,"") | AR15: =IF(R15<>0,AQ15/R15,"") | AS15: =IF(R15<>0,AM15+AO15+AQ15,"") | AT15: =IF(R15<>0,(AS15/AVERAGE(AS:AS))-100%,"") | AU15: =IF(R15<>0,AS15/R15,"") | AV15: =IF(R15<>0,(AU15/AVERAGE(AU:AU))-100%,"")
A16: 5 | AN16: =IF(R16<>0,AM16/R16,"") | AP16: =IF(R16<>0,1.3%*AQ16,"") | AR16: =IF(R16<>0,AQ16/R16,"") | AS16: =IF(R16<>0,AM16+AO16+AQ16,"") | AT16: =IF(R16<>0,(AS16/AVERAGE(AS:AS))-100%,"") | AU16: =IF(R16<>0,AS16/R16,"") | AV16: =IF(R16<>0,(AU16/AVERAGE(AU:AU))-100%,"")
A17: 6 | AN17: =IF(R17<>0,AM17/R17,"") | AP17: =IF(R17<>0,1.3%*AQ17,"") | AR17: =IF(R17<>0,AQ17/R17,"") | AS17: =IF(R17<>0,AM17+AO17+AQ17,"") | AT17: =IF(R17<>0,(AS17/AVERAGE(AS:AS))-100%,"") | AU17: =IF(R17<>0,AS17/R17,"") | AV17: =IF(R17<>0,(AU17/AVERAGE(AU:AU))-100%,"")
A18: 7 | AN18: =IF(R18<>0,AM18/R18,"") | AP18: =IF(R18<>0,1.3%*AQ18,"") | AR18: =IF(R18<>0,AQ18/R18,"") | AS18: =IF(R18<>0,AM18+AO18+AQ18,"") | AT18: =IF(R18<>0,(AS18/AVERAGE(AS:AS))-100%,"") | AU18: =IF(R18<>0,AS18/R18,"") | AV18: =IF(R18<>0,(AU18/AVERAGE(AU:AU))-100%,"")
A19: 8 | AN19: =IF(R19<>0,AM19/R19,"") | AP19: =IF(R19<>0,1.3%*AQ19,"") | AR19: =IF(R19<>0,AQ19/R19,"") | AS19: =IF(R19<>0,AM19+AO19+AQ19,"") | AT19: =IF(R19<>0,(AS19/AVERAGE(AS:AS))-100%,"") | AU19: =IF(R19<>0,AS19/R19,"") | AV19: =IF(R19<>0,(AU19/AVERAGE(AU:AU))-100%,"")
A20: 9 | AN20: =IF(R20<>0,AM20/R20,"") | AP20: =IF(R20<>0,1.3%*AQ20,"") | AR20: =IF(R20<>0,AQ20/R20,"") | AS20: =IF(R20<>0,AM20+AO20+AQ20,"") | AT20: =IF(R20<>0,(AS20/AVERAGE(AS:AS))-100%,"") | AU20: =IF(R20<>0,AS20/R20,"") | AV20: =IF(R20<>0,(AU20/AVERAGE(AU:AU))-100%,"")
A21: 10 | AN21: =IF(R21<>0,AM21/R21,"") | AP21: =IF(R21<>0,1.3%*AQ21,"") | AR21: =IF(R21<>0,AQ21/R21,"") | AS21: =IF(R21<>0,AM21+AO21+AQ21,"") | AT21: =IF(R21<>0,(AS21/AVERAGE(AS:AS))-100%,"") | AU21: =IF(R21<>0,AS21/R21,"") | AV21: =IF(R21<>0,(AU21/AVERAGE(AU:AU))-100%,"")
A22: 11 | AN22: =IF(R22<>0,AM22/R22,"") | AP22: =IF(R22<>0,1.3%*AQ22,"") | AR22: =IF(R22<>0,AQ22/R22,"") | AS22: =IF(R22<>0,AM22+AO22+AQ22,"") | AT22: =IF(R22<>0,(AS22/AVERAGE(AS:AS))-100%,"") | AU22: =IF(R22<>0,AS22/R22,"") | AV22: =IF(R22<>0,(AU22/AVERAGE(AU:AU))-100%,"")
A23: 12 | AN23: =IF(R23<>0,AM23/R23,"") | AP23: =IF(R23<>0,1.3%*AQ23,"") | AR23: =IF(R23<>0,AQ23/R23,"") | AS23: =IF(R23<>0,AM23+AO23+AQ23,"") | AT23: =IF(R23<>0,(AS23/AVERAGE(AS:AS))-100%,"") | AU23: =IF(R23<>0,AS23/R23,"") | AV23: =IF(R23<>0,(AU23/AVERAGE(AU:AU))-100%,"")
A24: 13 | AN24: =IF(R24<>0,AM24/R24,"") | AP24: =IF(R24<>0,1.3%*AQ24,"") | AR24: =IF(R24<>0,AQ24/R24,"") | AS24: =IF(R24<>0,AM24+AO24+AQ24,"") | AT24: =IF(R24<>0,(AS24/AVERAGE(AS:AS))-100%,"") | AU24: =IF(R24<>0,AS24/R24,"") | AV24: =IF(R24<>0,(AU24/AVERAGE(AU:AU))-100%,"")
... A41: 30 | AN41: =IF(R41<>0,AM41/R41,"") | AP41: =IF(R41<>0,1.3%*AQ41,"") | AR41: =IF(R41<>0,AQ41/R41,"") | AS41: =IF(R41<>0,AM41+AO41+AQ41,"") | AT41: =IF(R41<>0,(AS41/AVERAGE(AS:AS))-100%,"") | AU41: =IF(R41<>0,AS41/R41,"") | AV41: =IF(R41<>0,(AU41/AVERAGE(AU:AU))-100%,"")

Sheet 11-Viabilidade
B1: © Escola de Imóveis - www.escoladeimoveis.com.br | Siga no instagram e tenha o melhor conteúdo: @escoladeimoveis | J1: 11/12/2022 - V2-2.1 - Ajustado erro do ponto e virgula dos números de seleção.
B2: É terminantemente proibida a utilização, acesso, cópia ou divulgação não autorizada das informações presentes nesta planilha. | J2: 14/02/2024 - V2-2.2 - Adicionado campos para cáculo de aluguel de Airbnb
B3: ATENÇÃO: SOMENTE ALTERAR AS CÉLULAS ROXAS COM A ESCRITA FAÇA VOCÊ | J3: 15/02/2024 - V2-2.3 - Ajustado erro na fórmula de vacância.
B5: Viabilidade
B7: Premissas de Compra (Pronto) | F7: Premissas de Compra (Planta) | J7: Premissas de Locação e Operação | N7: Premissas de Venda e Mercado
C9: Faça Você | G9: Faça Você | K9: Faça Você | O9: Faça Você
B10: Valor Imóvel | C10: 300000 | F10: Compra planta? | G10: Não | J10: Aluguel | K10: 3000 | N10: Inflação Aluguel | O10: 0.05 | P10: =(1+O10)^(1/12)-1 -> 0.0040741238
B11: LTV | C11: 0.8 | F11: Prazo Obra | G11: 12 | J11: Vacância Mês | K11: 2 | L11: =((K11*K10)/K13)+((K16+K17)*K11)/K13 -> 392.22222 | N11: Valorização Imóvel | O11: 0.05
B12: Taxa Anual | C12: 0.1 | F12: INCC | G12: 0.04 | H12: =(1+G12)^(1/12)-1 -> 0.0032737398 | J12: Corretagem | K12: 1 | L12: =K12/K13 -> 0.055555556 | N12: Reforma 10º Ano | O12: 0
B13: Tamanho (m²) | C13: 25 | F13: Pagamento Obra | G13: =IF(G10="Sim",C15,0) -> 0 | J13: Tempo Contrato | K13: 18 | N13: Comissão Venda | O13: 0
B14: Empréstimo | C14: =IF($G$10="Não",$C$10*$C$11,((($C$10*$C$11)*(1+$G$12)^(($G$11+1)/12)))) -> 240000 | F14: Entrada | G14: =G13*G19 -> 0 | J14: Adm Mensal | K14: 0 | N14: Saída (Ano) | O14: 15 | P14: =O14*12 -> 180
B15: Entrada | C15: =C10*(100%-C11) -> 60000 | F15: 1ª Parcela Mensal | G15: =(G20*G13)/G11 -> 0 | J15: Fundo Reparos | K15: 0.05 | N15: Custo Capital | O15: 0.1
F16: Chaves | G16: =G13*G21 -> 0 | J16: IPTU | K16: 80 | N16: IR Renda | O16: 0.15
J17: Condomínio | K17: 450 | N17: IR Venda | O17: 0
C18: Faça Você | G18: Faça Você
B19: ITBI | C19: 0.03 | D19: =C19*C10 -> 9000 | F19: Entrada | G19: 0.1 | J19: Para Airbnb (Usar para calcular aluguel)
B20: Escritura | C20: 0 | D20: =C20*C10 -> 0 | F20: Parcelas Obra | G20: 0.8
B21: Registro | C21: 0.02 | D21: =C21*C10 -> 6000 | F21: Chaves | G21: 0.1 | K21: Faça Você
B22: Avaliação | C22: 1500 | F22: Total (100%) | G22: =SUM(G19:G21) -> 1 | J22: Diária Média | K22: 150 | W22: Comparador de Cenários (Teste as variações do modelo)
B23: Reforma Inicial | C23: 50000 | F23: *Para calcular certo a parcela de chaves não pode ser 0% | J23: Ocupação Média | K23: 0.85 | L23: =K23*30 -> 25.5 | W23: Mto. Pessimista | X23: Pessimista | Y23: Normal | Z23: Otimista | AA23: Mto. otimista
B24: Prazo Reforma | C24: 6 | J24: Administrador | K24: 0.15 | W24: Cenário A | X24: Cenário B | Y24: Cenário C | Z24: Cenário D | AA24: Cenário E
B25: Custo Alavancado | C25: =C15+D19+D21+C22+C23 -> 126500 | J25: Luz/Gás | K25: 100 | V25: Valor Imóvel
B26: Custo Total | C26: =C10+D19+D20+D21+C23 -> 365000 | J26: Internet | K26: 100 | V26: LTV
B27: Custo m² Compra | C27: =(C14+C15)/C13 -> 12000 | J27: Outros | K27: 0 | V27: INCC
B28: Custo m² Total | C28: =(C23+D21+D20+D19+C15+C14)/C13 -> 14600 | J28: IPTU | K28: =K16 -> 80 | V28: Aluguel
J29: Condomínio | K29: =K17 -> 450 | V29: Vacância Mês
J30: Aluguel Airbnb | K30: =(((K22*L23)*(100%-K24))-(K25+K26+K27+K28+K29)) -> 2521.25 | V30: Corretagem
B31: Imóvel Pronto | J31: Limpeza foi considerada paga com a taxa de limpeza | V31: Adm Mensal
C32: Faça Você | D32: Faça Você
C33: Valor de Mercado | D33: 0 | E33: 0 | F33: 0 | G33: 0 | H33: 0 | I33: 0 | J33: 0 | K33: 0 | L33: 0 | M33: 0 | N33: 0 | O33: 0 | P33: 0 | Q33: 0
C34: =$C$10+$C$23 -> 350000 | D34: =IF(D33<C34,(C34+(C34*$O$11)),D33) -> 367500 | E34: =IF(E33<D34,(D34+(D34*$O$11)),E33) -> 385875 | F34: =IF(F33<E34,(E34+(E34*$O$11)),F33) -> 405168.75 | G34: =IF(G33<F34,(F34+(F34*$O$11)),G33) -> 425427.19 | H34: =IF(H33<G34,(G34+(G34*$O$11)),H33) -> 446698.55 | I34: =IF(I33<H34,(H34+(H34*$O$11)),I33) -> 469033.47 | J34: =IF(J33<I34,(I34+(I34*$O$11)),J33) -> 492485.15 | K34: =IF(K33<J34,(J34+(J34*$O$11)),K33) -> 517109.41 | ... Q34: =IF(Q33<P34,(P34+(P34*$O$11)),Q33) -> 692976.06
B35: À Vista | C35: 1º Ano | D35: 2º Ano | E35: 3º Ano | F35: 4º Ano | G35: 5º Ano | H35: 6º Ano | I35: 7º Ano | J35: 8º Ano | K35: 9º Ano | L35: 10º Ano | M35: 11º Ano | N35: 12º Ano | O35: 13º Ano | P35: 14º Ano | Q35: 15º Ano | S35: Indicadores À Vista
B36: Investimento | C36: =-($D$19+$D$20+$D$21+$C$10+$C$23) -> -365000 | S36: TIR | T36: =IRR(C39:Q39) -> 0.11387441 | V36: TIR
B37: Renda | C37: =IF($O$14>=1,SUM('11.1 - Auxiliar Viabilidade'!$M$8:$M$19),0) -> 7979.7934 | D37: =IF($O$14>=2,SUM('11.1 - Auxiliar Viabilidade'!$M$20:$M$31),0) -> 23153.169 | E37: =IF($O$14>=3,SUM('11.1 - Auxiliar Viabilidade'!$M$32:$M$43),0) -> 24310.827 | F37: =IF($O$14>=4,SUM('11.1 - Auxiliar Viabilidade'!$M$44:$M$55),0) -> 25526.368 | G37: =IF($O$14>=5,SUM('11.1 - Auxiliar Viabilidade'!$M$56:$M$67),0) -> 26802.687 | H37: =IF($O$14>=6,SUM('11.1 - Auxiliar Viabilidade'!$M$68:$M$79),0) -> 28142.821 | I37: =IF($O$14>=7,SUM('11.1 - Auxiliar Viabilidade'!$M$80:$M$91),0) -> 29549.962 | J37: =IF($O$14>=8,SUM('11.1 - Auxiliar Viabilidade'!$M$92:$M$103),0) -> 31027.46 | K37: =IF($O$14>=9,SUM('11.1 - Auxiliar Viabilidade'!$M$104:$M$115),0) -> 32578.833 | L37: =IF($O$14>=10,SUM('11.1 - Auxiliar Viabilidade'!$M$116:$M$127)-$O$12,0) -> 34207.775 | M37: =IF($O$14>=11,SUM('11.1 - Auxiliar Viabilidade'!$M$128:$M$139),0) -> 35918.164 | N37: =IF($O$14>=12,SUM('11.1 - Auxiliar Viabilidade'!$M$140:$M$151),0) -> 37714.072 | O37: =IF($O$14>=13,SUM('11.1 - Auxiliar Viabilidade'!$M$152:$M$163),0) -> 39599.775 | P37: =IF($O$14>=14,SUM('11.1 - Auxiliar Viabilidade'!$M$164:$M$175),0) -> 41579.764 | Q37: =IF($O$14>=15,SUM('11.1 - Auxiliar Viabilidade'!$M$176:$M$187),0) -> 43658.752 | S37: ROI | T37: =((SUM(D39:Q39)+C39)/-C39) -> 2.2119932 | V37: ROI
B38: Venda | C38: =IF($O$14=1,C34-((C34*$O$13)+$O$17*(C34-$C$10)),0) -> 0 | D38: =IF($O$14=2,D34-((D34*$O$13)+$O$17*(D34-$C$10)),0) -> 0 | E38: =IF($O$14=3,E34-((E34*$O$13)+$O$17*(E34-$C$10)),0) -> 0 | F38: =IF($O$14=4,F34-((F34*$O$13)+$O$17*(F34-$C$10)),0) -> 0 | G38: =IF($O$14=5,G34-((G34*$O$13)+$O$17*(G34-$C$10)),0) -> 0 | H38: =IF($O$14=6,H34-((H34*$O$13)+$O$17*(H34-$C$10)),0) -> 0 | I38: =IF($O$14=7,I34-((I34*$O$13)+$O$17*(I34-$C$10)),0) -> 0 | J38: =IF($O$14=8,J34-((J34*$O$13)+$O$17*(J34-$C$10)),0) -> 0 | K38: =IF($O$14=9,K34-((K34*$O$13)+$O$17*(K34-$C$10)),0) -> 0 | L38: =IF($O$14=10,L34-((L34*$O$13)+$O$17*(L34-$C$10)),0) -> 0 | M38: =IF($O$14=11,M34-((M34*$O$13)+$O$17*(M34-$C$10)),0) -> 0 | N38: =IF($O$14=12,N34-((N34*$O$13)+$O$17*(N34-$C$10)),0) -> 0 | O38: =IF($O$14=13,O34-((O34*$O$13)+$O$17*(O34-$C$10)),0) -> 0 | P38: =IF($O$14=14,P34-((P34*$O$13)+$O$17*(P34-$C$10)),0) -> 0 | Q38: =IF($O$14=15,$Q$34-(($Q$34*$O$13)+$O$17*($Q$34-$C$10)),0) -> 692976.06 | S38: Multiplo | T38: =SUM(D39:Q39)/-C39 -> 3.2119932 | V38: Multiplo
B39: Fluxo | C39: =SUM(C36:C38) -> -357020.21 | D39: =SUM(D36:D38) -> 23153.169 | E39: =SUM(E36:E38) -> 24310.827 | F39: =SUM(F36:F38) -> 25526.368 | G39: =SUM(G36:G38) -> 26802.687 | H39: =SUM(H36:H38) -> 28142.821 | I39: =SUM(I36:I38) -> 29549.962 | J39: =SUM(J36:J38) -> 31027.46 | ... Q39: =SUM(Q36:Q38) -> 736634.81 | S39: VPL | T39: {=NPV($O$15,D39:Q39)+C39} -> 47094.424 | V39: VPL
B40: Yield | C40: =C37/-$C$36 -> 0.021862448 | D40: =IF($C$37<0,-D37/$C$39,-D37/$C$36) -> 0.063433338 | E40: =IF($C$37<0,-E37/$C$39,-E37/$C$36) -> 0.066605005 | F40: =IF($C$37<0,-F37/$C$39,-F37/$C$36) -> 0.069935256 | G40: =IF($C$37<0,-G37/$C$39,-G37/$C$36) -> 0.073432018 | H40: =IF($C$37<0,-H37/$C$39,-H37/$C$36) -> 0.077103619 | I40: =IF($C$37<0,-I37/$C$39,-I37/$C$36) -> 0.0809588 | J40: =IF($C$37<0,-J37/$C$39,-J37/$C$36) -> 0.08500674 | K40: =IF($C$37<0,-K37/$C$39,-K37/$C$36) -> 0.089257077 | ... Q40: =IF($C$37<0,-Q37/$C$39,-Q37/$C$36) -> 0.11961302
B42: Alavancagem | C42: 1º Ano | D42: 2º Ano | E42: 3º Ano | F42: 4º Ano | G42: 5º Ano | H42: 6º Ano | I42: 7º Ano | J42: 8º Ano | K42: 9º Ano | L42: 10º Ano | M42: 11º Ano | N42: 12º Ano | O42: 13º Ano | P42: 14º Ano | Q42: 15º Ano | S42: Indicadores Alavancado
B43: Investimento | C43: =-($C$15+$D$19+$D$21+$C$22+$C$23) -> -126500 | S43: TIR Ala. | T43: =IRR(C46:Q46) -> 0.1153716 | V43: TIR Ala.
B44: Renda | C44: =IF($O$14>=1,SUM('11.1 - Auxiliar Viabilidade'!$L$8:$L$19),0) -> -21542.135 | D44: =IF($O$14>=2,SUM('11.1 - Auxiliar Viabilidade'!$L$20:$L$31),0) -> -5712.6019 | E44: =IF($O$14>=3,SUM('11.1 - Auxiliar Viabilidade'!$L$32:$L$43),0) -> -3898.7856 | F44: =IF($O$14>=4,SUM('11.1 - Auxiliar Viabilidade'!$L$44:$L$55),0) -> -2027.0865 | G44: =IF($O$14>=5,SUM('11.1 - Auxiliar Viabilidade'!$L$56:$L$67),0) -> -94.610205 | H44: =IF($O$14>=6,SUM('11.1 - Auxiliar Viabilidade'!$L$68:$L$79),0) -> 1901.682 | I44: =IF($O$14>=7,SUM('11.1 - Auxiliar Viabilidade'!$L$80:$L$91),0) -> 3964.9809 | J44: =IF($O$14>=8,SUM('11.1 - Auxiliar Viabilidade'!$L$92:$L$103),0) -> 6098.6368 | K44: =IF($O$14>=9,SUM('11.1 - Auxiliar Viabilidade'!$L$104:$L$115),0) -> 8306.1677 | L44: =IF($O$14>=10,SUM('11.1 - Auxiliar Viabilidade'!$L$116:$L$127)-$O$12,0) -> 10591.267 | M44: =IF($O$14>=11,SUM('11.1 - Auxiliar Viabilidade'!$L$128:$L$139),0) -> 12957.814 | N44: =IF($O$14>=12,SUM('11.1 - Auxiliar Viabilidade'!$L$140:$L$151),0) -> 15409.88 | O44: =IF($O$14>=13,SUM('11.1 - Auxiliar Viabilidade'!$L$152:$L$163),0) -> 17951.741 | P44: =IF($O$14>=14,SUM('11.1 - Auxiliar Viabilidade'!$L$164:$L$175),0) -> 20587.888 | Q44: =IF($O$14>=15,SUM('11.1 - Auxiliar Viabilidade'!$L$176:$L$187),0) -> 23323.034 | S44: ROI Ala. | T44: =((SUM(D46:Q46)+C46)/-C46) -> 3.4932695 | V44: ROI Ala.
B45: Venda | C45: =IF($O$14=1,C34-((C34*$O$13)+$O$17*(C34-$C$10))-'11.1 - Auxiliar Viabilidade'!J19,0) -> 0 | D45: =IF($O$14=2,D34-((D34*$O$13)+$O$17*(D34-$C$10))-'11.1 - Auxiliar Viabilidade'!J31,0) -> 0 | E45: =IF($O$14=3,E34-((E34*$O$13)+$O$17*(E34-$C$10))-'11.1 - Auxiliar Viabilidade'!J43,0) -> 0 | F45: =IF($O$14=4,F34-((F34*$O$13)+$O$17*(F34-$C$10))-'11.1 - Auxiliar Viabilidade'!J55,0) -> 0 | G45: =IF($O$14=5,G34-((G34*$O$13)+$O$17*(G34-$C$10))-'11.1 - Auxiliar Viabilidade'!J67,0) -> 0 | H45: =IF($O$14=6,H34-((H34*$O$13)+$O$17*(H34-$C$10))-'11.1 - Auxiliar Viabilidade'!J79,0) -> 0 | I45: =IF($O$14=7,I34-((I34*$O$13)+$O$17*(I34-$C$10))-'11.1 - Auxiliar Viabilidade'!J91,0) -> 0 | J45: =IF($O$14=8,J34-((J34*$O$13)+$O$17*(J34-$C$10))-'11.1 - Auxiliar Viabilidade'!J103,0) -> 0 | K45: =IF($O$14=9,K34-((K34*$O$13)+$O$17*(K34-$C$10))-'11.1 - Auxiliar Viabilidade'!J115,0) -> 0 | L45: =IF($O$14=10,L34-((L34*$O$13)+$O$17*(L34-$C$10))-'11.1 - Auxiliar Viabilidade'!J127,0) -> 0 | M45: =IF($O$14=11,M34-((M34*$O$13)+$O$17*(M34-$C$10))-'11.1 - Auxiliar Viabilidade'!J139,0) -> 0 | N45: =IF($O$14=12,N34-((N34*$O$13)+$O$17*(N34-$C$10))-'11.1 - Auxiliar Viabilidade'!J151,0) -> 0 | O45: =IF($O$14=13,O34-((O34*$O$13)+$O$17*(O34-$C$10))-'11.1 - Auxiliar Viabilidade'!J163,0) -> 0 | P45: =IF($O$14=14,P34-((P34*$O$13)+$O$17*(P34-$C$10))-'11.1 - Auxiliar Viabilidade'!J175,0) -> 0 | Q45: =IF($O$14=15,$Q$34-(($Q$34*$O$13)+$O$17*($Q$34-$C$10))-'11.1 - Auxiliar Viabilidade'!$J$187,0) -> 555833.2 | S45: Multiplo Ala. | T45: =SUM(D46:Q46)/-C46 -> 4.4932695 | V45: Multiplo Ala.
B46: Fluxo | C46: =SUM(C43:C45) -> -148042.13 | D46: =SUM(D43:D45) -> -5712.6019 | E46: =SUM(E43:E45) -> -3898.7856 | F46: =SUM(F43:F45) -> -2027.0865 | G46: =SUM(G43:G45) -> -94.610205 | H46: =SUM(H43:H45) -> 1901.682 | I46: =SUM(I43:I45) -> 3964.9809 | J46: =SUM(J43:J45) -> 6098.6368 | ... Q46: =SUM(Q43:Q45) -> 579156.24 | S46: VPL Ala. | T46: {=NPV($O$15,D46:Q46)+C46} -> 31460.323 | U46: =C46/C39 -> 0.41466038 | V46: VPL Ala.
B47: Yield | C47: =C44/-$C$43 -> -0.17029356 | D47: =IF($C$44<0,-D44/$C$46,-D44/$C$43) -> -0.038587676 | E47: =IF($C$44<0,-E44/$C$46,-E44/$C$43) -> -0.026335649 | F47: =IF($C$44<0,-F44/$C$46,-F44/$C$43) -> -0.013692632 | G47: =IF($C$44<0,-G44/$C$46,-G44/$C$43) -> -0.0006390762 | H47: =IF($C$44<0,-H44/$C$46,-H44/$C$43) -> 0.012845545 | I47: =IF($C$44<0,-I44/$C$46,-I44/$C$43) -> 0.026782786 | J47: =IF($C$44<0,-J44/$C$46,-J44/$C$43) -> 0.041195277 | K47: =IF($C$44<0,-K44/$C$46,-K44/$C$43) -> 0.056106781 | ... Q47: =IF($C$44<0,-Q44/$C$46,-Q44/$C$43) -> 0.15754321 | S47: VPL Comparado | T47: =(100%*T46)/U46 -> 75870.095 | U47: 1 | V47: VPL Comparado
B49: Imóvel na Planta
C50: Faça Você | D50: Faça Você
C51: Valor de Mercado | D51: 0 | E51: 0 | F51: 0 | G51: 0 | H51: 0 | I51: 0 | J51: 0 | K51: 0 | L51: 0 | M51: 0 | N51: 0 | O51: 0 | P51: 0 | Q51: 0
C52: =$C$10+$C$23 -> 350000 | D52: =IF(D51<C52,(C52+(C52*$O$11)),D51) -> 367500 | E52: =IF(E51<D52,(D52+(D52*$O$11)),E51) -> 385875 | F52: =IF(F51<E52,(E52+(E52*$O$11)),F51) -> 405168.75 | G52: =IF(G51<F52,(F52+(F52*$O$11)),G51) -> 425427.19 | H52: =IF(H51<G52,(G52+(G52*$O$11)),H51) -> 446698.55 | I52: =IF(I51<H52,(H52+(H52*$O$11)),I51) -> 469033.47 | J52: =IF(J51<I52,(I52+(I52*$O$11)),J51) -> 492485.15 | K52: =IF(K51<J52,(J52+(J52*$O$11)),K51) -> 517109.41 | ... Q52: =IF(Q51<P52,(P52+(P52*$O$11)),Q51) -> 692976.06
B53: À Vista | C53: 1º Ano | D53: 2º Ano | E53: 3º Ano | F53: 4º Ano | G53: 5º Ano | H53: 6º Ano | I53: 7º Ano | J53: 8º Ano | K53: 9º Ano | L53: 10º Ano | M53: 11º Ano | N53: 12º Ano | O53: 13º Ano | P53: 14º Ano | Q53: 15º Ano | S53: Indicadores À Vista
B54: Investimento | C54: =IF(G11<=12,-($D$19+$D$20+$D$21+$C$10+$C$23),(-C10)) -> -365000 | D54: =IF(G11<=12,0,-(D19+D20+D21+C23)) -> 0 | S54: TIR | T54: =IRR(C57:Q57) -> 0.11387441 | V54: TIR
B55: Renda | C55: =IF($O$14>=1,SUM('11.1 - Auxiliar Viabilidade'!$AD$8:$AD$19),0) -> 7979.7934 | D55: =IF($O$14>=2,SUM('11.1 - Auxiliar Viabilidade'!$AD$20:$AD$31),0) -> 23153.169 | E55: =IF($O$14>=3,SUM('11.1 - Auxiliar Viabilidade'!$AD$32:$AD$43),0) -> 24310.827 | F55: =IF($O$14>=4,SUM('11.1 - Auxiliar Viabilidade'!$AD$44:$AD$55),0) -> 25526.368 | G55: =IF($O$14>=5,SUM('11.1 - Auxiliar Viabilidade'!$AD$56:$AD$67),0) -> 26802.687 | H55: =IF($O$14>=6,SUM('11.1 - Auxiliar Viabilidade'!$AD$68:$AD$79),0) -> 28142.821 | I55: =IF($O$14>=7,SUM('11.1 - Auxiliar Viabilidade'!$AD$80:$AD$91),0) -> 29549.962 | J55: =IF($O$14>=8,SUM('11.1 - Auxiliar Viabilidade'!$AD$92:$AD$103),0) -> 31027.46 | K55: =IF($O$14>=9,SUM('11.1 - Auxiliar Viabilidade'!$AD$104:$AD$115),0) -> 32578.833 | L55: =IF($O$14>=10,SUM('11.1 - Auxiliar Viabilidade'!$AD$116:$AD$127)-$O$12,0) -> 34207.775 | M55: =IF($O$14>=11,SUM('11.1 - Auxiliar Viabilidade'!$AD$128:$AD$139),0) -> 35918.164 | N55: =IF($O$14>=12,SUM('11.1 - Auxiliar Viabilidade'!$AD$140:$AD$151),0) -> 37714.072 | O55: =IF($O$14>=13,SUM('11.1 - Auxiliar Viabilidade'!$AD$152:$AD$163),0) -> 39599.775 | P55: =IF($O$14>=14,SUM('11.1 - Auxiliar Viabilidade'!$AD$164:$AD$175),0) -> 41579.764 | Q55: =IF($O$14>=15,SUM('11.1 - Auxiliar Viabilidade'!$AD$176:$AD$187),0) -> 43658.752 | S55: ROI | T55: =IF(G11<=12,(SUM(D57:Q57)+C57)/-C57,(SUM(E57:Q57)+(C57+D57))/-(C57+D57)) -> 2.2119932 | V55: ROI
B56: Venda | C56: =IF($O$14=1,C52-((C52*$O$13)+$O$17*(C52-$C$10)),0) -> 0 | D56: =IF($O$14=2,D52-((D52*$O$13)+$O$17*(D52-$C$10)),0) -> 0 | E56: =IF($O$14=3,E52-((E52*$O$13)+$O$17*(E52-$C$10)),0) -> 0 | F56: =IF($O$14=4,F52-((F52*$O$13)+$O$17*(F52-$C$10)),0) -> 0 | G56: =IF($O$14=5,G52-((G52*$O$13)+$O$17*(G52-$C$10)),0) -> 0 | H56: =IF($O$14=6,H52-((H52*$O$13)+$O$17*(H52-$C$10)),0) -> 0 | I56: =IF($O$14=7,I52-((I52*$O$13)+$O$17*(I52-$C$10)),0) -> 0 | J56: =IF($O$14=8,J52-((J52*$O$13)+$O$17*(J52-$C$10)),0) -> 0 | K56: =IF($O$14=9,K52-((K52*$O$13)+$O$17*(K52-$C$10)),0) -> 0 | L56: =IF($O$14=10,L52-((L52*$O$13)+$O$17*(L52-$C$10)),0) -> 0 | M56: =IF($O$14=11,M52-((M52*$O$13)+$O$17*(M52-$C$10)),0) -> 0 | N56: =IF($O$14=12,N52-((N52*$O$13)+$O$17*(N52-$C$10)),0) -> 0 | O56: =IF($O$14=13,O52-((O52*$O$13)+$O$17*(O52-$C$10)),0) -> 0 | P56: =IF($O$14=14,P52-((P52*$O$13)+$O$17*(P52-$C$10)),0) -> 0 | Q56: =IF($O$14=15,$Q$52-(($Q$52*$O$13)+$O$17*($Q$52-$C$10)),0) -> 692976.06 | S56: Multiplo | T56: =IF(G11<=12,SUM(D57:Q57)/-C57,SUM(E57:Q57)/-(C57+D57)) -> 3.2119932 | V56: Multiplo
B57: Fluxo | C57: =SUM(C54:C56) -> -357020.21 | D57: =SUM(D54:D56) -> 23153.169 | E57: =SUM(E54:E56) -> 24310.827 | F57: =SUM(F54:F56) -> 25526.368 | G57: =SUM(G54:G56) -> 26802.687 | H57: =SUM(H54:H56) -> 28142.821 | I57: =SUM(I54:I56) -> 29549.962 | J57: =SUM(J54:J56) -> 31027.46 | ... Q57: =SUM(Q54:Q56) -> 736634.81 | S57: VPL | T57: {=NPV($O$15,D57:Q57)+C57} -> 47094.424 | V57: VPL
B58: Yield | C58: =C55/-$C$36 -> 0.021862448 | D58: =IF($C$55<0,-D55/$C$57,-D55/$C$54) -> 0.063433338 | E58: =IF($C$55<0,-E55/$C$57,-E55/$C$54) -> 0.066605005 | F58: =IF($C$55<0,-F55/$C$57,-F55/$C$54) -> 0.069935256 | G58: =IF($C$55<0,-G55/$C$57,-G55/$C$54) -> 0.073432018 | H58: =IF($C$55<0,-H55/$C$57,-H55/$C$54) -> 0.077103619 | I58: =IF($C$55<0,-I55/$C$57,-I55/$C$54) -> 0.0809588 | J58: =IF($C$55<0,-J55/$C$57,-J55/$C$54) -> 0.08500674 | K58: =IF($C$55<0,-K55/$C$57,-K55/$C$54) -> 0.089257077 | ... Q58: =IF($C$55<0,-Q55/$C$57,-Q55/$C$54) -> 0.11961302
B60: Alavancagem | C60: 1º Ano | D60: 2º Ano | E60: 3º Ano | F60: 4º Ano | G60: 5º Ano | H60: 6º Ano | I60: 7º Ano | J60: 8º Ano | K60: 9º Ano | L60: 10º Ano | M60: 11º Ano | N60: 12º Ano | O60: 13º Ano | P60: 14º Ano | Q60: 15º Ano | S60: Indicadores Alavancado
B61: Investimento | C61: =IF(G11<=12,-(D19+D21+C22+C23),0) -> -66500 | D61: =IF(G11>=13,-(D19+D21+C22+C23),0) -> 0 | S61: TIR Ala. | T61: =IRR(C64:Q64) -> 0.15742527 | V61: TIR Ala.
B62: Pagto/Renda | C62: =IF($O$14>=1,SUM('11.1 - Auxiliar Viabilidade'!$AC$8:$AC$19),0) -> -21542.135 | D62: =IF($O$14>=2,SUM('11.1 - Auxiliar Viabilidade'!$AC$20:$AC$31),0) -> -5712.6019 | E62: =IF($O$14>=3,SUM('11.1 - Auxiliar Viabilidade'!$AC$32:$AC$43),0) -> -3898.7856 | F62: =IF($O$14>=4,SUM('11.1 - Auxiliar Viabilidade'!$AC$44:$AC$55),0) -> -2027.0865 | G62: =IF($O$14>=5,SUM('11.1 - Auxiliar Viabilidade'!$AC$56:$AC$67),0) -> -94.610205 | H62: =IF($O$14>=6,SUM('11.1 - Auxiliar Viabilidade'!$AC$68:$AC$79),0) -> 1901.682 | I62: =IF($O$14>=7,SUM('11.1 - Auxiliar Viabilidade'!$AC$80:$AC$91),0) -> 3964.9809 | J62: =IF($O$14>=8,SUM('11.1 - Auxiliar Viabilidade'!$AC$92:$AC$103),0) -> 6098.6368 | K62: =IF($O$14>=9,SUM('11.1 - Auxiliar Viabilidade'!$AC$104:$AC$115),0) -> 8306.1677 | L62: =IF($O$14>=10,SUM('11.1 - Auxiliar Viabilidade'!$AC$116:$AC$127)-$O$12,0) -> 10591.267 | M62: =IF($O$14>=11,SUM('11.1 - Auxiliar Viabilidade'!$AC$128:$AC$139),0) -> 12957.814 | N62: =IF($O$14>=12,SUM('11.1 - Auxiliar Viabilidade'!$AC$140:$AC$151),0) -> 15409.88 | O62: =IF($O$14>=13,SUM('11.1 - Auxiliar Viabilidade'!$AC$152:$AC$163),0) -> 17951.741 | P62: =IF($O$14>=14,SUM('11.1 - Auxiliar Viabilidade'!$AC$164:$AC$175),0) -> 20587.888 | Q62: =IF($O$14>=15,SUM('11.1 - Auxiliar Viabilidade'!$AC$176:$AC$187),0) -> 23323.034 | S62: ROI Ala. | T62: =IF(G18<=12,(SUM(D64:Q64)+C64)/-C64,(SUM(E64:Q64)+(C64+D64))/-(C64+D64)) -> 6.1559671 | V62: ROI Ala.
B63: Venda | C63: =IF($O$14=1,C52-((C52*$O$13)+$O$17*(C52-$C$10))-'11.1 - Auxiliar Viabilidade'!J37,0) -> 0 | D63: =IF($O$14=2,D52-((D52*$O$13)+$O$17*(D52-$C$10))-'11.1 - Auxiliar Viabilidade'!J49,0) -> 0 | E63: =IF($O$14=3,E52-((E52*$O$13)+$O$17*(E52-$C$10))-'11.1 - Auxiliar Viabilidade'!J61,0) -> 0 | F63: =IF($O$14=4,F52-((F52*$O$13)+$O$17*(F52-$C$10))-'11.1 - Auxiliar Viabilidade'!J73,0) -> 0 | G63: =IF($O$14=5,G52-((G52*$O$13)+$O$17*(G52-$C$10))-'11.1 - Auxiliar Viabilidade'!J85,0) -> 0 | H63: =IF($O$14=6,H52-((H52*$O$13)+$O$17*(H52-$C$10))-'11.1 - Auxiliar Viabilidade'!J97,0) -> 0 | I63: =IF($O$14=7,I52-((I52*$O$13)+$O$17*(I52-$C$10))-'11.1 - Auxiliar Viabilidade'!J109,0) -> 0 | J63: =IF($O$14=8,J52-((J52*$O$13)+$O$17*(J52-$C$10))-'11.1 - Auxiliar Viabilidade'!J121,0) -> 0 | K63: =IF($O$14=9,K52-((K52*$O$13)+$O$17*(K52-$C$10))-'11.1 - Auxiliar Viabilidade'!J133,0) -> 0 | L63: =IF($O$14=10,L52-((L52*$O$13)+$O$17*(L52-$C$10))-'11.1 - Auxiliar Viabilidade'!J145,0) -> 0 | M63: =IF($O$14=11,M52-((M52*$O$13)+$O$17*(M52-$C$10))-'11.1 - Auxiliar Viabilidade'!J157,0) -> 0 | N63: =IF($O$14=12,N52-((N52*$O$13)+$O$17*(N52-$C$10))-'11.1 - Auxiliar Viabilidade'!J169,0) -> 0 | O63: =IF($O$14=13,O52-((O52*$O$13)+$O$17*(O52-$C$10))-'11.1 - Auxiliar Viabilidade'!J181,0) -> 0 | P63: =IF($O$14=14,P52-((P52*$O$13)+$O$17*(P52-$C$10))-'11.1 - Auxiliar Viabilidade'!J193,0) -> 0 | Q63: =IF($O$14=15,$Q$52-(($Q$52*$O$13)+$O$17*($Q$52-$C$10))-'11.1 - Auxiliar Viabilidade'!$J$187,0) -> 555833.2 | S63: Multiplo Ala. | T63: =IF(G18<=12,SUM(D64:Q64)/-C64,SUM(E64:Q64)/-(C64+D64)) -> 7.1559671 | V63: Multiplo Ala.
B64: Fluxo | C64: =SUM(C61:C63) -> -88042.135 | D64: =SUM(D61:D63) -> -5712.6019 | E64: =SUM(E61:E63) -> -3898.7856 | F64: =SUM(F61:F63) -> -2027.0865 | G64: =SUM(G61:G63) -> -94.610205 | H64: =SUM(H61:H63) -> 1901.682 | I64: =SUM(I61:I63) -> 3964.9809 | J64: =SUM(J61:J63) -> 6098.6368 | ... Q64: =SUM(Q61:Q63) -> 579156.24 | S64: VPL Ala. | T64: {=NPV($O$15,D64:Q64)+C64} -> 91460.323 | U64: =IF(G11>=12,(C64+D64)/(C57+D57),C64/(C57+D57)) -> 0.28081459 | V64: VPL Ala.
B65: Yield | C65: =IF(C62<0,0,C62/C61) -> 0 | D65: =IF($D$62<0,0,-D62/$C$64) -> 0 | E65: =IF($E$62<0,0,-E62/(C64+D64)) -> 0 | F65: =IF($E$62<0,F62/-SUM($C$64:$E$64),F62/-SUM($C$64:$D$64)) -> -0.020757945 | G65: =IF($E$62<0,G62/-SUM($C$64:$E$64),G62/-SUM($C$64:$D$64)) -> -0.00096883556 | H65: =IF($E$62<0,H62/-SUM($C$64:$E$64),H62/-SUM($C$64:$D$64)) -> 0.019473767 | I65: =IF($E$62<0,I62/-SUM($C$64:$E$64),I62/-SUM($C$64:$D$64)) -> 0.040602538 | J65: =IF($E$62<0,J62/-SUM($C$64:$E$64),J62/-SUM($C$64:$D$64)) -> 0.062451785 | K65: =IF($E$62<0,K62/-SUM($C$64:$E$64),K62/-SUM($C$64:$D$64)) -> 0.085057533 | L65: =IF($E$62<0,L62/-SUM($C$64:$E$64),L62/-SUM($C$64:$D$64)) -> 0.10845761 | M65: =IF($E$62<0,M62/-SUM($C$64:$E$64),M62/-SUM($C$64:$D$64)) -> 0.13269172 | ... Q65: =IF($E$62<0,Q62/-SUM($C$64:$E$64),Q62/-SUM($C$64:$D$64)) -> 0.23883454 | S65: VPL Comparado | T65: =(100%*T64)/U64 -> 325696.47 | U65: 1 | V65: VPL Comparado

Sheet 11.1 - Auxiliar Viabilidade
B1: © Escola de Imóveis - www.escoladeimoveis.com.br | Siga no instagram e tenha o melhor conteúdo: @escoladeimoveis
B2: É terminantemente proibida a utilização, acesso, cópia ou divulgação não autorizada das informações presentes nesta planilha.
B3: ATENÇÃO: SOMENTE ALTERAR AS CÉLULAS ROXAS COM A ESCRITA FAÇA VOCÊ
B5: Auxiliar Viabilidade Completa
B7: Mês | C7: Offset Mês | D7: Aluguel | E7: Corretagem | F7: Administração | G7: Fundo Reparos | H7: Vacância | I7: Prestação | J7: Saldo Devedor | K7: Imposto | L7: Líquido Alavan. | M7: Líquido À Vista | O7: Entrada | P7: Parcelas Obra | Q7: Parcela Entrega | R7: Total Planta | S7: Mês Ajustado | T7: Offset Planta | U7: Aluguel | V7: Corretagem | W7: Administração | X7: Fundo Reparos | Y7: Vacância | Z7: Prestação | AA7: Saldo Devedor | AB7: Imposto | AC7: Líquido Alavan. | AD7: Líquido À Vista
A8: =IF(AND('11-Viabilidade'!P14>0,'11-Viabilidade'!P14<421),1,0) -> 1 | B8: =IF(A8>0,1,0) -> 1 | C8: =IF($B8<'11-Viabilidade'!$C$24,0,$B8-'11-Viabilidade'!$C$24) -> 0 | D8: =IF(C8>0,'11-Viabilidade'!$K$10,0)*((1+'11-Viabilidade'!$O$10)^(($C8-1)/12)) -> 0 | E8: =D8*'11-Viabilidade'!$L$12 -> 0 | F8: =D8*'11-Viabilidade'!$K$14 -> 0 | G8: =D8*'11-Viabilidade'!$K$15 -> 0 | H8: =IF(D8=0,'11-Viabilidade'!$K$16+'11-Viabilidade'!$K$17,('11-Viabilidade'!$L$11)*((1+'11-Viabilidade'!$O$10)^(($C8-1)/12))) -> 530 | I8: ='12-SAC Viabilidade'!G11 -> 2485.2223 | J8: ='12-SAC Viabilidade'!H11 -> 239428.57 | K8: =(D8-F8)*'11-Viabilidade'!$O$16 -> 0 | L8: =D8-(E8+F8+G8+H8+I8+K8) -> -3015.2223 | M8: =D8-(E8+F8+G8+H8+K8) -> -530 | O8: =IF('11-Viabilidade'!G10="Sim",'11-Viabilidade'!G14,0) -> 0 | P8: =IF(B8<='11-Viabilidade'!$G$11,'11-Viabilidade'!$G$15,0) -> 0 | Q8: =IF(B8='11-Viabilidade'!$G$11,'11-Viabilidade'!$G$16,0)*(1+'11-Viabilidade'!$G$12)^((B8-1)/12) -> 0 | R8: =-SUM(O8:Q8) -> 0 | S8: =IF(R8<>0,0,1) -> 1 | T8: =IF($S8<'11-Viabilidade'!$C$24,0,$S8-'11-Viabilidade'!$C$24) -> 0 | U8: =IF(T8>0,'11-Viabilidade'!$K$10,0)*((1+'11-Viabilidade'!$O$10)^(($T8-1)/12)) -> 0 | V8: =U8*'11-Viabilidade'!$L$12 -> 0 | W8: =U8*'11-Viabilidade'!$K$14 -> 0 | X8: =U8*'11-Viabilidade'!$K$15 -> 0 | Y8: =IF(AND(U8=0,S8=0),0,IF(AND(U8=0,S8<>0),'11-Viabilidade'!$K$16+'11-Viabilidade'!$K$17,('11-Viabilidade'!$L$11)*((1+'11-Viabilidade'!$O$10)^(($C8-1)/12)))) -> 530 | Z8: =IFERROR(VLOOKUP(S8,'12-SAC Viabilidade'!$B$11:$G$430,6,FALSE),0) -> 2485.2223 | AA8: =IFERROR(VLOOKUP(S8,'12-SAC Viabilidade'!$B$11:$H$430,7,FALSE),0) -> 239428.57 | AB8: =(U8-W8)*'11-Viabilidade'!$O$16 -> 0 | AC8: =U8-(V8+W8+X8+Y8+Z8+AB8-R8) -> -3015.2223 | AD8: =U8-(V8+W8+X8+Y8+AB8) -> -530
B9: =IF(AND(B8>0,B8<'11-Viabilidade'!$P$14),B8+1,0) -> 2 | C9: =IF($B9<'11-Viabilidade'!$C$24,0,$B9-'11-Viabilidade'!$C$24) -> 0 | D9: =IF(C9>0,'11-Viabilidade'!$K$10,0)*((1+'11-Viabilidade'!$O$10)^(($C9-1)/12)) -> 0 | E9: =D9*'11-Viabilidade'!$L$12 -> 0 | F9: =D9*'11-Viabilidade'!$K$14 -> 0 | G9: =D9*'11-Viabilidade'!$K$15 -> 0 | H9: =IF(D9=0,'11-Viabilidade'!$K$16+'11-Viabilidade'!$K$17,('11-Viabilidade'!$L$11)*((1+'11-Viabilidade'!$O$10)^(($C9-1)/12))) -> 530 | I9: ='12-SAC Viabilidade'!G12 -> 2480.6656 | J9: ='12-SAC Viabilidade'!H12 -> 238857.14 | K9: =(D9-F9)*'11-Viabilidade'!$O$16 -> 0 | L9: =D9-(E9+F9+G9+H9+I9+K9) -> -3010.6656 | M9: =D9-(E9+F9+G9+H9+K9) -> -530 | P9: =IF(B9<='11-Viabilidade'!$G$11,(P8+(P8*'11-Viabilidade'!$H$12)),0) -> 0 | Q9: =IF(B9='11-Viabilidade'!$G$11,'11-Viabilidade'!$G$16,0)*(1+'11-Viabilidade'!$G$12)^((B9-1)/12) -> 0 | R9: =-SUM(O9:Q9) -> 0 | S9: =IF(R9<>0,0,S8+1) -> 2 | T9: =IF($S9<'11-Viabilidade'!$C$24,0,$S9-'11-Viabilidade'!$C$24) -> 0 | U9: =IF(T9>0,'11-Viabilidade'!$K$10,0)*((1+'11-Viabilidade'!$O$10)^(($T9-1)/12)) -> 0 | V9: =U9*'11-Viabilidade'!$L$12 -> 0 | W9: =U9*'11-Viabilidade'!$K$14 -> 0 | X9: =U9*'11-Viabilidade'!$K$15 -> 0 | Y9: =IF(AND(U9=0,S9=0),0,IF(AND(U9=0,S9<>0),'11-Viabilidade'!$K$16+'11-Viabilidade'!$K$17,('11-Viabilidade'!$L$11)*((1+'11-Viabilidade'!$O$10)^(($C9-1)/12)))) -> 530 | Z9: =IFERROR(VLOOKUP(S9,'12-SAC Viabilidade'!$B$11:$G$430,6,FALSE),0) -> 2480.6656 | AA9: =IFERROR(VLOOKUP(S9,'12-SAC Viabilidade'!$B$11:$H$430,7,FALSE),0) -> 238857.14 | AB9: =(U9-W9)*'11-Viabilidade'!$O$16 -> 0 | AC9: =U9-(V9+W9+X9+Y9+Z9+AB9-R9) -> -3010.6656 | AD9: =U9-(V9+W9+X9+Y9+AB9) -> -530
B10: =IF(AND(B9>0,B9<'11-Viabilidade'!$P$14),B9+1,0) -> 3 | C10: =IF($B10<'11-Viabilidade'!$C$24,0,$B10-'11-Viabilidade'!$C$24) -> 0 | D10: =IF(C10>0,'11-Viabilidade'!$K$10,0)*((1+'11-Viabilidade'!$O$10)^(($C10-1)/12)) -> 0 | E10: =D10*'11-Viabilidade'!$L$12 -> 0 | F10: =D10*'11-Viabilidade'!$K$14 -> 0 | G10: =D10*'11-Viabilidade'!$K$15 -> 0 | H10: =IF(D10=0,'11-Viabilidade'!$K$16+'11-Viabilidade'!$K$17,('11-Viabilidade'!$L$11)*((1+'11-Viabilidade'!$O$10)^(($C10-1)/12))) -> 530 | I10: ='12-SAC Viabilidade'!G13 -> 2476.109 | J10: ='12-SAC Viabilidade'!H13 -> 238285.71 | K10: =(D10-F10)*'11-Viabilidade'!$O$16 -> 0 | L10: =D10-(E10+F10+G10+H10+I10+K10) -> -3006.109 | M10: =D10-(E10+F10+G10+H10+K10) -> -530 | P10: =IF(B10<='11-Viabilidade'!$G$11,(P9+(P9*'11-Viabilidade'!$H$12)),0) -> 0 | Q10: =IF(B10='11-Viabilidade'!$G$11,'11-Viabilidade'!$G$16,0)*(1+'11-Viabilidade'!$G$12)^((B10-1)/12) -> 0 | R10: =-SUM(O10:Q10) -> 0 | S10: =IF(R10<>0,0,S9+1) -> 3 | T10: =IF($S10<'11-Viabilidade'!$C$24,0,$S10-'11-Viabilidade'!$C$24) -> 0 | U10: =IF(T10>0,'11-Viabilidade'!$K$10,0)*((1+'11-Viabilidade'!$O$10)^(($T10-1)/12)) -> 0 | V10: =U10*'11-Viabilidade'!$L$12 -> 0 | W10: =U10*'11-Viabilidade'!$K$14 -> 0 | X10: =U10*'11-Viabilidade'!$K$15 -> 0 | Y10: =IF(AND(U10=0,S10=0),0,IF(AND(U10=0,S10<>0),'11-Viabilidade'!$K$16+'11-Viabilidade'!$K$17,('11-Viabilidade'!$L$11)*((1+'11-Viabilidade'!$O$10)^(($C10-1)/12)))) -> 530 | Z10: =IFERROR(VLOOKUP(S10,'12-SAC Viabilidade'!$B$11:$G$430,6,FALSE),0) -> 2476.109 | AA10: =IFERROR(VLOOKUP(S10,'12-SAC Viabilidade'!$B$11:$H$430,7,FALSE),0) -> 238285.71 | AB10: =(U10-W10)*'11-Viabilidade'!$O$16 -> 0 | AC10: =U10-(V10+W10+X10+Y10+Z10+AB10-R10) -> -3006.109 | AD10: =U10-(V10+W10+X10+Y10+AB10) -> -530
B11: =IF(AND(B10>0,B10<'11-Viabilidade'!$P$14),B10+1,0) -> 4 | C11: =IF($B11<'11-Viabilidade'!$C$24,0,$B11-'11-Viabilidade'!$C$24) -> 0 | D11: =IF(C11>0,'11-Viabilidade'!$K$10,0)*((1+'11-Viabilidade'!$O$10)^(($C11-1)/12)) -> 0 | E11: =D11*'11-Viabilidade'!$L$12 -> 0 | F11: =D11*'11-Viabilidade'!$K$14 -> 0 | G11: =D11*'11-Viabilidade'!$K$15 -> 0 | H11: =IF(D11=0,'11-Viabilidade'!$K$16+'11-Viabilidade'!$K$17,('11-Viabilidade'!$L$11)*((1+'11-Viabilidade'!$O$10)^(($C11-1)/12))) -> 530 | I11: ='12-SAC Viabilidade'!G14 -> 2471.5523 | J11: ='12-SAC Viabilidade'!H14 -> 237714.29 | K11: =(D11-F11)*'11-Viabilidade'!$O$16 -> 0 | L11: =D11-(E11+F11+G11+H11+I11+K11) -> -3001.5523 | M11: =D11-(E11+F11+G11+H11+K11) -> -530 | P11: =IF(B11<='11-Viabilidade'!$G$11,(P10+(P10*'11-Viabilidade'!$H$12)),0) -> 0 | Q11: =IF(B11='11-Viabilidade'!$G$11,'11-Viabilidade'!$G$16,0)*(1+'11-Viabilidade'!$G$12)^((B11-1)/12) -> 0 | R11: =-SUM(O11:Q11) -> 0 | S11: =IF(R11<>0,0,S10+1) -> 4 | T11: =IF($S11<'11-Viabilidade'!$C$24,0,$S11-'11-Viabilidade'!$C$24) -> 0 | U11: =IF(T11>0,'11-Viabilidade'!$K$10,0)*((1+'11-Viabilidade'!$O$10)^(($T11-1)/12)) -> 0 | V11: =U11*'11-Viabilidade'!$L$12 -> 0 | W11: =U11*'11-Viabilidade'!$K$14 -> 0 | X11: =U11*'11-Viabilidade'!$K$15 -> 0 | Y11: =IF(AND(U11=0,S11=0),0,IF(AND(U11=0,S11<>0),'11-Viabilidade'!$K$16+'11-Viabilidade'!$K$17,('11-Viabilidade'!$L$11)*((1+'11-Viabilidade'!$O$10)^(($C11-1)/12)))) -> 530 | Z11: =IFERROR(VLOOKUP(S11,'12-SAC Viabilidade'!$B$11:$G$430,6,FALSE),0) -> 2471.5523 | AA11: =IFERROR(VLOOKUP(S11,'12-SAC Viabilidade'!$B$11:$H$430,7,FALSE),0) -> 237714.29 | AB11: =(U11-W11)*'11-Viabilidade'!$O$16 -> 0 | AC11: =U11-(V11+W11+X11+Y11+Z11+AB11-R11) -> -3001.5523 | AD11: =U11-(V11+W11+X11+Y11+AB11) -> -530
B12: =IF(AND(B11>0,B11<'11-Viabilidade'!$P$14),B11+1,0) -> 5 | C12: =IF($B12<'11-Viabilidade'!$C$24,0,$B12-'11-Viabilidade'!$C$24) -> 0 | D12: =IF(C12>0,'11-Viabilidade'!$K$10,0)*((1+'11-Viabilidade'!$O$10)^(($C12-1)/12)) -> 0 | E12: =D12*'11-Viabilidade'!$L$12 -> 0 | F12: =D12*'11-Viabilidade'!$K$14 -> 0 | G12: =D12*'11-Viabilidade'!$K$15 -> 0 | H12: =IF(D12=0,'11-Viabilidade'!$K$16+'11-Viabilidade'!$K$17,('11-Viabilidade'!$L$11)*((1+'11-Viabilidade'!$O$10)^(($C12-1)/12))) -> 530 | I12: ='12-SAC Viabilidade'!G15 -> 2466.9957 | J12: ='12-SAC Viabilidade'!H15 -> 237142.86 | K12: =(D12-F12)*'11-Viabilidade'!$O$16 -> 0 | L12: =D12-(E12+F12+G12+H12+I12+K12) -> -2996.9957 | M12: =D12-(E12+F12+G12+H12+K12) -> -530 | P12: =IF(B12<='11-Viabilidade'!$G$11,(P11+(P11*'11-Viabilidade'!$H$12)),0) -> 0 | Q12: =IF(B12='11-Viabilidade'!$G$11,'11-Viabilidade'!$G$16,0)*(1+'11-Viabilidade'!$G$12)^((B12-1)/12) -> 0 | R12: =-SUM(O12:Q12) -> 0 | S12: =IF(R12<>0,0,S11+1) -> 5 | T12: =IF($S12<'11-Viabilidade'!$C$24,0,$S12-'11-Viabilidade'!$C$24) -> 0 | U12: =IF(T12>0,'11-Viabilidade'!$K$10,0)*((1+'11-Viabilidade'!$O$10)^(($T12-1)/12)) -> 0 | V12: =U12*'11-Viabilidade'!$L$12 -> 0 | W12: =U12*'11-Viabilidade'!$K$14 -> 0 | X12: =U12*'11-Viabilidade'!$K$15 -> 0 | Y12: =IF(AND(U12=0,S12=0),0,IF(AND(U12=0,S12<>0),'11-Viabilidade'!$K$16+'11-Viabilidade'!$K$17,('11-Viabilidade'!$L$11)*((1+'11-Viabilidade'!$O$10)^(($C12-1)/12)))) -> 530 | Z12: =IFERROR(VLOOKUP(S12,'12-SAC Viabilidade'!$B$11:$G$430,6,FALSE),0) -> 2466.9957 | AA12: =IFERROR(VLOOKUP(S12,'12-SAC Viabilidade'!$B$11:$H$430,7,FALSE),0) -> 237142.86 | AB12: =(U12-W12)*'11-Viabilidade'!$O$16 -> 0 | AC12: =U12-(V12+W12+X12+Y12+Z12+AB12-R12) -> -2996.9957 | AD12: =U12-(V12+W12+X12+Y12+AB12) -> -530
B13: =IF(AND(B12>0,B12<'11-Viabilidade'!$P$14),B12+1,0) -> 6 | C13: =IF($B13<'11-Viabilidade'!$C$24,0,$B13-'11-Viabilidade'!$C$24) -> 0 | D13: =IF(C13>0,'11-Viabilidade'!$K$10,0)*((1+'11-Viabilidade'!$O$10)^(($C13-1)/12)) -> 0 | E13: =D13*'11-Viabilidade'!$L$12 -> 0 | F13: =D13*'11-Viabilidade'!$K$14 -> 0 | G13: =D13*'11-Viabilidade'!$K$15 -> 0 | H13: =IF(D13=0,'11-Viabilidade'!$K$16+'11-Viabilidade'!$K$17,('11-Viabilidade'!$L$11)*((1+'11-Viabilidade'!$O$10)^(($C13-1)/12))) -> 530 | I13: ='12-SAC Viabilidade'!G16 -> 2462.439 | J13: ='12-SAC Viabilidade'!H16 -> 236571.43 | K13: =(D13-F13)*'11-Viabilidade'!$O$16 -> 0 | L13: =D13-(E13+F13+G13+H13+I13+K13) -> -2992.439 | M13: =D13-(E13+F13+G13+H13+K13) -> -530 | P13: =IF(B13<='11-Viabilidade'!$G$11,(P12+(P12*'11-Viabilidade'!$H$12)),0) -> 0 | Q13: =IF(B13='11-Viabilidade'!$G$11,'11-Viabilidade'!$G$16,0)*(1+'11-Viabilidade'!$G$12)^((B13-1)/12) -> 0 | R13: =-SUM(O13:Q13) -> 0 | S13: =IF(R13<>0,0,S12+1) -> 6 | T13: =IF($S13<'11-Viabilidade'!$C$24,0,$S13-'11-Viabilidade'!$C$24) -> 0 | U13: =IF(T13>0,'11-Viabilidade'!$K$10,0)*((1+'11-Viabilidade'!$O$10)^(($T13-1)/12)) -> 0 | V13: =U13*'11-Viabilidade'!$L$12 -> 0 | W13: =U13*'11-Viabilidade'!$K$14 -> 0 | X13: =U13*'11-Viabilidade'!$K$15 -> 0 | Y13: =IF(AND(U13=0,S13=0),0,IF(AND(U13=0,S13<>0),'11-Viabilidade'!$K$16+'11-Viabilidade'!$K$17,('11-Viabilidade'!$L$11)*((1+'11-Viabilidade'!$O$10)^(($C13-1)/12)))) -> 530 | Z13: =IFERROR(VLOOKUP(S13,'12-SAC Viabilidade'!$B$11:$G$430,6,FALSE),0) -> 2462.439 | AA13: =IFERROR(VLOOKUP(S13,'12-SAC Viabilidade'!$B$11:$H$430,7,FALSE),0) -> 236571.43 | AB13: =(U13-W13)*'11-Viabilidade'!$O$16 -> 0 | AC13: =U13-(V13+W13+X13+Y13+Z13+AB13-R13) -> -2992.439 | AD13: =U13-(V13+W13+X13+Y13+AB13) -> -530
B14: =IF(AND(B13>0,B13<'11-Viabilidade'!$P$14),B13+1,0) -> 7 | C14: =IF($B14<'11-Viabilidade'!$C$24,0,$B14-'11-Viabilidade'!$C$24) -> 1 | D14: =IF(C14>0,'11-Viabilidade'!$K$10,0)*((1+'11-Viabilidade'!$O$10)^(($C14-1)/12)) -> 3000 | E14: =D14*'11-Viabilidade'!$L$12 -> 166.66667 | F14: =D14*'11-Viabilidade'!$K$14 -> 0 | G14: =D14*'11-Viabilidade'!$K$15 -> 150 | H14: =IF(D14=0,'11-Viabilidade'!$K$16+'11-Viabilidade'!$K$17,('11-Viabilidade'!$L$11)*((1+'11-Viabilidade'!$O$10)^(($C14-1)/12))) -> 392.22222 | I14: ='12-SAC Viabilidade'!G17 -> 2457.8824 | J14: ='12-SAC Viabilidade'!H17 -> 236000 | K14: =(D14-F14)*'11-Viabilidade'!$O$16 -> 450 | L14: =D14-(E14+F14+G14+H14+I14+K14) -> -616.77125 | M14: =D14-(E14+F14+G14+H14+K14) -> 1841.1111 | P14: =IF(B14<='11-Viabilidade'!$G$11,(P13+(P13*'11-Viabilidade'!$H$12)),0) -> 0 | Q14: =IF(B14='11-Viabilidade'!$G$11,'11-Viabilidade'!$G$16,0)*(1+'11-Viabilidade'!$G$12)^((B14-1)/12) -> 0 | R14: =-SUM(O14:Q14) -> 0 | S14: =IF(R14<>0,0,S13+1) -> 7 | T14: =IF($S14<'11-Viabilidade'!$C$24,0,$S14-'11-Viabilidade'!$C$24) -> 1 | U14: =IF(T14>0,'11-Viabilidade'!$K$10,0)*((1+'11-Viabilidade'!$O$10)^(($T14-1)/12)) -> 3000 | V14: =U14*'11-Viabilidade'!$L$12 -> 166.66667 | W14: =U14*'11-Viabilidade'!$K$14 -> 0 | X14: =U14*'11-Viabilidade'!$K$15 -> 150 | Y14: =IF(AND(U14=0,S14=0),0,IF(AND(U14=0,S14<>0),'11-Viabilidade'!$K$16+'11-Viabilidade'!$K$17,('11-Viabilidade'!$L$11)*((1+'11-Viabilidade'!$O$10)^(($C14-1)/12)))) -> 392.22222 | Z14: =IFERROR(VLOOKUP(S14,'12-SAC Viabilidade'!$B$11:$G$430,6,FALSE),0) -> 2457.8824 | AA14: =IFERROR(VLOOKUP(S14,'12-SAC Viabilidade'!$B$11:$H$430,7,FALSE),0) -> 236000 | AB14: =(U14-W14)*'11-Viabilidade'!$O$16 -> 450 | AC14: =U14-(V14+W14+X14+Y14+Z14+AB14-R14) -> -616.77125 | AD14: =U14-(V14+W14+X14+Y14+AB14) -> 1841.1111
B15: =IF(AND(B14>0,B14<'11-Viabilidade'!$P$14),B14+1,0) -> 8 | C15: =IF($B15<'11-Viabilidade'!$C$24,0,$B15-'11-Viabilidade'!$C$24) -> 2 | D15: =IF(C15>0,'11-Viabilidade'!$K$10,0)*((1+'11-Viabilidade'!$O$10)^(($C15-1)/12)) -> 3012.2224 | E15: =D15*'11-Viabilidade'!$L$12 -> 167.34569 | F15: =D15*'11-Viabilidade'!$K$14 -> 0 | G15: =D15*'11-Viabilidade'!$K$15 -> 150.61112 | H15: =IF(D15=0,'11-Viabilidade'!$K$16+'11-Viabilidade'!$K$17,('11-Viabilidade'!$L$11)*((1+'11-Viabilidade'!$O$10)^(($C15-1)/12))) -> 393.82018 | I15: ='12-SAC Viabilidade'!G18 -> 2453.3257 | J15: ='12-SAC Viabilidade'!H18 -> 235428.57 | K15: =(D15-F15)*'11-Viabilidade'!$O$16 -> 451.83336 | L15: =D15-(E15+F15+G15+H15+I15+K15) -> -604.71369 | M15: =D15-(E15+F15+G15+H15+K15) -> 1848.612 | P15: =IF(B15<='11-Viabilidade'!$G$11,(P14+(P14*'11-Viabilidade'!$H$12)),0) -> 0 | Q15: =IF(B15='11-Viabilidade'!$G$11,'11-Viabilidade'!$G$16,0)*(1+'11-Viabilidade'!$G$12)^((B15-1)/12) -> 0 | R15: =-SUM(O15:Q15) -> 0 | S15: =IF(R15<>0,0,S14+1) -> 8 | T15: =IF($S15<'11-Viabilidade'!$C$24,0,$S15-'11-Viabilidade'!$C$24) -> 2 | U15: =IF(T15>0,'11-Viabilidade'!$K$10,0)*((1+'11-Viabilidade'!$O$10)^(($T15-1)/12)) -> 3012.2224 | V15: =U15*'11-Viabilidade'!$L$12 -> 167.34569 | W15: =U15*'11-Viabilidade'!$K$14 -> 0 | X15: =U15*'11-Viabilidade'!$K$15 -> 150.61112 | Y15: =IF(AND(U15=0,S15=0),0,IF(AND(U15=0,S15<>0),'11-Viabilidade'!$K$16+'11-Viabilidade'!$K$17,('11-Viabilidade'!$L$11)*((1+'11-Viabilidade'!$O$10)^(($C15-1)/12)))) -> 393.82018 | Z15: =IFERROR(VLOOKUP(S15,'12-SAC Viabilidade'!$B$11:$G$430,6,FALSE),0) -> 2453.3257 | AA15: =IFERROR(VLOOKUP(S15,'12-SAC Viabilidade'!$B$11:$H$430,7,FALSE),0) -> 235428.57 | AB15: =(U15-W15)*'11-Viabilidade'!$O$16 -> 451.83336 | AC15: =U15-(V15+W15+X15+Y15+Z15+AB15-R15) -> -604.71369 | AD15: =U15-(V15+W15+X15+Y15+AB15) -> 1848.612
B16: =IF(AND(B15>0,B15<'11-Viabilidade'!$P$14),B15+1,0) -> 9 | C16: =IF($B16<'11-Viabilidade'!$C$24,0,$B16-'11-Viabilidade'!$C$24) -> 3 | D16: =IF(C16>0,'11-Viabilidade'!$K$10,0)*((1+'11-Viabilidade'!$O$10)^(($C16-1)/12)) -> 3024.4945 | E16: =D16*'11-Viabilidade'!$L$12 -> 168.02747 | F16: =D16*'11-Viabilidade'!$K$14 -> 0 | G16: =D16*'11-Viabilidade'!$K$15 -> 151.22473 | H16: =IF(D16=0,'11-Viabilidade'!$K$16+'11-Viabilidade'!$K$17,('11-Viabilidade'!$L$11)*((1+'11-Viabilidade'!$O$10)^(($C16-1)/12))) -> 395.42466 | I16: ='12-SAC Viabilidade'!G19 -> 2448.7691 | J16: ='12-SAC Viabilidade'!H19 -> 234857.14 | K16: =(D16-F16)*'11-Viabilidade'!$O$16 -> 453.67418 | L16: =D16-(E16+F16+G16+H16+I16+K16) -> -592.62556 | M16: =D16-(E16+F16+G16+H16+K16) -> 1856.1435 | P16: =IF(B16<='11-Viabilidade'!$G$11,(P15+(P15*'11-Viabilidade'!$H$12)),0) -> 0 | Q16: =IF(B16='11-Viabilidade'!$G$11,'11-Viabilidade'!$G$16,0)*(1+'11-Viabilidade'!$G$12)^((B16-1)/12) -> 0 | R16: =-SUM(O16:Q16) -> 0 | S16: =IF(R16<>0,0,S15+1) -> 9 | T16: =IF($S16<'11-Viabilidade'!$C$24,0,$S16-'11-Viabilidade'!$C$24) -> 3 | U16: =IF(T16>0,'11-Viabilidade'!$K$10,0)*((1+'11-Viabilidade'!$O$10)^(($T16-1)/12)) -> 3024.4945 | V16: =U16*'11-Viabilidade'!$L$12 -> 168.02747 | W16: =U16*'11-Viabilidade'!$K$14 -> 0 | X16: =U16*'11-Viabilidade'!$K$15 -> 151.22473 | Y16: =IF(AND(U16=0,S16=0),0,IF(AND(U16=0,S16<>0),'11-Viabilidade'!$K$16+'11-Viabilidade'!$K$17,('11-Viabilidade'!$L$11)*((1+'11-Viabilidade'!$O$10)^(($C16-1)/12)))) -> 395.42466 | Z16: =IFERROR(VLOOKUP(S16,'12-SAC Viabilidade'!$B$11:$G$430,6,FALSE),0) -> 2448.7691 | AA16: =IFERROR(VLOOKUP(S16,'12-SAC Viabilidade'!$B$11:$H$430,7,FALSE),0) -> 234857.14 | AB16: =(U16-W16)*'11-Viabilidade'!$O$16 -> 453.67418 | AC16: =U16-(V16+W16+X16+Y16+Z16+AB16-R16) -> -592.62556 | AD16: =U16-(V16+W16+X16+Y16+AB16) -> 1856.1435
B17: =IF(AND(B16>0,B16<'11-Viabilidade'!$P$14),B16+1,0) -> 10 | C17: =IF($B17<'11-Viabilidade'!$C$24,0,$B17-'11-Viabilidade'!$C$24) -> 4 | D17: =IF(C17>0,'11-Viabilidade'!$K$10,0)*((1+'11-Viabilidade'!$O$10)^(($C17-1)/12)) -> 3036.8167 | E17: =D17*'11-Viabilidade'!$L$12 -> 168.71204 | F17: =D17*'11-Viabilidade'!$K$14 -> 0 | G17: =D17*'11-Viabilidade'!$K$15 -> 151.84084 | H17: =IF(D17=0,'11-Viabilidade'!$K$16+'11-Viabilidade'!$K$17,('11-Viabilidade'!$L$11)*((1+'11-Viabilidade'!$O$10)^(($C17-1)/12))) -> 397.03567 | I17: ='12-SAC Viabilidade'!G20 -> 2444.2124 | J17: ='12-SAC Viabilidade'!H20 -> 234285.71 | K17: =(D17-F17)*'11-Viabilidade'!$O$16 -> 455.52251 | L17: =D17-(E17+F17+G17+H17+I17+K17) -> -580.50675 | M17: =D17-(E17+F17+G17+H17+K17) -> 1863.7057 | P17: =IF(B17<='11-Viabilidade'!$G$11,(P16+(P16*'11-Viabilidade'!$H$12)),0) -> 0 | Q17: =IF(B17='11-Viabilidade'!$G$11,'11-Viabilidade'!$G$16,0)*(1+'11-Viabilidade'!$G$12)^((B17-1)/12) -> 0 | R17: =-SUM(O17:Q17) -> 0 | S17: =IF(R17<>0,0,S16+1) -> 10 | T17: =IF($S17<'11-Viabilidade'!$C$24,0,$S17-'11-Viabilidade'!$C$24) -> 4 | U17: =IF(T17>0,'11-Viabilidade'!$K$10,0)*((1+'11-Viabilidade'!$O$10)^(($T17-1)/12)) -> 3036.8167 | V17: =U17*'11-Viabilidade'!$L$12 -> 168.71204 | W17: =U17*'11-Viabilidade'!$K$14 -> 0 | X17: =U17*'11-Viabilidade'!$K$15 -> 151.84084 | Y17: =IF(AND(U17=0,S17=0),0,IF(AND(U17=0,S17<>0),'11-Viabilidade'!$K$16+'11-Viabilidade'!$K$17,('11-Viabilidade'!$L$11)*((1+'11-Viabilidade'!$O$10)^(($C17-1)/12)))) -> 397.03567 | Z17: =IFERROR(VLOOKUP(S17,'12-SAC Viabilidade'!$B$11:$G$430,6,FALSE),0) -> 2444.2124 | AA17: =IFERROR(VLOOKUP(S17,'12-SAC Viabilidade'!$B$11:$H$430,7,FALSE),0) -> 234285.71 | AB17: =(U17-W17)*'11-Viabilidade'!$O$16 -> 455.52251 | AC17: =U17-(V17+W17+X17+Y17+Z17+AB17-R17) -> -580.50675 | AD17: =U17-(V17+W17+X17+Y17+AB17) -> 1863.7057
B18: =IF(AND(B17>0,B17<'11-Viabilidade'!$P$14),B17+1,0) -> 11 | C18: =IF($B18<'11-Viabilidade'!$C$24,0,$B18-'11-Viabilidade'!$C$24) -> 5 | D18: =IF(C18>0,'11-Viabilidade'!$K$10,0)*((1+'11-Viabilidade'!$O$10)^(($C18-1)/12)) -> 3049.1891 | E18: =D18*'11-Viabilidade'!$L$12 -> 169.39939 | F18: =D18*'11-Viabilidade'!$K$14 -> 0 | G18: =D18*'11-Viabilidade'!$K$15 -> 152.45945 | H18: =IF(D18=0,'11-Viabilidade'!$K$16+'11-Viabilidade'!$K$17,('11-Viabilidade'!$L$11)*((1+'11-Viabilidade'!$O$10)^(($C18-1)/12))) -> 398.65324 | I18: ='12-SAC Viabilidade'!G21 -> 2439.6558 | J18: ='12-SAC Viabilidade'!H21 -> 233714.29 | K18: =(D18-F18)*'11-Viabilidade'!$O$16 -> 457.37836 | L18: =D18-(E18+F18+G18+H18+I18+K18) -> -568.35713 | M18: =D18-(E18+F18+G18+H18+K18) -> 1871.2986 | P18: =IF(B18<='11-Viabilidade'!$G$11,(P17+(P17*'11-Viabilidade'!$H$12)),0) -> 0 | Q18: =IF(B18='11-Viabilidade'!$G$11,'11-Viabilidade'!$G$16,0)*(1+'11-Viabilidade'!$G$12)^((B18-1)/12) -> 0 | R18: =-SUM(O18:Q18) -> 0 | S18: =IF(R18<>0,0,S17+1) -> 11 | T18: =IF($S18<'11-Viabilidade'!$C$24,0,$S18-'11-Viabilidade'!$C$24) -> 5 | U18: =IF(T18>0,'11-Viabilidade'!$K$10,0)*((1+'11-Viabilidade'!$O$10)^(($T18-1)/12)) -> 3049.1891 | V18: =U18*'11-Viabilidade'!$L$12 -> 169.39939 | W18: =U18*'11-Viabilidade'!$K$14 -> 0 | X18: =U18*'11-Viabilidade'!$K$15 -> 152.45945 | Y18: =IF(AND(U18=0,S18=0),0,IF(AND(U18=0,S18<>0),'11-Viabilidade'!$K$16+'11-Viabilidade'!$K$17,('11-Viabilidade'!$L$11)*((1+'11-Viabilidade'!$O$10)^(($C18-1)/12)))) -> 398.65324 | Z18: =IFERROR(VLOOKUP(S18,'12-SAC Viabilidade'!$B$11:$G$430,6,FALSE),0) -> 2439.6558 | AA18: =IFERROR(VLOOKUP(S18,'12-SAC Viabilidade'!$B$11:$H$430,7,FALSE),0) -> 233714.29 | AB18: =(U18-W18)*'11-Viabilidade'!$O$16 -> 457.37836 | AC18: =U18-(V18+W18+X18+Y18+Z18+AB18-R18) -> -568.35713 | AD18: =U18-(V18+W18+X18+Y18+AB18) -> 1871.2986
A19: 2º Ano | B19: =IF(AND(B18>0,B18<'11-Viabilidade'!$P$14),B18+1,0) -> 12 | C19: =IF($B19<'11-Viabilidade'!$C$24,0,$B19-'11-Viabilidade'!$C$24) -> 6 | D19: =IF(C19>0,'11-Viabilidade'!$K$10,0)*((1+'11-Viabilidade'!$O$10)^(($C19-1)/12)) -> 3061.6118 | E19: =D19*'11-Viabilidade'!$L$12 -> 170.08955 | F19: =D19*'11-Viabilidade'!$K$14 -> 0 | G19: =D19*'11-Viabilidade'!$K$15 -> 153.08059 | H19: =IF(D19=0,'11-Viabilidade'!$K$16+'11-Viabilidade'!$K$17,('11-Viabilidade'!$L$11)*((1+'11-Viabilidade'!$O$10)^(($C19-1)/12))) -> 400.2774 | I19: ='12-SAC Viabilidade'!G22 -> 2435.0991 | J19: ='12-SAC Viabilidade'!H22 -> 233142.86 | K19: =(D19-F19)*'11-Viabilidade'!$O$16 -> 459.24178 | L19: =D19-(E19+F19+G19+H19+I19+K19) -> -556.17658 | M19: =D19-(E19+F19+G19+H19+K19) -> 1878.9225 | P19: =IF(B19<='11-Viabilidade'!$G$11,(P18+(P18*'11-Viabilidade'!$H$12)),0) -> 0 | Q19: =IF(B19='11-Viabilidade'!$G$11,'11-Viabilidade'!$G$16,0)*(1+'11-Viabilidade'!$G$12)^((B19-1)/12) -> 0 | R19: =-SUM(O19:Q19) -> 0 | S19: =IF(R19<>0,0,S18+1) -> 12 | T19: =IF($S19<'11-Viabilidade'!$C$24,0,$S19-'11-Viabilidade'!$C$24) -> 6 | U19: =IF(T19>0,'11-Viabilidade'!$K$10,0)*((1+'11-Viabilidade'!$O$10)^(($T19-1)/12)) -> 3061.6118 | V19: =U19*'11-Viabilidade'!$L$12 -> 170.08955 | W19: =U19*'11-Viabilidade'!$K$14 -> 0 | X19: =U19*'11-Viabilidade'!$K$15 -> 153.08059 | Y19: =IF(AND(U19=0,S19=0),0,IF(AND(U19=0,S19<>0),'11-Viabilidade'!$K$16+'11-Viabilidade'!$K$17,('11-Viabilidade'!$L$11)*((1+'11-Viabilidade'!$O$10)^(($C19-1)/12)))) -> 400.2774 | Z19: =IFERROR(VLOOKUP(S19,'12-SAC Viabilidade'!$B$11:$G$430,6,FALSE),0) -> 2435.0991 | AA19: =IFERROR(VLOOKUP(S19,'12-SAC Viabilidade'!$B$11:$H$430,7,FALSE),0) -> 233142.86 | AB19: =(U19-W19)*'11-Viabilidade'!$O$16 -> 459.24178 | AC19: =U19-(V19+W19+X19+Y19+Z19+AB19-R19) -> -556.17658 | AD19: =U19-(V19+W19+X19+Y19+AB19) -> 1878.9225
B20: =IF(AND(B19>0,B19<'11-Viabilidade'!$P$14),B19+1,0) -> 13 | C20: =IF($B20<'11-Viabilidade'!$C$24,0,$B20-'11-Viabilidade'!$C$24) -> 7 | D20: =IF(C20>0,'11-Viabilidade'!$K$10,0)*((1+'11-Viabilidade'!$O$10)^(($C20-1)/12)) -> 3074.0852 | E20: =D20*'11-Viabilidade'!$L$12 -> 170.78251 | F20: =D20*'11-Viabilidade'!$K$14 -> 0 | G20: =D20*'11-Viabilidade'!$K$15 -> 153.70426 | H20: =IF(D20=0,'11-Viabilidade'!$K$16+'11-Viabilidade'!$K$17,('11-Viabilidade'!$L$11)*((1+'11-Viabilidade'!$O$10)^(($C20-1)/12))) -> 401.90818 | I20: ='12-SAC Viabilidade'!G23 -> 2430.5425 | J20: ='12-SAC Viabilidade'!H23 -> 232571.43 | K20: =(D20-F20)*'11-Viabilidade'!$O$16 -> 461.11278 | L20: =D20-(E20+F20+G20+H20+I20+K20) -> -543.96496 | M20: =D20-(E20+F20+G20+H20+K20) -> 1886.5775 | P20: =IF(B20<='11-Viabilidade'!$G$11,(P19+(P19*'11-Viabilidade'!$H$12)),0) -> 0 | Q20: =IF(B20='11-Viabilidade'!$G$11,'11-Viabilidade'!$G$16,0)*(1+'11-Viabilidade'!$G$12)^((B20-1)/12) -> 0 | R20: =-SUM(O20:Q20) -> 0 | S20: =IF(R20<>0,0,S19+1) -> 13 | T20: =IF($S20<'11-Viabilidade'!$C$24,0,$S20-'11-Viabilidade'!$C$24) -> 7 | U20: =IF(T20>0,'11-Viabilidade'!$K$10,0)*((1+'11-Viabilidade'!$O$10)^(($T20-1)/12)) -> 3074.0852 | V20: =U20*'11-Viabilidade'!$L$12 -> 170.78251 | W20: =U20*'11-Viabilidade'!$K$14 -> 0 | X20: =U20*'11-Viabilidade'!$K$15 -> 153.70426 | Y20: =IF(AND(U20=0,S20=0),0,IF(AND(U20=0,S20<>0),'11-Viabilidade'!$K$16+'11-Viabilidade'!$K$17,('11-Viabilidade'!$L$11)*((1+'11-Viabilidade'!$O$10)^(($C20-1)/12)))) -> 401.90818 | Z20: =IFERROR(VLOOKUP(S20,'12-SAC Viabilidade'!$B$11:$G$430,6,FALSE),0) -> 2430.5425 | AA20: =IFERROR(VLOOKUP(S20,'12-SAC Viabilidade'!$B$11:$H$430,7,FALSE),0) -> 232571.43 | AB20: =(U20-W20)*'11-Viabilidade'!$O$16 -> 461.11278 | AC20: =U20-(V20+W20+X20+Y20+Z20+AB20-R20) -> -543.96496 | AD20: =U20-(V20+W20+X20+Y20+AB20) -> 1886.5775
B21: =IF(AND(B20>0,B20<'11-Viabilidade'!$P$14),B20+1,0) -> 14 | C21: =IF($B21<'11-Viabilidade'!$C$24,0,$B21-'11-Viabilidade'!$C$24) -> 8 | D21: =IF(C21>0,'11-Viabilidade'!$K$10,0)*((1+'11-Viabilidade'!$O$10)^(($C21-1)/12)) -> 3086.6094 | E21: =D21*'11-Viabilidade'!$L$12 -> 171.4783 | F21: =D21*'11-Viabilidade'!$K$14 -> 0 | G21: =D21*'11-Viabilidade'!$K$15 -> 154.33047 | H21: =IF(D21=0,'11-Viabilidade'!$K$16+'11-Viabilidade'!$K$17,('11-Viabilidade'!$L$11)*((1+'11-Viabilidade'!$O$10)^(($C21-1)/12))) -> 403.5456 | I21: ='12-SAC Viabilidade'!G24 -> 2425.9858 | J21: ='12-SAC Viabilidade'!H24 -> 232000 | K21: =(D21-F21)*'11-Viabilidade'!$O$16 -> 462.99142 | L21: =D21-(E21+F21+G21+H21+I21+K21) -> -531.72216 | M21: =D21-(E21+F21+G21+H21+K21) -> 1894.2636 | P21: =IF(B21<='11-Viabilidade'!$G$11,(P20+(P20*'11-Viabilidade'!$H$12)),0) -> 0 | Q21: =IF(B21='11-Viabilidade'!$G$11,'11-Viabilidade'!$G$16,0)*(1+'11-Viabilidade'!$G$12)^((B21-1)/12) -> 0 | R21: =-SUM(O21:Q21) -> 0 | S21: =IF(R21<>0,0,S20+1) -> 14 | T21: =IF($S21<'11-Viabilidade'!$C$24,0,$S21-'11-Viabilidade'!$C$24) -> 8 | U21: =IF(T21>0,'11-Viabilidade'!$K$10,0)*((1+'11-Viabilidade'!$O$10)^(($T21-1)/12)) -> 3086.6094 | V21: =U21*'11-Viabilidade'!$L$12 -> 171.4783 | W21: =U21*'11-Viabilidade'!$K$14 -> 0 | X21: =U21*'11-Viabilidade'!$K$15 -> 154.33047 | Y21: =IF(AND(U21=0,S21=0),0,IF(AND(U21=0,S21<>0),'11-Viabilidade'!$K$16+'11-Viabilidade'!$K$17,('11-Viabilidade'!$L$11)*((1+'11-Viabilidade'!$O$10)^(($C21-1)/12)))) -> 403.5456 | Z21: =IFERROR(VLOOKUP(S21,'12-SAC Viabilidade'!$B$11:$G$430,6,FALSE),0) -> 2425.9858 | AA21: =IFERROR(VLOOKUP(S21,'12-SAC Viabilidade'!$B$11:$H$430,7,FALSE),0) -> 232000 | AB21: =(U21-W21)*'11-Viabilidade'!$O$16 -> 462.99142 | AC21: =U21-(V21+W21+X21+Y21+Z21+AB21-R21) -> -531.72216 | AD21: =U21-(V21+W21+X21+Y21+AB21) -> 1894.2636
B22: =IF(AND(B21>0,B21<'11-Viabilidade'!$P$14),B21+1,0) -> 15 | C22: =IF($B22<'11-Viabilidade'!$C$24,0,$B22-'11-Viabilidade'!$C$24) -> 9 | D22: =IF(C22>0,'11-Viabilidade'!$K$10,0)*((1+'11-Viabilidade'!$O$10)^(($C22-1)/12)) -> 3099.1847 | E22: =D22*'11-Viabilidade'!$L$12 -> 172.17693 | F22: =D22*'11-Viabilidade'!$K$14 -> 0 | G22: =D22*'11-Viabilidade'!$K$15 -> 154.95923 | H22: =IF(D22=0,'11-Viabilidade'!$K$16+'11-Viabilidade'!$K$17,('11-Viabilidade'!$L$11)*((1+'11-Viabilidade'!$O$10)^(($C22-1)/12))) -> 405.1897 | I22: ='12-SAC Viabilidade'!G25 -> 2421.4292 | J22: ='12-SAC Viabilidade'!H25 -> 231428.57 | K22: =(D22-F22)*'11-Viabilidade'!$O$16 -> 464.8777 | L22: =D22-(E22+F22+G22+H22+I22+K22) -> -519.44805 | M22: =D22-(E22+F22+G22+H22+K22) -> 1901.9811 | P22: =IF(B22<='11-Viabilidade'!$G$11,(P21+(P21*'11-Viabilidade'!$H$12)),0) -> 0 | Q22: =IF(B22='11-Viabilidade'!$G$11,'11-Viabilidade'!$G$16,0)*(1+'11-Viabilidade'!$G$12)^((B22-1)/12) -> 0 | R22: =-SUM(O22:Q22) -> 0 | S22: =IF(R22<>0,0,S21+1) -> 15 | T22: =IF($S22<'11-Viabilidade'!$C$24,0,$S22-'11-Viabilidade'!$C$24) -> 9 | U22: =IF(T22>0,'11-Viabilidade'!$K$10,0)*((1+'11-Viabilidade'!$O$10)^(($T22-1)/12)) -> 3099.1847 | V22: =U22*'11-Viabilidade'!$L$12 -> 172.17693 | W22: =U22*'11-Viabilidade'!$K$14 -> 0 | X22: =U22*'11-Viabilidade'!$K$15 -> 154.95923 | Y22: =IF(AND(U22=0,S22=0),0,IF(AND(U22=0,S22<>0),'11-Viabilidade'!$K$16+'11-Viabilidade'!$K$17,('11-Viabilidade'!$L$11)*((1+'11-Viabilidade'!$O$10)^(($C22-1)/12)))) -> 405.1897 | Z22: =IFERROR(VLOOKUP(S22,'12-SAC Viabilidade'!$B$11:$G$430,6,FALSE),0) -> 2421.4292 | AA22: =IFERROR(VLOOKUP(S22,'12-SAC Viabilidade'!$B$11:$H$430,7,FALSE),0) -> 231428.57 | AB22: =(U22-W22)*'11-Viabilidade'!$O$16 -> 464.8777 | AC22: =U22-(V22+W22+X22+Y22+Z22+AB22-R22) -> -519.44805 | AD22: =U22-(V22+W22+X22+Y22+AB22) -> 1901.9811
B23: =IF(AND(B22>0,B22<'11-Viabilidade'!$P$14),B22+1,0) -> 16 | C23: =IF($B23<'11-Viabilidade'!$C$24,0,$B23-'11-Viabilidade'!$C$24) -> 10 | D23: =IF(C23>0,'11-Viabilidade'!$K$10,0)*((1+'11-Viabilidade'!$O$10)^(($C23-1)/12)) -> 3111.8111 | E23: =D23*'11-Viabilidade'!$L$12 -> 172.8784 | F23: =D23*'11-Viabilidade'!$K$14 -> 0 | G23: =D23*'11-Viabilidade'!$K$15 -> 155.59056 | H23: =IF(D23=0,'11-Viabilidade'!$K$16+'11-Viabilidade'!$K$17,('11-Viabilidade'!$L$11)*((1+'11-Viabilidade'!$O$10)^(($C23-1)/12))) -> 406.84049 | I23: ='12-SAC Viabilidade'!G26 -> 2416.8725 | J23: ='12-SAC Viabilidade'!H26 -> 230857.14 | K23: =(D23-F23)*'11-Viabilidade'!$O$16 -> 466.77167 | L23: =D23-(E23+F23+G23+H23+I23+K23) -> -507.14249 | M23: =D23-(E23+F23+G23+H23+K23) -> 1909.73 | P23: =IF(B23<='11-Viabilidade'!$G$11,(P22+(P22*'11-Viabilidade'!$H$12)),0) -> 0 | Q23: =IF(B23='11-Viabilidade'!$G$11,'11-Viabilidade'!$G$16,0)*(1+'11-Viabilidade'!$G$12)^((B23-1)/12) -> 0 | R23: =-SUM(O23:Q23) -> 0 | S23: =IF(R23<>0,0,S22+1) -> 16 | T23: =IF($S23<'11-Viabilidade'!$C$24,0,$S23-'11-Viabilidade'!$C$24) -> 10 | U23: =IF(T23>0,'11-Viabilidade'!$K$10,0)*((1+'11-Viabilidade'!$O$10)^(($T23-1)/12)) -> 3111.8111 | V23: =U23*'11-Viabilidade'!$L$12 -> 172.8784 | W23: =U23*'11-Viabilidade'!$K$14 -> 0 | X23: =U23*'11-Viabilidade'!$K$15 -> 155.59056 | Y23: =IF(AND(U23=0,S23=0),0,IF(AND(U23=0,S23<>0),'11-Viabilidade'!$K$16+'11-Viabilidade'!$K$17,('11-Viabilidade'!$L$11)*((1+'11-Viabilidade'!$O$10)^(($C23-1)/12)))) -> 406.84049 | Z23: =IFERROR(VLOOKUP(S23,'12-SAC Viabilidade'!$B$11:$G$430,6,FALSE),0) -> 2416.8725 | AA23: =IFERROR(VLOOKUP(S23,'12-SAC Viabilidade'!$B$11:$H$430,7,FALSE),0) -> 230857.14 | AB23: =(U23-W23)*'11-Viabilidade'!$O$16 -> 466.77167 | AC23: =U23-(V23+W23+X23+Y23+Z23+AB23-R23) -> -507.14249 | AD23: =U23-(V23+W23+X23+Y23+AB23) -> 1909.73
B24: =IF(AND(B23>0,B23<'11-Viabilidade'!$P$14),B23+1,0) -> 17 | C24: =IF($B24<'11-Viabilidade'!$C$24,0,$B24-'11-Viabilidade'!$C$24) -> 11 | D24: =IF(C24>0,'11-Viabilidade'!$K$10,0)*((1+'11-Viabilidade'!$O$10)^(($C24-1)/12)) -> 3124.489 | E24: =D24*'11-Viabilidade'!$L$12 -> 173.58272 | F24: =D24*'11-Viabilidade'!$K$14 -> 0 | G24: =D24*'11-Viabilidade'!$K$15 -> 156.22445 | H24: =IF(D24=0,'11-Viabilidade'!$K$16+'11-Viabilidade'!$K$17,('11-Viabilidade'!$L$11)*((1+'11-Viabilidade'!$O$10)^(($C24-1)/12))) -> 408.49801 | I24: ='12-SAC Viabilidade'!G27 -> 2412.3158 | J24: ='12-SAC Viabilidade'!H27 -> 230285.71 | K24: =(D24-F24)*'11-Viabilidade'!$O$16 -> 468.67335 | L24: =D24-(E24+F24+G24+H24+I24+K24) -> -494.80536 | M24: =D24-(E24+F24+G24+H24+K24) -> 1917.5105 | P24: =IF(B24<='11-Viabilidade'!$G$11,(P23+(P23*'11-Viabilidade'!$H$12)),0) -> 0 | Q24: =IF(B24='11-Viabilidade'!$G$11,'11-Viabilidade'!$G$16,0)*(1+'11-Viabilidade'!$G$12)^((B24-1)/12) -> 0 | R24: =-SUM(O24:Q24) -> 0 | S24: =IF(R24<>0,0,S23+1) -> 17 | T24: =IF($S24<'11-Viabilidade'!$C$24,0,$S24-'11-Viabilidade'!$C$24) -> 11 | U24: =IF(T24>0,'11-Viabilidade'!$K$10,0)*((1+'11-Viabilidade'!$O$10)^(($T24-1)/12)) -> 3124.489 | V24: =U24*'11-Viabilidade'!$L$12 -> 173.58272 | W24: =U24*'11-Viabilidade'!$K$14 -> 0 | X24: =U24*'11-Viabilidade'!$K$15 -> 156.22445 | Y24: =IF(AND(U24=0,S24=0),0,IF(AND(U24=0,S24<>0),'11-Viabilidade'!$K$16+'11-Viabilidade'!$K$17,('11-Viabilidade'!$L$11)*((1+'11-Viabilidade'!$O$10)^(($C24-1)/12)))) -> 408.49801 | Z24: =IFERROR(VLOOKUP(S24,'12-SAC Viabilidade'!$B$11:$G$430,6,FALSE),0) -> 2412.3158 | AA24: =IFERROR(VLOOKUP(S24,'12-SAC Viabilidade'!$B$11:$H$430,7,FALSE),0) -> 230285.71 | AB24: =(U24-W24)*'11-Viabilidade'!$O$16 -> 468.67335 | AC24: =U24-(V24+W24+X24+Y24+Z24+AB24-R24) -> -494.80536 | AD24: =U24-(V24+W24+X24+Y24+AB24) -> 1917.5105
B25: =IF(AND(B24>0,B24<'11-Viabilidade'!$P$14),B24+1,0) -> 18 | C25: =IF($B25<'11-Viabilidade'!$C$24,0,$B25-'11-Viabilidade'!$C$24) -> 12 | D25: =IF(C25>0,'11-Viabilidade'!$K$10,0)*((1+'11-Viabilidade'!$O$10)^(($C25-1)/12)) -> 3137.2186 | E25: =D25*'11-Viabilidade'!$L$12 -> 174.28992 | F25: =D25*'11-Viabilidade'!$K$14 -> 0 | G25: =D25*'11-Viabilidade'!$K$15 -> 156.86093 | H25: =IF(D25=0,'11-Viabilidade'!$K$16+'11-Viabilidade'!$K$17,('11-Viabilidade'!$L$11)*((1+'11-Viabilidade'!$O$10)^(($C25-1)/12))) -> 410.16228 | I25: ='12-SAC Viabilidade'!G28 -> 2407.7592 | J25: ='12-SAC Viabilidade'!H28 -> 229714.29 | K25: =(D25-F25)*'11-Viabilidade'!$O$16 -> 470.58279 | L25: =D25-(E25+F25+G25+H25+I25+K25) -> -482.43653 | M25: =D25-(E25+F25+G25+H25+K25) -> 1925.3227 | P25: =IF(B25<='11-Viabilidade'!$G$11,(P24+(P24*'11-Viabilidade'!$H$12)),0) -> 0 | Q25: =IF(B25='11-Viabilidade'!$G$11,'11-Viabilidade'!$G$16,0)*(1+'11-Viabilidade'!$G$12)^((B25-1)/12) -> 0 | R25: =-SUM(O25:Q25) -> 0 | S25: =IF(R25<>0,0,S24+1) -> 18 | T25: =IF($S25<'11-Viabilidade'!$C$24,0,$S25-'11-Viabilidade'!$C$24) -> 12 | U25: =IF(T25>0,'11-Viabilidade'!$K$10,0)*((1+'11-Viabilidade'!$O$10)^(($T25-1)/12)) -> 3137.2186 | V25: =U25*'11-Viabilidade'!$L$12 -> 174.28992 | W25: =U25*'11-Viabilidade'!$K$14 -> 0 | X25: =U25*'11-Viabilidade'!$K$15 -> 156.86093 | Y25: =IF(AND(U25=0,S25=0),0,IF(AND(U25=0,S25<>0),'11-Viabilidade'!$K$16+'11-Viabilidade'!$K$17,('11-Viabilidade'!$L$11)*((1+'11-Viabilidade'!$O$10)^(($C25-1)/12)))) -> 410.16228 | Z25: =IFERROR(VLOOKUP(S25,'12-SAC Viabilidade'!$B$11:$G$430,6,FALSE),0) -> 2407.7592 | AA25: =IFERROR(VLOOKUP(S25,'12-SAC Viabilidade'!$B$11:$H$430,7,FALSE),0) -> 229714.29 | AB25: =(U25-W25)*'11-Viabilidade'!$O$16 -> 470.58279 | AC25: =U25-(V25+W25+X25+Y25+Z25+AB25-R25) -> -482.43653 | AD25: =U25-(V25+W25+X25+Y25+AB25) -> 1925.3227
B26: =IF(AND(B25>0,B25<'11-Viabilidade'!$P$14),B25+1,0) -> 19 | C26: =IF($B26<'11-Viabilidade'!$C$24,0,$B26-'11-Viabilidade'!$C$24) -> 13 | D26: =IF(C26>0,'11-Viabilidade'!$K$10,0)*((1+'11-Viabilidade'!$O$10)^(($C26-1)/12)) -> 3150 | E26: =D26*'11-Viabilidade'!$L$12 -> 175 | F26: =D26*'11-Viabilidade'!$K$14 -> 0 | G26: =D26*'11-Viabilidade'!$K$15 -> 157.5 | H26: =IF(D26=0,'11-Viabilidade'!$K$16+'11-Viabilidade'!$K$17,('11-Viabilidade'!$L$11)*((1+'11-Viabilidade'!$O$10)^(($C26-1)/12))) -> 411.83333 | I26: ='12-SAC Viabilidade'!G29 -> 2403.2025 | J26: ='12-SAC Viabilidade'!H29 -> 229142.86 | K26: =(D26-F26)*'11-Viabilidade'!$O$16 -> 472.5 | L26: =D26-(E26+F26+G26+H26+I26+K26) -> -470.03588 | M26: =D26-(E26+F26+G26+H26+K26) -> 1933.1667 | P26: =IF(B26<='11-Viabilidade'!$G$11,(P25+(P25*'11-Viabilidade'!$H$12)),0) -> 0 | Q26: =IF(B26='11-Viabilidade'!$G$11,'11-Viabilidade'!$G$16,0)*(1+'11-Viabilidade'!$G$12)^((B26-1)/12) -> 0 | R26: =-SUM(O26:Q26) -> 0 | S26: =IF(R26<>0,0,S25+1) -> 19 | T26: =IF($S26<'11-Viabilidade'!$C$24,0,$S26-'11-Viabilidade'!$C$24) -> 13 | U26: =IF(T26>0,'11-Viabilidade'!$K$10,0)*((1+'11-Viabilidade'!$O$10)^(($T26-1)/12)) -> 3150 | V26: =U26*'11-Viabilidade'!$L$12 -> 175 | W26: =U26*'11-Viabilidade'!$K$14 -> 0 | X26: =U26*'11-Viabilidade'!$K$15 -> 157.5 | Y26: =IF(AND(U26=0,S26=0),0,IF(AND(U26=0,S26<>0),'11-Viabilidade'!$K$16+'11-Viabilidade'!$K$17,('11-Viabilidade'!$L$11)*((1+'11-Viabilidade'!$O$10)^(($C26-1)/12)))) -> 411.83333 | Z26: =IFERROR(VLOOKUP(S26,'12-SAC Viabilidade'!$B$11:$G$430,6,FALSE),0) -> 2403.2025 | AA26: =IFERROR(VLOOKUP(S26,'12-SAC Viabilidade'!$B$11:$H$430,7,FALSE),0) -> 229142.86 | AB26: =(U26-W26)*'11-Viabilidade'!$O$16 -> 472.5 | AC26: =U26-(V26+W26+X26+Y26+Z26+AB26-R26) -> -470.03588 | AD26: =U26-(V26+W26+X26+Y26+AB26) -> 1933.1667
B27: =IF(AND(B26>0,B26<'11-Viabilidade'!$P$14),B26+1,0) -> 20 | C27: =IF($B27<'11-Viabilidade'!$C$24,0,$B27-'11-Viabilidade'!$C$24) -> 14 | D27: =IF(C27>0,'11-Viabilidade'!$K$10,0)*((1+'11-Viabilidade'!$O$10)^(($C27-1)/12)) -> 3162.8335 | E27: =D27*'11-Viabilidade'!$L$12 -> 175.71297 | F27: =D27*'11-Viabilidade'!$K$14 -> 0 | G27: =D27*'11-Viabilidade'!$K$15 -> 158.14167 | H27: =IF(D27=0,'11-Viabilidade'!$K$16+'11-Viabilidade'!$K$17,('11-Viabilidade'!$L$11)*((1+'11-Viabilidade'!$O$10)^(($C27-1)/12))) -> 413.51119 | I27: ='12-SAC Viabilidade'!G30 -> 2398.6459 | J27: ='12-SAC Viabilidade'!H30 -> 228571.43 | K27: =(D27-F27)*'11-Viabilidade'!$O$16 -> 474.42502 | L27: =D27-(E27+F27+G27+H27+I27+K27) -> -457.60327 | M27: =D27-(E27+F27+G27+H27+K27) -> 1941.0426 | P27: =IF(B27<='11-Viabilidade'!$G$11,(P26+(P26*'11-Viabilidade'!$H$12)),0) -> 0 | Q27: =IF(B27='11-Viabilidade'!$G$11,'11-Viabilidade'!$G$16,0)*(1+'11-Viabilidade'!$G$12)^((B27-1)/12) -> 0 | R27: =-SUM(O27:Q27) -> 0 | S27: =IF(R27<>0,0,S26+1) -> 20 | T27: =IF($S27<'11-Viabilidade'!$C$24,0,$S27-'11-Viabilidade'!$C$24) -> 14 | U27: =IF(T27>0,'11-Viabilidade'!$K$10,0)*((1+'11-Viabilidade'!$O$10)^(($T27-1)/12)) -> 3162.8335 | V27: =U27*'11-Viabilidade'!$L$12 -> 175.71297 | W27: =U27*'11-Viabilidade'!$K$14 -> 0 | X27: =U27*'11-Viabilidade'!$K$15 -> 158.14167 | Y27: =IF(AND(U27=0,S27=0),0,IF(AND(U27=0,S27<>0),'11-Viabilidade'!$K$16+'11-Viabilidade'!$K$17,('11-Viabilidade'!$L$11)*((1+'11-Viabilidade'!$O$10)^(($C27-1)/12)))) -> 413.51119 | Z27: =IFERROR(VLOOKUP(S27,'12-SAC Viabilidade'!$B$11:$G$430,6,FALSE),0) -> 2398.6459 | AA27: =IFERROR(VLOOKUP(S27,'12-SAC Viabilidade'!$B$11:$H$430,7,FALSE),0) -> 228571.43 | AB27: =(U27-W27)*'11-Viabilidade'!$O$16 -> 474.42502 | AC27: =U27-(V27+W27+X27+Y27+Z27+AB27-R27) -> -457.60327 | AD27: =U27-(V27+W27+X27+Y27+AB27) -> 1941.0426
B28: =IF(AND(B27>0,B27<'11-Viabilidade'!$P$14),B27+1,0) -> 21 | C28: =IF($B28<'11-Viabilidade'!$C$24,0,$B28-'11-Viabilidade'!$C$24) -> 15 | D28: =IF(C28>0,'11-Viabilidade'!$K$10,0)*((1+'11-Viabilidade'!$O$10)^(($C28-1)/12)) -> 3175.7193 | E28: =D28*'11-Viabilidade'!$L$12 -> 176.42885 | F28: =D28*'11-Viabilidade'!$K$14 -> 0 | G28: =D28*'11-Viabilidade'!$K$15 -> 158.78596 | H28: =IF(D28=0,'11-Viabilidade'!$K$16+'11-Viabilidade'!$K$17,('11-Viabilidade'!$L$11)*((1+'11-Viabilidade'!$O$10)^(($C28-1)/12))) -> 415.19589 | I28: ='12-SAC Viabilidade'!G31 -> 2394.0892 | J28: ='12-SAC Viabilidade'!H31 -> 228000 | K28: =(D28-F28)*'11-Viabilidade'!$O$16 -> 476.35789 | L28: =D28-(E28+F28+G28+H28+I28+K28) -> -445.13857 | M28: =D28-(E28+F28+G28+H28+K28) -> 1948.9507 | P28: =IF(B28<='11-Viabilidade'!$G$11,(P27+(P27*'11-Viabilidade'!$H$12)),0) -> 0 | Q28: =IF(B28='11-Viabilidade'!$G$11,'11-Viabilidade'!$G$16,0)*(1+'11-Viabilidade'!$G$12)^((B28-1)/12) -> 0 | R28: =-SUM(O28:Q28) -> 0 | S28: =IF(R28<>0,0,S27+1) -> 21 | T28: =IF($S28<'11-Viabilidade'!$C$24,0,$S28-'11-Viabilidade'!$C$24) -> 15 | U28: =IF(T28>0,'11-Viabilidade'!$K$10,0)*((1+'11-Viabilidade'!$O$10)^(($T28-1)/12)) -> 3175.7193 | V28: =U28*'11-Viabilidade'!$L$12 -> 176.42885 | W28: =U28*'11-Viabilidade'!$K$14 -> 0 | X28: =U28*'11-Viabilidade'!$K$15 -> 158.78596 | Y28: =IF(AND(U28=0,S28=0),0,IF(AND(U28=0,S28<>0),'11-Viabilidade'!$K$16+'11-Viabilidade'!$K$17,('11-Viabilidade'!$L$11)*((1+'11-Viabilidade'!$O$10)^(($C28-1)/12)))) -> 415.19589 | Z28: =IFERROR(VLOOKUP(S28,'12-SAC Viabilidade'!$B$11:$G$430,6,FALSE),0) -> 2394.0892 | AA28: =IFERROR(VLOOKUP(S28,'12-SAC Viabilidade'!$B$11:$H$430,7,FALSE),0) -> 228000 | AB28: =(U28-W28)*'11-Viabilidade'!$O$16 -> 476.35789 | AC28: =U28-(V28+W28+X28+Y28+Z28+AB28-R28) -> -445.13857 | AD28: =U28-(V28+W28+X28+Y28+AB28) -> 1948.9507
B29: =IF(AND(B28>0,B28<'11-Viabilidade'!$P$14),B28+1,0) -> 22 | C29: =IF($B29<'11-Viabilidade'!$C$24,0,$B29-'11-Viabilidade'!$C$24) -> 16 | D29: =IF(C29>0,'11-Viabilidade'!$K$10,0)*((1+'11-Viabilidade'!$O$10)^(($C29-1)/12)) -> 3188.6575 | E29: =D29*'11-Viabilidade'!$L$12 -> 177.14764 | F29: =D29*'11-Viabilidade'!$K$14 -> 0 | G29: =D29*'11-Viabilidade'!$K$15 -> 159.43288 | H29: =IF(D29=0,'11-Viabilidade'!$K$16+'11-Viabilidade'!$K$17,('11-Viabilidade'!$L$11)*((1+'11-Viabilidade'!$O$10)^(($C29-1)/12))) -> 416.88745 | I29: ='12-SAC Viabilidade'!G32 -> 2389.5326 | J29: ='12-SAC Viabilidade'!H32 -> 227428.57 | K29: =(D29-F29)*'11-Viabilidade'!$O$16 -> 478.29863 | L29: =D29-(E29+F29+G29+H29+I29+K29) -> -432.64165 | M29: =D29-(E29+F29+G29+H29+K29) -> 1956.8909 | P29: =IF(B29<='11-Viabilidade'!$G$11,(P28+(P28*'11-Viabilidade'!$H$12)),0) -> 0 | Q29: =IF(B29='11-Viabilidade'!$G$11,'11-Viabilidade'!$G$16,0)*(1+'11-Viabilidade'!$G$12)^((B29-1)/12) -> 0 | R29: =-SUM(O29:Q29) -> 0 | S29: =IF(R29<>0,0,S28+1) -> 22 | T29: =IF($S29<'11-Viabilidade'!$C$24,0,$S29-'11-Viabilidade'!$C$24) -> 16 | U29: =IF(T29>0,'11-Viabilidade'!$K$10,0)*((1+'11-Viabilidade'!$O$10)^(($T29-1)/12)) -> 3188.6575 | V29: =U29*'11-Viabilidade'!$L$12 -> 177.14764 | W29: =U29*'11-Viabilidade'!$K$14 -> 0 | X29: =U29*'11-Viabilidade'!$K$15 -> 159.43288 | Y29: =IF(AND(U29=0,S29=0),0,IF(AND(U29=0,S29<>0),'11-Viabilidade'!$K$16+'11-Viabilidade'!$K$17,('11-Viabilidade'!$L$11)*((1+'11-Viabilidade'!$O$10)^(($C29-1)/12)))) -> 416.88745 | Z29: =IFERROR(VLOOKUP(S29,'12-SAC Viabilidade'!$B$11:$G$430,6,FALSE),0) -> 2389.5326 | AA29: =IFERROR(VLOOKUP(S29,'12-SAC Viabilidade'!$B$11:$H$430,7,FALSE),0) -> 227428.57 | AB29: =(U29-W29)*'11-Viabilidade'!$O$16 -> 478.29863 | AC29: =U29-(V29+W29+X29+Y29+Z29+AB29-R29) -> -432.64165 | AD29: =U29-(V29+W29+X29+Y29+AB29) -> 1956.8909
B30: =IF(AND(B29>0,B29<'11-Viabilidade'!$P$14),B29+1,0) -> 23 | C30: =IF($B30<'11-Viabilidade'!$C$24,0,$B30-'11-Viabilidade'!$C$24) -> 17 | D30: =IF(C30>0,'11-Viabilidade'!$K$10,0)*((1+'11-Viabilidade'!$O$10)^(($C30-1)/12)) -> 3201.6485 | E30: =D30*'11-Viabilidade'!$L$12 -> 177.86936 | F30: =D30*'11-Viabilidade'!$K$14 -> 0 | G30: =D30*'11-Viabilidade'!$K$15 -> 160.08243 | H30: =IF(D30=0,'11-Viabilidade'!$K$16+'11-Viabilidade'!$K$17,('11-Viabilidade'!$L$11)*((1+'11-Viabilidade'!$O$10)^(($C30-1)/12))) -> 418.5859 | I30: ='12-SAC Viabilidade'!G33 -> 2384.9759 | J30: ='12-SAC Viabilidade'!H33 -> 226857.14 | K30: =(D30-F30)*'11-Viabilidade'!$O$16 -> 480.24728 | L30: =D30-(E30+F30+G30+H30+I30+K30) -> -420.11238 | M30: =D30-(E30+F30+G30+H30+K30) -> 1964.8636 | P30: =IF(B30<='11-Viabilidade'!$G$11,(P29+(P29*'11-Viabilidade'!$H$12)),0) -> 0 | Q30: =IF(B30='11-Viabilidade'!$G$11,'11-Viabilidade'!$G$16,0)*(1+'11-Viabilidade'!$G$12)^((B30-1)/12) -> 0 | R30: =-SUM(O30:Q30) -> 0 | S30: =IF(R30<>0,0,S29+1) -> 23 | T30: =IF($S30<'11-Viabilidade'!$C$24,0,$S30-'11-Viabilidade'!$C$24) -> 17 | U30: =IF(T30>0,'11-Viabilidade'!$K$10,0)*((1+'11-Viabilidade'!$O$10)^(($T30-1)/12)) -> 3201.6485 | V30: =U30*'11-Viabilidade'!$L$12 -> 177.86936 | W30: =U30*'11-Viabilidade'!$K$14 -> 0 | X30: =U30*'11-Viabilidade'!$K$15 -> 160.08243 | Y30: =IF(AND(U30=0,S30=0),0,IF(AND(U30=0,S30<>0),'11-Viabilidade'!$K$16+'11-Viabilidade'!$K$17,('11-Viabilidade'!$L$11)*((1+'11-Viabilidade'!$O$10)^(($C30-1)/12)))) -> 418.5859 | Z30: =IFERROR(VLOOKUP(S30,'12-SAC Viabilidade'!$B$11:$G$430,6,FALSE),0) -> 2384.9759 | AA30: =IFERROR(VLOOKUP(S30,'12-SAC Viabilidade'!$B$11:$H$430,7,FALSE),0) -> 226857.14 | AB30: =(U30-W30)*'11-Viabilidade'!$O$16 -> 480.24728 | AC30: =U30-(V30+W30+X30+Y30+Z30+AB30-R30) -> -420.11238 | AD30: =U30-(V30+W30+X30+Y30+AB30) -> 1964.8636
A31: 3º Ano | B31: =IF(AND(B30>0,B30<'11-Viabilidade'!$P$14),B30+1,0) -> 24 | C31: =IF($B31<'11-Viabilidade'!$C$24,0,$B31-'11-Viabilidade'!$C$24) -> 18 | D31: =IF(C31>0,'11-Viabilidade'!$K$10,0)*((1+'11-Viabilidade'!$O$10)^(($C31-1)/12)) -> 3214.6924 | E31: =D31*'11-Viabilidade'!$L$12 -> 178.59402 | F31: =D31*'11-Viabilidade'!$K$14 -> 0 | G31: =D31*'11-Viabilidade'!$K$15 -> 160.73462 | H31: =IF(D31=0,'11-Viabilidade'!$K$16+'11-Viabilidade'!$K$17,('11-Viabilidade'!$L$11)*((1+'11-Viabilidade'!$O$10)^(($C31-1)/12))) -> 420.29127 | I31: ='12-SAC Viabilidade'!G34 -> 2380.4193 | J31: ='12-SAC Viabilidade'!H34 -> 226285.71 | K31: =(D31-F31)*'11-Viabilidade'!$O$16 -> 482.20387 | L31: =D31-(E31+F31+G31+H31+I31+K31) -> -407.55063 | M31: =D31-(E31+F31+G31+H31+K31) -> 1972.8687 | P31: =IF(B31<='11-Viabilidade'!$G$11,(P30+(P30*'11-Viabilidade'!$H$12)),0) -> 0 | Q31: =IF(B31='11-Viabilidade'!$G$11,'11-Viabilidade'!$G$16,0)*(1+'11-Viabilidade'!$G$12)^((B31-1)/12) -> 0 | R31: =-SUM(O31:Q31) -> 0 | S31: =IF(R31<>0,0,S30+1) -> 24 | T31: =IF($S31<'11-Viabilidade'!$C$24,0,$S31-'11-Viabilidade'!$C$24) -> 18 | U31: =IF(T31>0,'11-Viabilidade'!$K$10,0)*((1+'11-Viabilidade'!$O$10)^(($T31-1)/12)) -> 3214.6924 | V31: =U31*'11-Viabilidade'!$L$12 -> 178.59402 | W31: =U31*'11-Viabilidade'!$K$14 -> 0 | X31: =U31*'11-Viabilidade'!$K$15 -> 160.73462 | Y31: =IF(AND(U31=0,S31=0),0,IF(AND(U31=0,S31<>0),'11-Viabilidade'!$K$16+'11-Viabilidade'!$K$17,('11-Viabilidade'!$L$11)*((1+'11-Viabilidade'!$O$10)^(($C31-1)/12)))) -> 420.29127 | Z31: =IFERROR(VLOOKUP(S31,'12-SAC Viabilidade'!$B$11:$G$430,6,FALSE),0) -> 2380.4193 | AA31: =IFERROR(VLOOKUP(S31,'12-SAC Viabilidade'!$B$11:$H$430,7,FALSE),0) -> 226285.71 | AB31: =(U31-W31)*'11-Viabilidade'!$O$16 -> 482.20387 | AC31: =U31-(V31+W31+X31+Y31+Z31+AB31-R31) -> -407.55063 | AD31: =U31-(V31+W31+X31+Y31+AB31) -> 1972.8687
B32: =IF(AND(B31>0,B31<'11-Viabilidade'!$P$14),B31+1,0) -> 25 | C32: =IF($B32<'11-Viabilidade'!$C$24,0,$B32-'11-Viabilidade'!$C$24) -> 19 | D32: =IF(C32>0,'11-Viabilidade'!$K$10,0)*((1+'11-Viabilidade'!$O$10)^(($C32-1)/12)) -> 3227.7895 | E32: =D32*'11-Viabilidade'!$L$12 -> 179.32164 | F32: =D32*'11-Viabilidade'!$K$14 -> 0 | G32: =D32*'11-Viabilidade'!$K$15 -> 161.38947 | H32: =IF(D32=0,'11-Viabilidade'!$K$16+'11-Viabilidade'!$K$17,('11-Viabilidade'!$L$11)*((1+'11-Viabilidade'!$O$10)^(($C32-1)/12))) -> 422.00359 | I32: ='12-SAC Viabilidade'!G35 -> 2375.8626 | J32: ='12-SAC Viabilidade'!H35 -> 225714.29 | K32: =(D32-F32)*'11-Viabilidade'!$O$16 -> 484.16842 | L32: =D32-(E32+F32+G32+H32+I32+K32) -> -394.95627 | M32: =D32-(E32+F32+G32+H32+K32) -> 1980.9064 | P32: =IF(B32<='11-Viabilidade'!$G$11,(P31+(P31*'11-Viabilidade'!$H$12)),0) -> 0 | Q32: =IF(B32='11-Viabilidade'!$G$11,'11-Viabilidade'!$G$16,0)*(1+'11-Viabilidade'!$G$12)^((B32-1)/12) -> 0 | R32: =-SUM(O32:Q32) -> 0 | S32: =IF(R32<>0,0,S31+1) -> 25 | T32: =IF($S32<'11-Viabilidade'!$C$24,0,$S32-'11-Viabilidade'!$C$24) -> 19 | U32: =IF(T32>0,'11-Viabilidade'!$K$10,0)*((1+'11-Viabilidade'!$O$10)^(($T32-1)/12)) -> 3227.7895 | V32: =U32*'11-Viabilidade'!$L$12 -> 179.32164 | W32: =U32*'11-Viabilidade'!$K$14 -> 0 | X32: =U32*'11-Viabilidade'!$K$15 -> 161.38947 | Y32: =IF(AND(U32=0,S32=0),0,IF(AND(U32=0,S32<>0),'11-Viabilidade'!$K$16+'11-Viabilidade'!$K$17,('11-Viabilidade'!$L$11)*((1+'11-Viabilidade'!$O$10)^(($C32-1)/12)))) -> 422.00359 | Z32: =IFERROR(VLOOKUP(S32,'12-SAC Viabilidade'!$B$11:$G$430,6,FALSE),0) -> 2375.8626 | AA32: =IFERROR(VLOOKUP(S32,'12-SAC Viabilidade'!$B$11:$H$430,7,FALSE),0) -> 225714.29 | AB32: =(U32-W32)*'11-Viabilidade'!$O$16 -> 484.16842 | AC32: =U32-(V32+W32+X32+Y32+Z32+AB32-R32) -> -394.95627 | AD32: =U32-(V32+W32+X32+Y32+AB32) -> 1980.9064
B33: =IF(AND(B32>0,B32<'11-Viabilidade'!$P$14),B32+1,0) -> 26 | C33: =IF($B33<'11-Viabilidade'!$C$24,0,$B33-'11-Viabilidade'!$C$24) -> 20 | D33: =IF(C33>0,'11-Viabilidade'!$K$10,0)*((1+'11-Viabilidade'!$O$10)^(($C33-1)/12)) -> 3240.9399 | E33: =D33*'11-Viabilidade'!$L$12 -> 180.05222 | F33: =D33*'11-Viabilidade'!$K$14 -> 0 | G33: =D33*'11-Viabilidade'!$K$15 -> 162.047 | H33: =IF(D33=0,'11-Viabilidade'!$K$16+'11-Viabilidade'!$K$17,('11-Viabilidade'!$L$11)*((1+'11-Viabilidade'!$O$10)^(($C33-1)/12))) -> 423.72288 | I33: ='12-SAC Viabilidade'!G36 -> 2371.306 | J33: ='12-SAC Viabilidade'!H36 -> 225142.86 | K33: =(D33-F33)*'11-Viabilidade'!$O$16 -> 486.14099 | L33: =D33-(E33+F33+G33+H33+I33+K33) -> -382.32916 | M33: =D33-(E33+F33+G33+H33+K33) -> 1988.9768 | P33: =IF(B33<='11-Viabilidade'!$G$11,(P32+(P32*'11-Viabilidade'!$H$12)),0) -> 0 | Q33: =IF(B33='11-Viabilidade'!$G$11,'11-Viabilidade'!$G$16,0)*(1+'11-Viabilidade'!$G$12)^((B33-1)/12) -> 0 | R33: =-SUM(O33:Q33) -> 0 | S33: =IF(R33<>0,0,S32+1) -> 26 | T33: =IF($S33<'11-Viabilidade'!$C$24,0,$S33-'11-Viabilidade'!$C$24) -> 20 | U33: =IF(T33>0,'11-Viabilidade'!$K$10,0)*((1+'11-Viabilidade'!$O$10)^(($T33-1)/12)) -> 3240.9399 | V33: =U33*'11-Viabilidade'!$L$12 -> 180.05222 | W33: =U33*'11-Viabilidade'!$K$14 -> 0 | X33: =U33*'11-Viabilidade'!$K$15 -> 162.047 | Y33: =IF(AND(U33=0,S33=0),0,IF(AND(U33=0,S33<>0),'11-Viabilidade'!$K$16+'11-Viabilidade'!$K$17,('11-Viabilidade'!$L$11)*((1+'11-Viabilidade'!$O$10)^(($C33-1)/12)))) -> 423.72288 | Z33: =IFERROR(VLOOKUP(S33,'12-SAC Viabilidade'!$B$11:$G$430,6,FALSE),0) -> 2371.306 | AA33: =IFERROR(VLOOKUP(S33,'12-SAC Viabilidade'!$B$11:$H$430,7,FALSE),0) -> 225142.86 | AB33: =(U33-W33)*'11-Viabilidade'!$O$16 -> 486.14099 | AC33: =U33-(V33+W33+X33+Y33+Z33+AB33-R33) -> -382.32916 | AD33: =U33-(V33+W33+X33+Y33+AB33) -> 1988.9768
B34: =IF(AND(B33>0,B33<'11-Viabilidade'!$P$14),B33+1,0) -> 27 | C34: =IF($B34<'11-Viabilidade'!$C$24,0,$B34-'11-Viabilidade'!$C$24) -> 21 | D34: =IF(C34>0,'11-Viabilidade'!$K$10,0)*((1+'11-Viabilidade'!$O$10)^(($C34-1)/12)) -> 3254.1439 | E34: =D34*'11-Viabilidade'!$L$12 -> 180.78577 | F34: =D34*'11-Viabilidade'!$K$14 -> 0 | G34: =D34*'11-Viabilidade'!$K$15 -> 162.70719 | H34: =IF(D34=0,'11-Viabilidade'!$K$16+'11-Viabilidade'!$K$17,('11-Viabilidade'!$L$11)*((1+'11-Viabilidade'!$O$10)^(($C34-1)/12))) -> 425.44918 | I34: ='12-SAC Viabilidade'!G37 -> 2366.7493 | J34: ='12-SAC Viabilidade'!H37 -> 224571.43 | K34: =(D34-F34)*'11-Viabilidade'!$O$16 -> 488.12158 | L34: =D34-(E34+F34+G34+H34+I34+K34) -> -369.66917 | M34: =D34-(E34+F34+G34+H34+K34) -> 1997.0802 | P34: =IF(B34<='11-Viabilidade'!$G$11,(P33+(P33*'11-Viabilidade'!$H$12)),0) -> 0 | Q34: =IF(B34='11-Viabilidade'!$G$11,'11-Viabilidade'!$G$16,0)*(1+'11-Viabilidade'!$G$12)^((B34-1)/12) -> 0 | R34: =-SUM(O34:Q34) -> 0 | S34: =IF(R34<>0,0,S33+1) -> 27 | T34: =IF($S34<'11-Viabilidade'!$C$24,0,$S34-'11-Viabilidade'!$C$24) -> 21 | U34: =IF(T34>0,'11-Viabilidade'!$K$10,0)*((1+'11-Viabilidade'!$O$10)^(($T34-1)/12)) -> 3254.1439 | V34: =U34*'11-Viabilidade'!$L$12 -> 180.78577 | W34: =U34*'11-Viabilidade'!$K$14 -> 0 | X34: =U34*'11-Viabilidade'!$K$15 -> 162.70719 | Y34: =IF(AND(U34=0,S34=0),0,IF(AND(U34=0,S34<>0),'11-Viabilidade'!$K$16+'11-Viabilidade'!$K$17,('11-Viabilidade'!$L$11)*((1+'11-Viabilidade'!$O$10)^(($C34-1)/12)))) -> 425.44918 | Z34: =IFERROR(VLOOKUP(S34,'12-SAC Viabilidade'!$B$11:$G$430,6,FALSE),0) -> 2366.7493 | AA34: =IFERROR(VLOOKUP(S34,'12-SAC Viabilidade'!$B$11:$H$430,7,FALSE),0) -> 224571.43 | AB34: =(U34-W34)*'11-Viabilidade'!$O$16 -> 488.12158 | AC34: =U34-(V34+W34+X34+Y34+Z34+AB34-R34) -> -369.66917 | AD34: =U34-(V34+W34+X34+Y34+AB34) -> 1997.0802
B35: =IF(AND(B34>0,B34<'11-Viabilidade'!$P$14),B34+1,0) -> 28 | C35: =IF($B35<'11-Viabilidade'!$C$24,0,$B35-'11-Viabilidade'!$C$24) -> 22 | D35: =IF(C35>0,'11-Viabilidade'!$K$10,0)*((1+'11-Viabilidade'!$O$10)^(($C35-1)/12)) -> 3267.4017 | E35: =D35*'11-Viabilidade'!$L$12 -> 181.52232 | F35: =D35*'11-Viabilidade'!$K$14 -> 0 | G35: =D35*'11-Viabilidade'!$K$15 -> 163.37008 | H35: =IF(D35=0,'11-Viabilidade'!$K$16+'11-Viabilidade'!$K$17,('11-Viabilidade'!$L$11)*((1+'11-Viabilidade'!$O$10)^(($C35-1)/12))) -> 427.18252 | I35: ='12-SAC Viabilidade'!G38 -> 2362.1927 | J35: ='12-SAC Viabilidade'!H38 -> 224000 | K35: =(D35-F35)*'11-Viabilidade'!$O$16 -> 490.11025 | L35: =D35-(E35+F35+G35+H35+I35+K35) -> -356.97617 | M35: =D35-(E35+F35+G35+H35+K35) -> 2005.2165 | P35: =IF(B35<='11-Viabilidade'!$G$11,(P34+(P34*'11-Viabilidade'!$H$12)),0) -> 0 | Q35: =IF(B35='11-Viabilidade'!$G$11,'11-Viabilidade'!$G$16,0)*(1+'11-Viabilidade'!$G$12)^((B35-1)/12) -> 0 | R35: =-SUM(O35:Q35) -> 0 | S35: =IF(R35<>0,0,S34+1) -> 28 | T35: =IF($S35<'11-Viabilidade'!$C$24,0,$S35-'11-Viabilidade'!$C$24) -> 22 | U35: =IF(T35>0,'11-Viabilidade'!$K$10,0)*((1+'11-Viabilidade'!$O$10)^(($T35-1)/12)) -> 3267.4017 | V35: =U35*'11-Viabilidade'!$L$12 -> 181.52232 | W35: =U35*'11-Viabilidade'!$K$14 -> 0 | X35: =U35*'11-Viabilidade'!$K$15 -> 163.37008 | Y35: =IF(AND(U35=0,S35=0),0,IF(AND(U35=0,S35<>0),'11-Viabilidade'!$K$16+'11-Viabilidade'!$K$17,('11-Viabilidade'!$L$11)*((1+'11-Viabilidade'!$O$10)^(($C35-1)/12)))) -> 427.18252 | Z35: =IFERROR(VLOOKUP(S35,'12-SAC Viabilidade'!$B$11:$G$430,6,FALSE),0) -> 2362.1927 | AA35: =IFERROR(VLOOKUP(S35,'12-SAC Viabilidade'!$B$11:$H$430,7,FALSE),0) -> 224000 | AB35: =(U35-W35)*'11-Viabilidade'!$O$16 -> 490.11025 | AC35: =U35-(V35+W35+X35+Y35+Z35+AB35-R35) -> -356.97617 | AD35: =U35-(V35+W35+X35+Y35+AB35) -> 2005.2165
B36: =IF(AND(B35>0,B35<'11-Viabilidade'!$P$14),B35+1,0) -> 29 | C36: =IF($B36<'11-Viabilidade'!$C$24,0,$B36-'11-Viabilidade'!$C$24) -> 23 | D36: =IF(C36>0,'11-Viabilidade'!$K$10,0)*((1+'11-Viabilidade'!$O$10)^(($C36-1)/12)) -> 3280.7135 | E36: =D36*'11-Viabilidade'!$L$12 -> 182.26186 | F36: =D36*'11-Viabilidade'!$K$14 -> 0 | G36: =D36*'11-Viabilidade'!$K$15 -> 164.03567 | H36: =IF(D36=0,'11-Viabilidade'!$K$16+'11-Viabilidade'!$K$17,('11-Viabilidade'!$L$11)*((1+'11-Viabilidade'!$O$10)^(($C36-1)/12))) -> 428.92291 | I36: ='12-SAC Viabilidade'!G39 -> 2357.636 | J36: ='12-SAC Viabilidade'!H39 -> 223428.57 | K36: =(D36-F36)*'11-Viabilidade'!$O$16 -> 492.10702 | L36: =D36-(E36+F36+G36+H36+I36+K36) -> -344.25001 | M36: =D36-(E36+F36+G36+H36+K36) -> 2013.386 | P36: =IF(B36<='11-Viabilidade'!$G$11,(P35+(P35*'11-Viabilidade'!$H$12)),0) -> 0 | Q36: =IF(B36='11-Viabilidade'!$G$11,'11-Viabilidade'!$G$16,0)*(1+'11-Viabilidade'!$G$12)^((B36-1)/12) -> 0 | R36: =-SUM(O36:Q36) -> 0 | S36: =IF(R36<>0,0,S35+1) -> 29 | T36: =IF($S36<'11-Viabilidade'!$C$24,0,$S36-'11-Viabilidade'!$C$24) -> 23 | U36: =IF(T36>0,'11-Viabilidade'!$K$10,0)*((1+'11-Viabilidade'!$O$10)^(($T36-1)/12)) -> 3280.7135 | V36: =U36*'11-Viabilidade'!$L$12 -> 182.26186 | W36: =U36*'11-Viabilidade'!$K$14 -> 0 | X36: =U36*'11-Viabilidade'!$K$15 -> 164.03567 | Y36: =IF(AND(U36=0,S36=0),0,IF(AND(U36=0,S36<>0),'11-Viabilidade'!$K$16+'11-Viabilidade'!$K$17,('11-Viabilidade'!$L$11)*((1+'11-Viabilidade'!$O$10)^(($C36-1)/12)))) -> 428.92291 | Z36: =IFERROR(VLOOKUP(S36,'12-SAC Viabilidade'!$B$11:$G$430,6,FALSE),0) -> 2357.636 | AA36: =IFERROR(VLOOKUP(S36,'12-SAC Viabilidade'!$B$11:$H$430,7,FALSE),0) -> 223428.57 | AB36: =(U36-W36)*'11-Viabilidade'!$O$16 -> 492.10702 | AC36: =U36-(V36+W36+X36+Y36+Z36+AB36-R36) -> -344.25001 | AD36: =U36-(V36+W36+X36+Y36+AB36) -> 2013.386
B37: =IF(AND(B36>0,B36<'11-Viabilidade'!$P$14),B36+1,0) -> 30 | C37: =IF($B37<'11-Viabilidade'!$C$24,0,$B37-'11-Viabilidade'!$C$24) -> 24 | D37: =IF(C37>0,'11-Viabilidade'!$K$10,0)*((1+'11-Viabilidade'!$O$10)^(($C37-1)/12)) -> 3294.0795 | E37: =D37*'11-Viabilidade'!$L$12 -> 183.00442 | F37: =D37*'11-Viabilidade'!$K$14 -> 0 | G37: =D37*'11-Viabilidade'!$K$15 -> 164.70398 | H37: =IF(D37=0,'11-Viabilidade'!$K$16+'11-Viabilidade'!$K$17,('11-Viabilidade'!$L$11)*((1+'11-Viabilidade'!$O$10)^(($C37-1)/12))) -> 430.6704 | I37: ='12-SAC Viabilidade'!G40 -> 2353.0794 | J37: ='12-SAC Viabilidade'!H40 -> 222857.14 | K37: =(D37-F37)*'11-Viabilidade'!$O$16 -> 494.11193 | L37: =D37-(E37+F37+G37+H37+I37+K37) -> -331.49058 | M37: =D37-(E37+F37+G37+H37+K37) -> 2021.5888 | P37: =IF(B37<='11-Viabilidade'!$G$11,(P36+(P36*'11-Viabilidade'!$H$12)),0) -> 0 | Q37: =IF(B37='11-Viabilidade'!$G$11,'11-Viabilidade'!$G$16,0)*(1+'11-Viabilidade'!$G$12)^((B37-1)/12) -> 0 | R37: =-SUM(O37:Q37) -> 0 | S37: =IF(R37<>0,0,S36+1) -> 30 | T37: =IF($S37<'11-Viabilidade'!$C$24,0,$S37-'11-Viabilidade'!$C$24) -> 24 | U37: =IF(T37>0,'11-Viabilidade'!$K$10,0)*((1+'11-Viabilidade'!$O$10)^(($T37-1)/12)) -> 3294.0795 | V37: =U37*'11-Viabilidade'!$L$12 -> 183.00442 | W37: =U37*'11-Viabilidade'!$K$14 -> 0 | X37: =U37*'11-Viabilidade'!$K$15 -> 164.70398 | Y37: =IF(AND(U37=0,S37=0),0,IF(AND(U37=0,S37<>0),'11-Viabilidade'!$K$16+'11-Viabilidade'!$K$17,('11-Viabilidade'!$L$11)*((1+'11-Viabilidade'!$O$10)^(($C37-1)/12)))) -> 430.6704 | Z37: =IFERROR(VLOOKUP(S37,'12-SAC Viabilidade'!$B$11:$G$430,6,FALSE),0) -> 2353.0794 | AA37: =IFERROR(VLOOKUP(S37,'12-SAC Viabilidade'!$B$11:$H$430,7,FALSE),0) -> 222857.14 | AB37: =(U37-W37)*'11-Viabilidade'!$O$16 -> 494.11193 | AC37: =U37-(V37+W37+X37+Y37+Z37+AB37-R37) -> -331.49058 | AD37: =U37-(V37+W37+X37+Y37+AB37) -> 2021.5888
B38: =IF(AND(B37>0,B37<'11-Viabilidade'!$P$14),B37+1,0) -> 31 | C38: =IF($B38<'11-Viabilidade'!$C$24,0,$B38-'11-Viabilidade'!$C$24) -> 25 | D38: =IF(C38>0,'11-Viabilidade'!$K$10,0)*((1+'11-Viabilidade'!$O$10)^(($C38-1)/12)) -> 3307.5 | E38: =D38*'11-Viabilidade'!$L$12 -> 183.75 | F38: =D38*'11-Viabilidade'!$K$14 -> 0 | G38: =D38*'11-Viabilidade'!$K$15 -> 165.375 | H38: =IF(D38=0,'11-Viabilidade'!$K$16+'11-Viabilidade'!$K$17,('11-Viabilidade'!$L$11)*((1+'11-Viabilidade'!$O$10)^(($C38-1)/12))) -> 432.425 | I38: ='12-SAC Viabilidade'!G41 -> 2348.5227 | J38: ='12-SAC Viabilidade'!H41 -> 222285.71 | K38: =(D38-F38)*'11-Viabilidade'!$O$16 -> 496.125 | L38: =D38-(E38+F38+G38+H38+I38+K38) -> -318.69772 | M38: =D38-(E38+F38+G38+H38+K38) -> 2029.825 | P38: =IF(B38<='11-Viabilidade'!$G$11,(P37+(P37*'11-Viabilidade'!$H$12)),0) -> 0 | Q38: =IF(B38='11-Viabilidade'!$G$11,'11-Viabilidade'!$G$16,0)*(1+'11-Viabilidade'!$G$12)^((B38-1)/12) -> 0 | R38: =-SUM(O38:Q38) -> 0 | S38: =IF(R38<>0,0,S37+1) -> 31 | T38: =IF($S38<'11-Viabilidade'!$C$24,0,$S38-'11-Viabilidade'!$C$24) -> 25 | U38: =IF(T38>0,'11-Viabilidade'!$K$10,0)*((1+'11-Viabilidade'!$O$10)^(($T38-1)/12)) -> 3307.5 | V38: =U38*'11-Viabilidade'!$L$12 -> 183.75 | W38: =U38*'11-Viabilidade'!$K$14 -> 0 | X38: =U38*'11-Viabilidade'!$K$15 -> 165.375 | Y38: =IF(AND(U38=0,S38=0),0,IF(AND(U38=0,S38<>0),'11-Viabilidade'!$K$16+'11-Viabilidade'!$K$17,('11-Viabilidade'!$L$11)*((1+'11-Viabilidade'!$O$10)^(($C38-1)/12)))) -> 432.425 | Z38: =IFERROR(VLOOKUP(S38,'12-SAC Viabilidade'!$B$11:$G$430,6,FALSE),0) -> 2348.5227 | AA38: =IFERROR(VLOOKUP(S38,'12-SAC Viabilidade'!$B$11:$H$430,7,FALSE),0) -> 222285.71 | AB38: =(U38-W38)*'11-Viabilidade'!$O$16 -> 496.125 | AC38: =U38-(V38+W38+X38+Y38+Z38+AB38-R38) -> -318.69772 | AD38: =U38-(V38+W38+X38+Y38+AB38) -> 2029.825
B39: =IF(AND(B38>0,B38<'11-Viabilidade'!$P$14),B38+1,0) -> 32 | C39: =IF($B39<'11-Viabilidade'!$C$24,0,$B39-'11-Viabilidade'!$C$24) -> 26 | D39: =IF(C39>0,'11-Viabilidade'!$K$10,0)*((1+'11-Viabilidade'!$O$10)^(($C39-1)/12)) -> 3320.9752 | E39: =D39*'11-Viabilidade'!$L$12 -> 184.49862 | F39: =D39*'11-Viabilidade'!$K$14 -> 0 | G39: =D39*'11-Viabilidade'!$K$15 -> 166.04876 | H39: =IF(D39=0,'11-Viabilidade'!$K$16+'11-Viabilidade'!$K$17,('11-Viabilidade'!$L$11)*((1+'11-Viabilidade'!$O$10)^(($C39-1)/12))) -> 434.18675 | I39: ='12-SAC Viabilidade'!G42 -> 2343.9661 | J39: ='12-SAC Viabilidade'!H42 -> 221714.29 | K39: =(D39-F39)*'11-Viabilidade'!$O$16 -> 498.14627 | L39: =D39-(E39+F39+G39+H39+I39+K39) -> -305.87131 | M39: =D39-(E39+F39+G39+H39+K39) -> 2038.0948 | P39: =IF(B39<='11-Viabilidade'!$G$11,(P38+(P38*'11-Viabilidade'!$H$12)),0) -> 0 | Q39: =IF(B39='11-Viabilidade'!$G$11,'11-Viabilidade'!$G$16,0)*(1+'11-Viabilidade'!$G$12)^((B39-1)/12) -> 0 | R39: =-SUM(O39:Q39) -> 0 | S39: =IF(R39<>0,0,S38+1) -> 32 | T39: =IF($S39<'11-Viabilidade'!$C$24,0,$S39-'11-Viabilidade'!$C$24) -> 26 | U39: =IF(T39>0,'11-Viabilidade'!$K$10,0)*((1+'11-Viabilidade'!$O$10)^(($T39-1)/12)) -> 3320.9752 | V39: =U39*'11-Viabilidade'!$L$12 -> 184.49862 | W39: =U39*'11-Viabilidade'!$K$14 -> 0 | X39: =U39*'11-Viabilidade'!$K$15 -> 166.04876 | Y39: =IF(AND(U39=0,S39=0),0,IF(AND(U39=0,S39<>0),'11-Viabilidade'!$K$16+'11-Viabilidade'!$K$17,('11-Viabilidade'!$L$11)*((1+'11-Viabilidade'!$O$10)^(($C39-1)/12)))) -> 434.18675 | Z39: =IFERROR(VLOOKUP(S39,'12-SAC Viabilidade'!$B$11:$G$430,6,FALSE),0) -> 2343.9661 | AA39: =IFERROR(VLOOKUP(S39,'12-SAC Viabilidade'!$B$11:$H$430,7,FALSE),0) -> 221714.29 | AB39: =(U39-W39)*'11-Viabilidade'!$O$16 -> 498.14627 | AC39: =U39-(V39+W39+X39+Y39+Z39+AB39-R39) -> -305.87131 | AD39: =U39-(V39+W39+X39+Y39+AB39) -> 2038.0948
B40: =IF(AND(B39>0,B39<'11-Viabilidade'!$P$14),B39+1,0) -> 33 | C40: =IF($B40<'11-Viabilidade'!$C$24,0,$B40-'11-Viabilidade'!$C$24) -> 27 | D40: =IF(C40>0,'11-Viabilidade'!$K$10,0)*((1+'11-Viabilidade'!$O$10)^(($C40-1)/12)) -> 3334.5052 | E40: =D40*'11-Viabilidade'!$L$12 -> 185.25029 | F40: =D40*'11-Viabilidade'!$K$14 -> 0 | G40: =D40*'11-Viabilidade'!$K$15 -> 166.72526 | H40: =IF(D40=0,'11-Viabilidade'!$K$16+'11-Viabilidade'!$K$17,('11-Viabilidade'!$L$11)*((1+'11-Viabilidade'!$O$10)^(($C40-1)/12))) -> 435.95568 | I40: ='12-SAC Viabilidade'!G43 -> 2339.4094 | J40: ='12-SAC Viabilidade'!H43 -> 221142.86 | K40: =(D40-F40)*'11-Viabilidade'!$O$16 -> 500.17578 | L40: =D40-(E40+F40+G40+H40+I40+K40) -> -293.01121 | M40: =D40-(E40+F40+G40+H40+K40) -> 2046.3982 | P40: =IF(B40<='11-Viabilidade'!$G$11,(P39+(P39*'11-Viabilidade'!$H$12)),0) -> 0 | Q40: =IF(B40='11-Viabilidade'!$G$11,'11-Viabilidade'!$G$16,0)*(1+'11-Viabilidade'!$G$12)^((B40-1)/12) -> 0 | R40: =-SUM(O40:Q40) -> 0 | S40: =IF(R40<>0,0,S39+1) -> 33 | T40: =IF($S40<'11-Viabilidade'!$C$24,0,$S40-'11-Viabilidade'!$C$24) -> 27 | U40: =IF(T40>0,'11-Viabilidade'!$K$10,0)*((1+'11-Viabilidade'!$O$10)^(($T40-1)/12)) -> 3334.5052 | V40: =U40*'11-Viabilidade'!$L$12 -> 185.25029 | W40: =U40*'11-Viabilidade'!$K$14 -> 0 | X40: =U40*'11-Viabilidade'!$K$15 -> 166.72526 | Y40: =IF(AND(U40=0,S40=0),0,IF(AND(U40=0,S40<>0),'11-Viabilidade'!$K$16+'11-Viabilidade'!$K$17,('11-Viabilidade'!$L$11)*((1+'11-Viabilidade'!$O$10)^(($C40-1)/12)))) -> 435.95568 | Z40: =IFERROR(VLOOKUP(S40,'12-SAC Viabilidade'!$B$11:$G$430,6,FALSE),0) -> 2339.4094 | AA40: =IFERROR(VLOOKUP(S40,'12-SAC Viabilidade'!$B$11:$H$430,7,FALSE),0) -> 221142.86 | AB40: =(U40-W40)*'11-Viabilidade'!$O$16 -> 500.17578 | AC40: =U40-(V40+W40+X40+Y40+Z40+AB40-R40) -> -293.01121 | AD40: =U40-(V40+W40+X40+Y40+AB40) -> 2046.3982
B41: =IF(AND(B40>0,B40<'11-Viabilidade'!$P$14),B40+1,0) -> 34 | C41: =IF($B41<'11-Viabilidade'!$C$24,0,$B41-'11-Viabilidade'!$C$24) -> 28 | D41: =IF(C41>0,'11-Viabilidade'!$K$10,0)*((1+'11-Viabilidade'!$O$10)^(($C41-1)/12)) -> 3348.0904 | E41: =D41*'11-Viabilidade'!$L$12 -> 186.00502 | F41: =D41*'11-Viabilidade'!$K$14 -> 0 | G41: =D41*'11-Viabilidade'!$K$15 -> 167.40452 | H41: =IF(D41=0,'11-Viabilidade'!$K$16+'11-Viabilidade'!$K$17,('11-Viabilidade'!$L$11)*((1+'11-Viabilidade'!$O$10)^(($C41-1)/12))) -> 437.73182 | I41: ='12-SAC Viabilidade'!G44 -> 2334.8528 | J41: ='12-SAC Viabilidade'!H44 -> 220571.43 | K41: =(D41-F41)*'11-Viabilidade'!$O$16 -> 502.21356 | L41: =D41-(E41+F41+G41+H41+I41+K41) -> -280.11728 | M41: =D41-(E41+F41+G41+H41+K41) -> 2054.7355 | P41: =IF(B41<='11-Viabilidade'!$G$11,(P40+(P40*'11-Viabilidade'!$H$12)),0) -> 0 | Q41: =IF(B41='11-Viabilidade'!$G$11,'11-Viabilidade'!$G$16,0)*(1+'11-Viabilidade'!$G$12)^((B41-1)/12) -> 0 | R41: =-SUM(O41:Q41) -> 0 | S41: =IF(R41<>0,0,S40+1) -> 34 | T41: =IF($S41<'11-Viabilidade'!$C$24,0,$S41-'11-Viabilidade'!$C$24) -> 28 | U41: =IF(T41>0,'11-Viabilidade'!$K$10,0)*((1+'11-Viabilidade'!$O$10)^(($T41-1)/12)) -> 3348.0904 | V41: =U41*'11-Viabilidade'!$L$12 -> 186.00502 | W41: =U41*'11-Viabilidade'!$K$14 -> 0 | X41: =U41*'11-Viabilidade'!$K$15 -> 167.40452 | Y41: =IF(AND(U41=0,S41=0),0,IF(AND(U41=0,S41<>0),'11-Viabilidade'!$K$16+'11-Viabilidade'!$K$17,('11-Viabilidade'!$L$11)*((1+'11-Viabilidade'!$O$10)^(($C41-1)/12)))) -> 437.73182 | Z41: =IFERROR(VLOOKUP(S41,'12-SAC Viabilidade'!$B$11:$G$430,6,FALSE),0) -> 2334.8528 | AA41: =IFERROR(VLOOKUP(S41,'12-SAC Viabilidade'!$B$11:$H$430,7,FALSE),0) -> 220571.43 | AB41: =(U41-W41)*'11-Viabilidade'!$O$16 -> 502.21356 | AC41: =U41-(V41+W41+X41+Y41+Z41+AB41-R41) -> -280.11728 | AD41: =U41-(V41+W41+X41+Y41+AB41) -> 2054.7355
B42: =IF(AND(B41>0,B41<'11-Viabilidade'!$P$14),B41+1,0) -> 35 | C42: =IF($B42<'11-Viabilidade'!$C$24,0,$B42-'11-Viabilidade'!$C$24) -> 29 | D42: =IF(C42>0,'11-Viabilidade'!$K$10,0)*((1+'11-Viabilidade'!$O$10)^(($C42-1)/12)) -> 3361.731 | E42: =D42*'11-Viabilidade'!$L$12 -> 186.76283 | F42: =D42*'11-Viabilidade'!$K$14 -> 0 | G42: =D42*'11-Viabilidade'!$K$15 -> 168.08655 | H42: =IF(D42=0,'11-Viabilidade'!$K$16+'11-Viabilidade'!$K$17,('11-Viabilidade'!$L$11)*((1+'11-Viabilidade'!$O$10)^(($C42-1)/12))) -> 439.51519 | I42: ='12-SAC Viabilidade'!G45 -> 2330.2961 | J42: ='12-SAC Viabilidade'!H45 -> 220000 | K42: =(D42-F42)*'11-Viabilidade'!$O$16 -> 504.25964 | L42: =D42-(E42+F42+G42+H42+I42+K42) -> -267.18938 | M42: =D42-(E42+F42+G42+H42+K42) -> 2063.1067 | P42: =IF(B42<='11-Viabilidade'!$G$11,(P41+(P41*'11-Viabilidade'!$H$12)),0) -> 0 | Q42: =IF(B42='11-Viabilidade'!$G$11,'11-Viabilidade'!$G$16,0)*(1+'11-Viabilidade'!$G$12)^((B42-1)/12) -> 0 | R42: =-SUM(O42:Q42) -> 0 | S42: =IF(R42<>0,0,S41+1) -> 35 | T42: =IF($S42<'11-Viabilidade'!$C$24,0,$S42-'11-Viabilidade'!$C$24) -> 29 | U42: =IF(T42>0,'11-Viabilidade'!$K$10,0)*((1+'11-Viabilidade'!$O$10)^(($T42-1)/12)) -> 3361.731 | V42: =U42*'11-Viabilidade'!$L$12 -> 186.76283 | W42: =U42*'11-Viabilidade'!$K$14 -> 0 | X42: =U42*'11-Viabilidade'!$K$15 -> 168.08655 | Y42: =IF(AND(U42=0,S42=0),0,IF(AND(U42=0,S42<>0),'11-Viabilidade'!$K$16+'11-Viabilidade'!$K$17,('11-Viabilidade'!$L$11)*((1+'11-Viabilidade'!$O$10)^(($C42-1)/12)))) -> 439.51519 | Z42: =IFERROR(VLOOKUP(S42,'12-SAC Viabilidade'!$B$11:$G$430,6,FALSE),0) -> 2330.2961 | AA42: =IFERROR(VLOOKUP(S42,'12-SAC Viabilidade'!$B$11:$H$430,7,FALSE),0) -> 220000 | AB42: =(U42-W42)*'11-Viabilidade'!$O$16 -> 504.25964 | AC42: =U42-(V42+W42+X42+Y42+Z42+AB42-R42) -> -267.18938 | AD42: =U42-(V42+W42+X42+Y42+AB42) -> 2063.1067
A43: 4º Ano | B43: =IF(AND(B42>0,B42<'11-Viabilidade'!$P$14),B42+1,0) -> 36 | C43: =IF($B43<'11-Viabilidade'!$C$24,0,$B43-'11-Viabilidade'!$C$24) -> 30 | D43: =IF(C43>0,'11-Viabilidade'!$K$10,0)*((1+'11-Viabilidade'!$O$10)^(($C43-1)/12)) -> 3375.4271 | E43: =D43*'11-Viabilidade'!$L$12 -> 187.52373 | F43: =D43*'11-Viabilidade'!$K$14 -> 0 | G43: =D43*'11-Viabilidade'!$K$15 -> 168.77135 | H43: =IF(D43=0,'11-Viabilidade'!$K$16+'11-Viabilidade'!$K$17,('11-Viabilidade'!$L$11)*((1+'11-Viabilidade'!$O$10)^(($C43-1)/12))) -> 441.30583 | I43: ='12-SAC Viabilidade'!G46 -> 2325.7395 | J43: ='12-SAC Viabilidade'!H46 -> 219428.57 | K43: =(D43-F43)*'11-Viabilidade'!$O$16 -> 506.31406 | L43: =D43-(E43+F43+G43+H43+I43+K43) -> -254.22738 | M43: =D43-(E43+F43+G43+H43+K43) -> 2071.5121 | P43: =IF(B43<='11-Viabilidade'!$G$11,(P42+(P42*'11-Viabilidade'!$H$12)),0) -> 0 | Q43: =IF(B43='11-Viabilidade'!$G$11,'11-Viabilidade'!$G$16,0)*(1+'11-Viabilidade'!$G$12)^((B43-1)/12) -> 0 | R43: =-SUM(O43:Q43) -> 0 | S43: =IF(R43<>0,0,S42+1) -> 36 | T43: =IF($S43<'11-Viabilidade'!$C$24,0,$S43-'11-Viabilidade'!$C$24) -> 30 | U43: =IF(T43>0,'11-Viabilidade'!$K$10,0)*((1+'11-Viabilidade'!$O$10)^(($T43-1)/12)) -> 3375.4271 | V43: =U43*'11-Viabilidade'!$L$12 -> 187.52373 | W43: =U43*'11-Viabilidade'!$K$14 -> 0 | X43: =U43*'11-Viabilidade'!$K$15 -> 168.77135 | Y43: =IF(AND(U43=0,S43=0),0,IF(AND(U43=0,S43<>0),'11-Viabilidade'!$K$16+'11-Viabilidade'!$K$17,('11-Viabilidade'!$L$11)*((1+'11-Viabilidade'!$O$10)^(($C43-1)/12)))) -> 441.30583 | Z43: =IFERROR(VLOOKUP(S43,'12-SAC Viabilidade'!$B$11:$G$430,6,FALSE),0) -> 2325.7395 | AA43: =IFERROR(VLOOKUP(S43,'12-SAC Viabilidade'!$B$11:$H$430,7,FALSE),0) -> 219428.57 | AB43: =(U43-W43)*'11-Viabilidade'!$O$16 -> 506.31406 | AC43: =U43-(V43+W43+X43+Y43+Z43+AB43-R43) -> -254.22738 | AD43: =U43-(V43+W43+X43+Y43+AB43) -> 2071.5121
B44: =IF(AND(B43>0,B43<'11-Viabilidade'!$P$14),B43+1,0) -> 37 | C44: =IF($B44<'11-Viabilidade'!$C$24,0,$B44-'11-Viabilidade'!$C$24) -> 31 | D44: =IF(C44>0,'11-Viabilidade'!$K$10,0)*((1+'11-Viabilidade'!$O$10)^(($C44-1)/12)) -> 3389.179 | E44: =D44*'11-Viabilidade'!$L$12 -> 188.28772 | F44: =D44*'11-Viabilidade'!$K$14 -> 0 | G44: =D44*'11-Viabilidade'!$K$15 -> 169.45895 | H44: =IF(D44=0,'11-Viabilidade'!$K$16+'11-Viabilidade'!$K$17,('11-Viabilidade'!$L$11)*((1+'11-Viabilidade'!$O$10)^(($C44-1)/12))) -> 443.10377 | I44: ='12-SAC Viabilidade'!G47 -> 2321.1828 | J44: ='12-SAC Viabilidade'!H47 -> 218857.14 | K44: =(D44-F44)*'11-Viabilidade'!$O$16 -> 508.37684 | L44: =D44-(E44+F44+G44+H44+I44+K44) -> -241.23113 | M44: =D44-(E44+F44+G44+H44+K44) -> 2079.9517 | P44: =IF(B44<='11-Viabilidade'!$G$11,(P43+(P43*'11-Viabilidade'!$H$12)),0) -> 0 | Q44: =IF(B44='11-Viabilidade'!$G$11,'11-Viabilidade'!$G$16,0)*(1+'11-Viabilidade'!$G$12)^((B44-1)/12) -> 0 | R44: =-SUM(O44:Q44) -> 0 | S44: =IF(R44<>0,0,S43+1) -> 37 | T44: =IF($S44<'11-Viabilidade'!$C$24,0,$S44-'11-Viabilidade'!$C$24) -> 31 | U44: =IF(T44>0,'11-Viabilidade'!$K$10,0)*((1+'11-Viabilidade'!$O$10)^(($T44-1)/12)) -> 3389.179 | V44: =U44*'11-Viabilidade'!$L$12 -> 188.28772 | W44: =U44*'11-Viabilidade'!$K$14 -> 0 | X44: =U44*'11-Viabilidade'!$K$15 -> 169.45895 | Y44: =IF(AND(U44=0,S44=0),0,IF(AND(U44=0,S44<>0),'11-Viabilidade'!$K$16+'11-Viabilidade'!$K$17,('11-Viabilidade'!$L$11)*((1+'11-Viabilidade'!$O$10)^(($C44-1)/12)))) -> 443.10377 | Z44: =IFERROR(VLOOKUP(S44,'12-SAC Viabilidade'!$B$11:$G$430,6,FALSE),0) -> 2321.1828 | AA44: =IFERROR(VLOOKUP(S44,'12-SAC Viabilidade'!$B$11:$H$430,7,FALSE),0) -> 218857.14 | AB44: =(U44-W44)*'11-Viabilidade'!$O$16 -> 508.37684 | AC44: =U44-(V44+W44+X44+Y44+Z44+AB44-R44) -> -241.23113 | AD44: =U44-(V44+W44+X44+Y44+AB44) -> 2079.9517
B45: =IF(AND(B44>0,B44<'11-Viabilidade'!$P$14),B44+1,0) -> 38 | C45: =IF($B45<'11-Viabilidade'!$C$24,0,$B45-'11-Viabilidade'!$C$24) -> 32 | D45: =IF(C45>0,'11-Viabilidade'!$K$10,0)*((1+'11-Viabilidade'!$O$10)^(($C45-1)/12)) -> 3402.9869 | E45: =D45*'11-Viabilidade'!$L$12 -> 189.05483 | F45: =D45*'11-Viabilidade'!$K$14 -> 0 | G45: =D45*'11-Viabilidade'!$K$15 -> 170.14935 | H45: =IF(D45=0,'11-Viabilidade'!$K$16+'11-Viabilidade'!$K$17,('11-Viabilidade'!$L$11)*((1+'11-Viabilidade'!$O$10)^(($C45-1)/12))) -> 444.90903 | I45: ='12-SAC Viabilidade'!G48 -> 2316.6262 | J45: ='12-SAC Viabilidade'!H48 -> 218285.71 | K45: =(D45-F45)*'11-Viabilidade'!$O$16 -> 510.44804 | L45: =D45-(E45+F45+G45+H45+I45+K45) -> -228.2005 | M45: =D45-(E45+F45+G45+H45+K45) -> 2088.4257 | P45: =IF(B45<='11-Viabilidade'!$G$11,(P44+(P44*'11-Viabilidade'!$H$12)),0) -> 0 | Q45: =IF(B45='11-Viabilidade'!$G$11,'11-Viabilidade'!$G$16,0)*(1+'11-Viabilidade'!$G$12)^((B45-1)/12) -> 0 | R45: =-SUM(O45:Q45) -> 0 | S45: =IF(R45<>0,0,S44+1) -> 38 | T45: =IF($S45<'11-Viabilidade'!$C$24,0,$S45-'11-Viabilidade'!$C$24) -> 32 | U45: =IF(T45>0,'11-Viabilidade'!$K$10,0)*((1+'11-Viabilidade'!$O$10)^(($T45-1)/12)) -> 3402.9869 | V45: =U45*'11-Viabilidade'!$L$12 -> 189.05483 | W45: =U45*'11-Viabilidade'!$K$14 -> 0 | X45: =U45*'11-Viabilidade'!$K$15 -> 170.14935 | Y45: =IF(AND(U45=0,S45=0),0,IF(AND(U45=0,S45<>0),'11-Viabilidade'!$K$16+'11-Viabilidade'!$K$17,('11-Viabilidade'!$L$11)*((1+'11-Viabilidade'!$O$10)^(($C45-1)/12)))) -> 444.90903 | Z45: =IFERROR(VLOOKUP(S45,'12-SAC Viabilidade'!$B$11:$G$430,6,FALSE),0) -> 2316.6262 | AA45: =IFERROR(VLOOKUP(S45,'12-SAC Viabilidade'!$B$11:$H$430,7,FALSE),0) -> 218285.71 | AB45: =(U45-W45)*'11-Viabilidade'!$O$16 -> 510.44804 | AC45: =U45-(V45+W45+X45+Y45+Z45+AB45-R45) -> -228.2005 | AD45: =U45-(V45+W45+X45+Y45+AB45) -> 2088.4257
B46: =IF(AND(B45>0,B45<'11-Viabilidade'!$P$14),B45+1,0) -> 39 | C46: =IF($B46<'11-Viabilidade'!$C$24,0,$B46-'11-Viabilidade'!$C$24) -> 33 | D46: =IF(C46>0,'11-Viabilidade'!$K$10,0)*((1+'11-Viabilidade'!$O$10)^(($C46-1)/12)) -> 3416.8511 | E46: =D46*'11-Viabilidade'!$L$12 -> 189.82506 | F46: =D46*'11-Viabilidade'!$K$14 -> 0 | G46: =D46*'11-Viabilidade'!$K$15 -> 170.84255 | H46: =IF(D46=0,'11-Viabilidade'!$K$16+'11-Viabilidade'!$K$17,('11-Viabilidade'!$L$11)*((1+'11-Viabilidade'!$O$10)^(($C46-1)/12))) -> 446.72164 | I46: ='12-SAC Viabilidade'!G49 -> 2312.0695 | J46: ='12-SAC Viabilidade'!H49 -> 217714.29 | K46: =(D46-F46)*'11-Viabilidade'!$O$16 -> 512.52766 | L46: =D46-(E46+F46+G46+H46+I46+K46) -> -215.13534 | M46: =D46-(E46+F46+G46+H46+K46) -> 2096.9342 | P46: =IF(B46<='11-Viabilidade'!$G$11,(P45+(P45*'11-Viabilidade'!$H$12)),0) -> 0 | Q46: =IF(B46='11-Viabilidade'!$G$11,'11-Viabilidade'!$G$16,0)*(1+'11-Viabilidade'!$G$12)^((B46-1)/12) -> 0 | R46: =-SUM(O46:Q46) -> 0 | S46: =IF(R46<>0,0,S45+1) -> 39 | T46: =IF($S46<'11-Viabilidade'!$C$24,0,$S46-'11-Viabilidade'!$C$24) -> 33 | U46: =IF(T46>0,'11-Viabilidade'!$K$10,0)*((1+'11-Viabilidade'!$O$10)^(($T46-1)/12)) -> 3416.8511 | V46: =U46*'11-Viabilidade'!$L$12 -> 189.82506 | W46: =U46*'11-Viabilidade'!$K$14 -> 0 | X46: =U46*'11-Viabilidade'!$K$15 -> 170.84255 | Y46: =IF(AND(U46=0,S46=0),0,IF(AND(U46=0,S46<>0),'11-Viabilidade'!$K$16+'11-Viabilidade'!$K$17,('11-Viabilidade'!$L$11)*((1+'11-Viabilidade'!$O$10)^(($C46-1)/12)))) -> 446.72164 | Z46: =IFERROR(VLOOKUP(S46,'12-SAC Viabilidade'!$B$11:$G$430,6,FALSE),0) -> 2312.0695 | AA46: =IFERROR(VLOOKUP(S46,'12-SAC Viabilidade'!$B$11:$H$430,7,FALSE),0) -> 217714.29 | AB46: =(U46-W46)*'11-Viabilidade'!$O$16 -> 512.52766 | AC46: =U46-(V46+W46+X46+Y46+Z46+AB46-R46) -> -215.13534 | AD46: =U46-(V46+W46+X46+Y46+AB46) -> 2096.9342
B47: =IF(AND(B46>0,B46<'11-Viabilidade'!$P$14),B46+1,0) -> 40 | C47: =IF($B47<'11-Viabilidade'!$C$24,0,$B47-'11-Viabilidade'!$C$24) -> 34 | D47: =IF(C47>0,'11-Viabilidade'!$K$10,0)*((1+'11-Viabilidade'!$O$10)^(($C47-1)/12)) -> 3430.7718 | E47: =D47*'11-Viabilidade'!$L$12 -> 190.59843 | F47: =D47*'11-Viabilidade'!$K$14 -> 0 | G47: =D47*'11-Viabilidade'!$K$15 -> 171.53859 | H47: =IF(D47=0,'11-Viabilidade'!$K$16+'11-Viabilidade'!$K$17,('11-Viabilidade'!$L$11)*((1+'11-Viabilidade'!$O$10)^(($C47-1)/12))) -> 448.54164 | I47: ='12-SAC Viabilidade'!G50 -> 2307.5129 | J47: ='12-SAC Viabilidade'!H50 -> 217142.86 | K47: =(D47-F47)*'11-Viabilidade'!$O$16 -> 514.61576 | L47: =D47-(E47+F47+G47+H47+I47+K47) -> -202.03552 | M47: =D47-(E47+F47+G47+H47+K47) -> 2105.4773 | P47: =IF(B47<='11-Viabilidade'!$G$11,(P46+(P46*'11-Viabilidade'!$H$12)),0) -> 0 | Q47: =IF(B47='11-Viabilidade'!$G$11,'11-Viabilidade'!$G$16,0)*(1+'11-Viabilidade'!$G$12)^((B47-1)/12) -> 0 | R47: =-SUM(O47:Q47) -> 0 | S47: =IF(R47<>0,0,S46+1) -> 40 | T47: =IF($S47<'11-Viabilidade'!$C$24,0,$S47-'11-Viabilidade'!$C$24) -> 34 | U47: =IF(T47>0,'11-Viabilidade'!$K$10,0)*((1+'11-Viabilidade'!$O$10)^(($T47-1)/12)) -> 3430.7718 | V47: =U47*'11-Viabilidade'!$L$12 -> 190.59843 | W47: =U47*'11-Viabilidade'!$K$14 -> 0 | X47: =U47*'11-Viabilidade'!$K$15 -> 171.53859 | Y47: =IF(AND(U47=0,S47=0),0,IF(AND(U47=0,S47<>0),'11-Viabilidade'!$K$16+'11-Viabilidade'!$K$17,('11-Viabilidade'!$L$11)*((1+'11-Viabilidade'!$O$10)^(($C47-1)/12)))) -> 448.54164 | Z47: =IFERROR(VLOOKUP(S47,'12-SAC Viabilidade'!$B$11:$G$430,6,FALSE),0) -> 2307.5129 | AA47: =IFERROR(VLOOKUP(S47,'12-SAC Viabilidade'!$B$11:$H$430,7,FALSE),0) -> 217142.86 | AB47: =(U47-W47)*'11-Viabilidade'!$O$16 -> 514.61576 | AC47: =U47-(V47+W47+X47+Y47+Z47+AB47-R47) -> -202.03552 | AD47: =U47-(V47+W47+X47+Y47+AB47) -> 2105.4773
B48: =IF(AND(B47>0,B47<'11-Viabilidade'!$P$14),B47+1,0) -> 41 | C48: =IF($B48<'11-Viabilidade'!$C$24,0,$B48-'11-Viabilidade'!$C$24) -> 35 | D48: =IF(C48>0,'11-Viabilidade'!$K$10,0)*((1+'11-Viabilidade'!$O$10)^(($C48-1)/12)) -> 3444.7492 | E48: =D48*'11-Viabilidade'!$L$12 -> 191.37495 | F48: =D48*'11-Viabilidade'!$K$14 -> 0 | G48: =D48*'11-Viabilidade'!$K$15 -> 172.23746 | H48: =IF(D48=0,'11-Viabilidade'!$K$16+'11-Viabilidade'!$K$17,('11-Viabilidade'!$L$11)*((1+'11-Viabilidade'!$O$10)^(($C48-1)/12))) -> 450.36906 | I48: ='12-SAC Viabilidade'!G51 -> 2302.9562 | J48: ='12-SAC Viabilidade'!H51 -> 216571.43 | K48: =(D48-F48)*'11-Viabilidade'!$O$16 -> 516.71237 | L48: =D48-(E48+F48+G48+H48+I48+K48) -> -188.90089 | M48: =D48-(E48+F48+G48+H48+K48) -> 2114.0553 | P48: =IF(B48<='11-Viabilidade'!$G$11,(P47+(P47*'11-Viabilidade'!$H$12)),0) -> 0 | Q48: =IF(B48='11-Viabilidade'!$G$11,'11-Viabilidade'!$G$16,0)*(1+'11-Viabilidade'!$G$12)^((B48-1)/12) -> 0 | R48: =-SUM(O48:Q48) -> 0 | S48: =IF(R48<>0,0,S47+1) -> 41 | T48: =IF($S48<'11-Viabilidade'!$C$24,0,$S48-'11-Viabilidade'!$C$24) -> 35 | U48: =IF(T48>0,'11-Viabilidade'!$K$10,0)*((1+'11-Viabilidade'!$O$10)^(($T48-1)/12)) -> 3444.7492 | V48: =U48*'11-Viabilidade'!$L$12 -> 191.37495 | W48: =U48*'11-Viabilidade'!$K$14 -> 0 | X48: =U48*'11-Viabilidade'!$K$15 -> 172.23746 | Y48: =IF(AND(U48=0,S48=0),0,IF(AND(U48=0,S48<>0),'11-Viabilidade'!$K$16+'11-Viabilidade'!$K$17,('11-Viabilidade'!$L$11)*((1+'11-Viabilidade'!$O$10)^(($C48-1)/12)))) -> 450.36906 | Z48: =IFERROR(VLOOKUP(S48,'12-SAC Viabilidade'!$B$11:$G$430,6,FALSE),0) -> 2302.9562 | AA48: =IFERROR(VLOOKUP(S48,'12-SAC Viabilidade'!$B$11:$H$430,7,FALSE),0) -> 216571.43 | AB48: =(U48-W48)*'11-Viabilidade'!$O$16 -> 516.71237 | AC48: =U48-(V48+W48+X48+Y48+Z48+AB48-R48) -> -188.90089 | AD48: =U48-(V48+W48+X48+Y48+AB48) -> 2114.0553
B49: =IF(AND(B48>0,B48<'11-Viabilidade'!$P$14),B48+1,0) -> 42 | C49: =IF($B49<'11-Viabilidade'!$C$24,0,$B49-'11-Viabilidade'!$C$24) -> 36 | D49: =IF(C49>0,'11-Viabilidade'!$K$10,0)*((1+'11-Viabilidade'!$O$10)^(($C49-1)/12)) -> 3458.7835 | E49: =D49*'11-Viabilidade'!$L$12 -> 192.15464 | F49: =D49*'11-Viabilidade'!$K$14 -> 0 | G49: =D49*'11-Viabilidade'!$K$15 -> 172.93917 | H49: =IF(D49=0,'11-Viabilidade'!$K$16+'11-Viabilidade'!$K$17,('11-Viabilidade'!$L$11)*((1+'11-Viabilidade'!$O$10)^(($C49-1)/12))) -> 452.20392 | I49: ='12-SAC Viabilidade'!G52 -> 2298.3996 | J49: ='12-SAC Viabilidade'!H52 -> 216000 | K49: =(D49-F49)*'11-Viabilidade'!$O$16 -> 518.81752 | L49: =D49-(E49+F49+G49+H49+I49+K49) -> -175.73132 | M49: =D49-(E49+F49+G49+H49+K49) -> 2122.6682 | P49: =IF(B49<='11-Viabilidade'!$G$11,(P48+(P48*'11-Viabilidade'!$H$12)),0) -> 0 | Q49: =IF(B49='11-Viabilidade'!$G$11,'11-Viabilidade'!$G$16,0)*(1+'11-Viabilidade'!$G$12)^((B49-1)/12) -> 0 | R49: =-SUM(O49:Q49) -> 0 | S49: =IF(R49<>0,0,S48+1) -> 42 | T49: =IF($S49<'11-Viabilidade'!$C$24,0,$S49-'11-Viabilidade'!$C$24) -> 36 | U49: =IF(T49>0,'11-Viabilidade'!$K$10,0)*((1+'11-Viabilidade'!$O$10)^(($T49-1)/12)) -> 3458.7835 | V49: =U49*'11-Viabilidade'!$L$12 -> 192.15464 | W49: =U49*'11-Viabilidade'!$K$14 -> 0 | X49: =U49*'11-Viabilidade'!$K$15 -> 172.93917 | Y49: =IF(AND(U49=0,S49=0),0,IF(AND(U49=0,S49<>0),'11-Viabilidade'!$K$16+'11-Viabilidade'!$K$17,('11-Viabilidade'!$L$11)*((1+'11-Viabilidade'!$O$10)^(($C49-1)/12)))) -> 452.20392 | Z49: =IFERROR(VLOOKUP(S49,'12-SAC Viabilidade'!$B$11:$G$430,6,FALSE),0) -> 2298.3996 | AA49: =IFERROR(VLOOKUP(S49,'12-SAC Viabilidade'!$B$11:$H$430,7,FALSE),0) -> 216000 | AB49: =(U49-W49)*'11-Viabilidade'!$O$16 -> 518.81752 | AC49: =U49-(V49+W49+X49+Y49+Z49+AB49-R49) -> -175.73132 | AD49: =U49-(V49+W49+X49+Y49+AB49) -> 2122.6682
B50: =IF(AND(B49>0,B49<'11-Viabilidade'!$P$14),B49+1,0) -> 43 | C50: =IF($B50<'11-Viabilidade'!$C$24,0,$B50-'11-Viabilidade'!$C$24) -> 37 | D50: =IF(C50>0,'11-Viabilidade'!$K$10,0)*((1+'11-Viabilidade'!$O$10)^(($C50-1)/12)) -> 3472.875 | E50: =D50*'11-Viabilidade'!$L$12 -> 192.9375 | F50: =D50*'11-Viabilidade'!$K$14 -> 0 | G50: =D50*'11-Viabilidade'!$K$15 -> 173.64375 | H50: =IF(D50=0,'11-Viabilidade'!$K$16+'11-Viabilidade'!$K$17,('11-Viabilidade'!$L$11)*((1+'11-Viabilidade'!$O$10)^(($C50-1)/12))) -> 454.04625 | I50: ='12-SAC Viabilidade'!G53 -> 2293.8429 | J50: ='12-SAC Viabilidade'!H53 -> 215428.57 | K50: =(D50-F50)*'11-Viabilidade'!$O$16 -> 520.93125 | L50: =D50-(E50+F50+G50+H50+I50+K50) -> -162.52665 | M50: =D50-(E50+F50+G50+H50+K50) -> 2131.3163 | P50: =IF(B50<='11-Viabilidade'!$G$11,(P49+(P49*'11-Viabilidade'!$H$12)),0) -> 0 | Q50: =IF(B50='11-Viabilidade'!$G$11,'11-Viabilidade'!$G$16,0)*(1+'11-Viabilidade'!$G$12)^((B50-1)/12) -> 0 | R50: =-SUM(O50:Q50) -> 0 | S50: =IF(R50<>0,0,S49+1) -> 43 | T50: =IF($S50<'11-Viabilidade'!$C$24,0,$S50-'11-Viabilidade'!$C$24) -> 37 | U50: =IF(T50>0,'11-Viabilidade'!$K$10,0)*((1+'11-Viabilidade'!$O$10)^(($T50-1)/12)) -> 3472.875 | V50: =U50*'11-Viabilidade'!$L$12 -> 192.9375 | W50: =U50*'11-Viabilidade'!$K$14 -> 0 | X50: =U50*'11-Viabilidade'!$K$15 -> 173.64375 | Y50: =IF(AND(U50=0,S50=0),0,IF(AND(U50=0,S50<>0),'11-Viabilidade'!$K$16+'11-Viabilidade'!$K$17,('11-Viabilidade'!$L$11)*((1+'11-Viabilidade'!$O$10)^(($C50-1)/12)))) -> 454.04625 | Z50: =IFERROR(VLOOKUP(S50,'12-SAC Viabilidade'!$B$11:$G$430,6,FALSE),0) -> 2293.8429 | AA50: =IFERROR(VLOOKUP(S50,'12-SAC Viabilidade'!$B$11:$H$430,7,FALSE),0) -> 215428.57 | AB50: =(U50-W50)*'11-Viabilidade'!$O$16 -> 520.93125 | AC50: =U50-(V50+W50+X50+Y50+Z50+AB50-R50) -> -162.52665 | AD50: =U50-(V50+W50+X50+Y50+AB50) -> 2131.3163
B51: =IF(AND(B50>0,B50<'11-Viabilidade'!$P$14),B50+1,0) -> 44 | C51: =IF($B51<'11-Viabilidade'!$C$24,0,$B51-'11-Viabilidade'!$C$24) -> 38 | D51: =IF(C51>0,'11-Viabilidade'!$K$10,0)*((1+'11-Viabilidade'!$O$10)^(($C51-1)/12)) -> 3487.0239 | E51: =D51*'11-Viabilidade'!$L$12 -> 193.72355 | F51: =D51*'11-Viabilidade'!$K$14 -> 0 | G51: =D51*'11-Viabilidade'!$K$15 -> 174.3512 | H51: =IF(D51=0,'11-Viabilidade'!$K$16+'11-Viabilidade'!$K$17,('11-Viabilidade'!$L$11)*((1+'11-Viabilidade'!$O$10)^(($C51-1)/12))) -> 455.89609 | I51: ='12-SAC Viabilidade'!G54 -> 2289.2863 | J51: ='12-SAC Viabilidade'!H54 -> 214857.14 | K51: =(D51-F51)*'11-Viabilidade'!$O$16 -> 523.05359 | L51: =D51-(E51+F51+G51+H51+I51+K51) -> -149.28676 | M51: =D51-(E51+F51+G51+H51+K51) -> 2139.9995 | P51: =IF(B51<='11-Viabilidade'!$G$11,(P50+(P50*'11-Viabilidade'!$H$12)),0) -> 0 | Q51: =IF(B51='11-Viabilidade'!$G$11,'11-Viabilidade'!$G$16,0)*(1+'11-Viabilidade'!$G$12)^((B51-1)/12) -> 0 | R51: =-SUM(O51:Q51) -> 0 | S51: =IF(R51<>0,0,S50+1) -> 44 | T51: =IF($S51<'11-Viabilidade'!$C$24,0,$S51-'11-Viabilidade'!$C$24) -> 38 | U51: =IF(T51>0,'11-Viabilidade'!$K$10,0)*((1+'11-Viabilidade'!$O$10)^(($T51-1)/12)) -> 3487.0239 | V51: =U51*'11-Viabilidade'!$L$12 -> 193.72355 | W51: =U51*'11-Viabilidade'!$K$14 -> 0 | X51: =U51*'11-Viabilidade'!$K$15 -> 174.3512 | Y51: =IF(AND(U51=0,S51=0),0,IF(AND(U51=0,S51<>0),'11-Viabilidade'!$K$16+'11-Viabilidade'!$K$17,('11-Viabilidade'!$L$11)*((1+'11-Viabilidade'!$O$10)^(($C51-1)/12)))) -> 455.89609 | Z51: =IFERROR(VLOOKUP(S51,'12-SAC Viabilidade'!$B$11:$G$430,6,FALSE),0) -> 2289.2863 | AA51: =IFERROR(VLOOKUP(S51,'12-SAC Viabilidade'!$B$11:$H$430,7,FALSE),0) -> 214857.14 | AB51: =(U51-W51)*'11-Viabilidade'!$O$16 -> 523.05359 | AC51: =U51-(V51+W51+X51+Y51+Z51+AB51-R51) -> -149.28676 | AD51: =U51-(V51+W51+X51+Y51+AB51) -> 2139.9995
B52: =IF(AND(B51>0,B51<'11-Viabilidade'!$P$14),B51+1,0) -> 45 | C52: =IF($B52<'11-Viabilidade'!$C$24,0,$B52-'11-Viabilidade'!$C$24) -> 39 | D52: =IF(C52>0,'11-Viabilidade'!$K$10,0)*((1+'11-Viabilidade'!$O$10)^(($C52-1)/12)) -> 3501.2305 | E52: =D52*'11-Viabilidade'!$L$12 -> 194.5128 | F52: =D52*'11-Viabilidade'!$K$14 -> 0 | G52: =D52*'11-Viabilidade'!$K$15 -> 175.06152 | H52: =IF(D52=0,'11-Viabilidade'!$K$16+'11-Viabilidade'!$K$17,('11-Viabilidade'!$L$11)*((1+'11-Viabilidade'!$O$10)^(($C52-1)/12))) -> 457.75347 | I52: ='12-SAC Viabilidade'!G55 -> 2284.7296 | J52: ='12-SAC Viabilidade'!H55 -> 214285.71 | K52: =(D52-F52)*'11-Viabilidade'!$O$16 -> 525.18457 | L52: =D52-(E52+F52+G52+H52+I52+K52) -> -136.01148 | M52: =D52-(E52+F52+G52+H52+K52) -> 2148.7181 | P52: =IF(B52<='11-Viabilidade'!$G$11,(P51+(P51*'11-Viabilidade'!$H$12)),0) -> 0 | Q52: =IF(B52='11-Viabilidade'!$G$11,'11-Viabilidade'!$G$16,0)*(1+'11-Viabilidade'!$G$12)^((B52-1)/12) -> 0 | R52: =-SUM(O52:Q52) -> 0 | S52: =IF(R52<>0,0,S51+1) -> 45 | T52: =IF($S52<'11-Viabilidade'!$C$24,0,$S52-'11-Viabilidade'!$C$24) -> 39 | U52: =IF(T52>0,'11-Viabilidade'!$K$10,0)*((1+'11-Viabilidade'!$O$10)^(($T52-1)/12)) -> 3501.2305 | V52: =U52*'11-Viabilidade'!$L$12 -> 194.5128 | W52: =U52*'11-Viabilidade'!$K$14 -> 0 | X52: =U52*'11-Viabilidade'!$K$15 -> 175.06152 | Y52: =IF(AND(U52=0,S52=0),0,IF(AND(U52=0,S52<>0),'11-Viabilidade'!$K$16+'11-Viabilidade'!$K$17,('11-Viabilidade'!$L$11)*((1+'11-Viabilidade'!$O$10)^(($C52-1)/12)))) -> 457.75347 | Z52: =IFERROR(VLOOKUP(S52,'12-SAC Viabilidade'!$B$11:$G$430,6,FALSE),0) -> 2284.7296 | AA52: =IFERROR(VLOOKUP(S52,'12-SAC Viabilidade'!$B$11:$H$430,7,FALSE),0) -> 214285.71 | AB52: =(U52-W52)*'11-Viabilidade'!$O$16 -> 525.18457 | AC52: =U52-(V52+W52+X52+Y52+Z52+AB52-R52) -> -136.01148 | AD52: =U52-(V52+W52+X52+Y52+AB52) -> 2148.7181
B53: =IF(AND(B52>0,B52<'11-Viabilidade'!$P$14),B52+1,0) -> 46 | C53: =IF($B53<'11-Viabilidade'!$C$24,0,$B53-'11-Viabilidade'!$C$24) -> 40 | D53: =IF(C53>0,'11-Viabilidade'!$K$10,0)*((1+'11-Viabilidade'!$O$10)^(($C53-1)/12)) -> 3515.4949 | E53: =D53*'11-Viabilidade'!$L$12 -> 195.30527 | F53: =D53*'11-Viabilidade'!$K$14 -> 0 | G53: =D53*'11-Viabilidade'!$K$15 -> 175.77475 | H53: =IF(D53=0,'11-Viabilidade'!$K$16+'11-Viabilidade'!$K$17,('11-Viabilidade'!$L$11)*((1+'11-Viabilidade'!$O$10)^(($C53-1)/12))) -> 459.61841 | I53: ='12-SAC Viabilidade'!G56 -> 2280.1729 | J53: ='12-SAC Viabilidade'!H56 -> 213714.29 | K53: =(D53-F53)*'11-Viabilidade'!$O$16 -> 527.32424 | L53: =D53-(E53+F53+G53+H53+I53+K53) -> -122.70069 | M53: =D53-(E53+F53+G53+H53+K53) -> 2157.4723 | P53: =IF(B53<='11-Viabilidade'!$G$11,(P52+(P52*'11-Viabilidade'!$H$12)),0) -> 0 | Q53: =IF(B53='11-Viabilidade'!$G$11,'11-Viabilidade'!$G$16,0)*(1+'11-Viabilidade'!$G$12)^((B53-1)/12) -> 0 | R53: =-SUM(O53:Q53) -> 0 | S53: =IF(R53<>0,0,S52+1) -> 46 | T53: =IF($S53<'11-Viabilidade'!$C$24,0,$S53-'11-Viabilidade'!$C$24) -> 40 | U53: =IF(T53>0,'11-Viabilidade'!$K$10,0)*((1+'11-Viabilidade'!$O$10)^(($T53-1)/12)) -> 3515.4949 | V53: =U53*'11-Viabilidade'!$L$12 -> 195.30527 | W53: =U53*'11-Viabilidade'!$K$14 -> 0 | X53: =U53*'11-Viabilidade'!$K$15 -> 175.77475 | Y53: =IF(AND(U53=0,S53=0),0,IF(AND(U53=0,S53<>0),'11-Viabilidade'!$K$16+'11-Viabilidade'!$K$17,('11-Viabilidade'!$L$11)*((1+'11-Viabilidade'!$O$10)^(($C53-1)/12)))) -> 459.61841 | Z53: =IFERROR(VLOOKUP(S53,'12-SAC Viabilidade'!$B$11:$G$430,6,FALSE),0) -> 2280.1729 | AA53: =IFERROR(VLOOKUP(S53,'12-SAC Viabilidade'!$B$11:$H$430,7,FALSE),0) -> 213714.29 | AB53: =(U53-W53)*'11-Viabilidade'!$O$16 -> 527.32424 | AC53: =U53-(V53+W53+X53+Y53+Z53+AB53-R53) -> -122.70069 | AD53: =U53-(V53+W53+X53+Y53+AB53) -> 2157.4723
B54: =IF(AND(B53>0,B53<'11-Viabilidade'!$P$14),B53+1,0) -> 47 | C54: =IF($B54<'11-Viabilidade'!$C$24,0,$B54-'11-Viabilidade'!$C$24) -> 41 | D54: =IF(C54>0,'11-Viabilidade'!$K$10,0)*((1+'11-Viabilidade'!$O$10)^(($C54-1)/12)) -> 3529.8175 | E54: =D54*'11-Viabilidade'!$L$12 -> 196.10097 | F54: =D54*'11-Viabilidade'!$K$14 -> 0 | G54: =D54*'11-Viabilidade'!$K$15 -> 176.49087 | H54: =IF(D54=0,'11-Viabilidade'!$K$16+'11-Viabilidade'!$K$17,('11-Viabilidade'!$L$11)*((1+'11-Viabilidade'!$O$10)^(($C54-1)/12))) -> 461.49095 | I54: ='12-SAC Viabilidade'!G57 -> 2275.6163 | J54: ='12-SAC Viabilidade'!H57 -> 213142.86 | K54: =(D54-F54)*'11-Viabilidade'!$O$16 -> 529.47262 | L54: =D54-(E54+F54+G54+H54+I54+K54) -> -109.35423 | M54: =D54-(E54+F54+G54+H54+K54) -> 2166.2621 | P54: =IF(B54<='11-Viabilidade'!$G$11,(P53+(P53*'11-Viabilidade'!$H$12)),0) -> 0 | Q54: =IF(B54='11-Viabilidade'!$G$11,'11-Viabilidade'!$G$16,0)*(1+'11-Viabilidade'!$G$12)^((B54-1)/12) -> 0 | R54: =-SUM(O54:Q54) -> 0 | S54: =IF(R54<>0,0,S53+1) -> 47 | T54: =IF($S54<'11-Viabilidade'!$C$24,0,$S54-'11-Viabilidade'!$C$24) -> 41 | U54: =IF(T54>0,'11-Viabilidade'!$K$10,0)*((1+'11-Viabilidade'!$O$10)^(($T54-1)/12)) -> 3529.8175 | V54: =U54*'11-Viabilidade'!$L$12 -> 196.10097 | W54: =U54*'11-Viabilidade'!$K$14 -> 0 | X54: =U54*'11-Viabilidade'!$K$15 -> 176.49087 | Y54: =IF(AND(U54=0,S54=0),0,IF(AND(U54=0,S54<>0),'11-Viabilidade'!$K$16+'11-Viabilidade'!$K$17,('11-Viabilidade'!$L$11)*((1+'11-Viabilidade'!$O$10)^(($C54-1)/12)))) -> 461.49095 | Z54: =IFERROR(VLOOKUP(S54,'12-SAC Viabilidade'!$B$11:$G$430,6,FALSE),0) -> 2275.6163 | AA54: =IFERROR(VLOOKUP(S54,'12-SAC Viabilidade'!$B$11:$H$430,7,FALSE),0) -> 213142.86 | AB54: =(U54-W54)*'11-Viabilidade'!$O$16 -> 529.47262 | AC54: =U54-(V54+W54+X54+Y54+Z54+AB54-R54) -> -109.35423 | AD54: =U54-(V54+W54+X54+Y54+AB54) -> 2166.2621
A55: 5º Ano | B55: =IF(AND(B54>0,B54<'11-Viabilidade'!$P$14),B54+1,0) -> 48 | C55: =IF($B55<'11-Viabilidade'!$C$24,0,$B55-'11-Viabilidade'!$C$24) -> 42 | D55: =IF(C55>0,'11-Viabilidade'!$K$10,0)*((1+'11-Viabilidade'!$O$10)^(($C55-1)/12)) -> 3544.1984 | E55: =D55*'11-Viabilidade'!$L$12 -> 196.89991 | F55: =D55*'11-Viabilidade'!$K$14 -> 0 | G55: =D55*'11-Viabilidade'!$K$15 -> 177.20992 | H55: =IF(D55=0,'11-Viabilidade'!$K$16+'11-Viabilidade'!$K$17,('11-Viabilidade'!$L$11)*((1+'11-Viabilidade'!$O$10)^(($C55-1)/12))) -> 463.37113 | I55: ='12-SAC Viabilidade'!G58 -> 2271.0596 | J55: ='12-SAC Viabilidade'!H58 -> 212571.43 | K55: =(D55-F55)*'11-Viabilidade'!$O$16 -> 531.62976 | L55: =D55-(E55+F55+G55+H55+I55+K55) -> -95.971954 | M55: =D55-(E55+F55+G55+H55+K55) -> 2175.0877 | P55: =IF(B55<='11-Viabilidade'!$G$11,(P54+(P54*'11-Viabilidade'!$H$12)),0) -> 0 | Q55: =IF(B55='11-Viabilidade'!$G$11,'11-Viabilidade'!$G$16,0)*(1+'11-Viabilidade'!$G$12)^((B55-1)/12) -> 0 | R55: =-SUM(O55:Q55) -> 0 | S55: =IF(R55<>0,0,S54+1) -> 48 | T55: =IF($S55<'11-Viabilidade'!$C$24,0,$S55-'11-Viabilidade'!$C$24) -> 42 | U55: =IF(T55>0,'11-Viabilidade'!$K$10,0)*((1+'11-Viabilidade'!$O$10)^(($T55-1)/12)) -> 3544.1984 | V55: =U55*'11-Viabilidade'!$L$12 -> 196.89991 | W55: =U55*'11-Viabilidade'!$K$14 -> 0 | X55: =U55*'11-Viabilidade'!$K$15 -> 177.20992 | Y55: =IF(AND(U55=0,S55=0),0,IF(AND(U55=0,S55<>0),'11-Viabilidade'!$K$16+'11-Viabilidade'!$K$17,('11-Viabilidade'!$L$11)*((1+'11-Viabilidade'!$O$10)^(($C55-1)/12)))) -> 463.37113 | Z55: =IFERROR(VLOOKUP(S55,'12-SAC Viabilidade'!$B$11:$G$430,6,FALSE),0) -> 2271.0596 | AA55: =IFERROR(VLOOKUP(S55,'12-SAC Viabilidade'!$B$11:$H$430,7,FALSE),0) -> 212571.43 | AB55: =(U55-W55)*'11-Viabilidade'!$O$16 -> 531.62976 | AC55: =U55-(V55+W55+X55+Y55+Z55+AB55-R55) -> -95.971954 | AD55: =U55-(V55+W55+X55+Y55+AB55) -> 2175.0877
B56: =IF(AND(B55>0,B55<'11-Viabilidade'!$P$14),B55+1,0) -> 49 | C56: =IF($B56<'11-Viabilidade'!$C$24,0,$B56-'11-Viabilidade'!$C$24) -> 43 | D56: =IF(C56>0,'11-Viabilidade'!$K$10,0)*((1+'11-Viabilidade'!$O$10)^(($C56-1)/12)) -> 3558.6379 | E56: =D56*'11-Viabilidade'!$L$12 -> 197.70211 | F56: =D56*'11-Viabilidade'!$K$14 -> 0 | G56: =D56*'11-Viabilidade'!$K$15 -> 177.9319 | H56: =IF(D56=0,'11-Viabilidade'!$K$16+'11-Viabilidade'!$K$17,('11-Viabilidade'!$L$11)*((1+'11-Viabilidade'!$O$10)^(($C56-1)/12))) -> 465.25896 | I56: ='12-SAC Viabilidade'!G59 -> 2266.503 | J56: ='12-SAC Viabilidade'!H59 -> 212000 | K56: =(D56-F56)*'11-Viabilidade'!$O$16 -> 533.79569 | L56: =D56-(E56+F56+G56+H56+I56+K56) -> -82.553726 | M56: =D56-(E56+F56+G56+H56+K56) -> 2183.9493 | P56: =IF(B56<='11-Viabilidade'!$G$11,(P55+(P55*'11-Viabilidade'!$H$12)),0) -> 0 | Q56: =IF(B56='11-Viabilidade'!$G$11,'11-Viabilidade'!$G$16,0)*(1+'11-Viabilidade'!$G$12)^((B56-1)/12) -> 0 | R56: =-SUM(O56:Q56) -> 0 | S56: =IF(R56<>0,0,S55+1) -> 49 | T56: =IF($S56<'11-Viabilidade'!$C$24,0,$S56-'11-Viabilidade'!$C$24) -> 43 | U56: =IF(T56>0,'11-Viabilidade'!$K$10,0)*((1+'11-Viabilidade'!$O$10)^(($T56-1)/12)) -> 3558.6379 | V56: =U56*'11-Viabilidade'!$L$12 -> 197.70211 | W56: =U56*'11-Viabilidade'!$K$14 -> 0 | X56: =U56*'11-Viabilidade'!$K$15 -> 177.9319 | Y56: =IF(AND(U56=0,S56=0),0,IF(AND(U56=0,S56<>0),'11-Viabilidade'!$K$16+'11-Viabilidade'!$K$17,('11-Viabilidade'!$L$11)*((1+'11-Viabilidade'!$O$10)^(($C56-1)/12)))) -> 465.25896 | Z56: =IFERROR(VLOOKUP(S56,'12-SAC Viabilidade'!$B$11:$G$430,6,FALSE),0) -> 2266.503 | AA56: =IFERROR(VLOOKUP(S56,'12-SAC Viabilidade'!$B$11:$H$430,7,FALSE),0) -> 212000 | AB56: =(U56-W56)*'11-Viabilidade'!$O$16 -> 533.79569 | AC56: =U56-(V56+W56+X56+Y56+Z56+AB56-R56) -> -82.553726 | AD56: =U56-(V56+W56+X56+Y56+AB56) -> 2183.9493
B57: =IF(AND(B56>0,B56<'11-Viabilidade'!$P$14),B56+1,0) -> 50 | C57: =IF($B57<'11-Viabilidade'!$C$24,0,$B57-'11-Viabilidade'!$C$24) -> 44 | D57: =IF(C57>0,'11-Viabilidade'!$K$10,0)*((1+'11-Viabilidade'!$O$10)^(($C57-1)/12)) -> 3573.1362 | E57: =D57*'11-Viabilidade'!$L$12 -> 198.50757 | F57: =D57*'11-Viabilidade'!$K$14 -> 0 | G57: =D57*'11-Viabilidade'!$K$15 -> 178.65681 | H57: =IF(D57=0,'11-Viabilidade'!$K$16+'11-Viabilidade'!$K$17,('11-Viabilidade'!$L$11)*((1+'11-Viabilidade'!$O$10)^(($C57-1)/12))) -> 467.15448 | I57: ='12-SAC Viabilidade'!G60 -> 2261.9463 | J57: ='12-SAC Viabilidade'!H60 -> 211428.57 | K57: =(D57-F57)*'11-Viabilidade'!$O$16 -> 535.97044 | L57: =D57-(E57+F57+G57+H57+I57+K57) -> -69.099395 | M57: =D57-(E57+F57+G57+H57+K57) -> 2192.8469 | P57: =IF(B57<='11-Viabilidade'!$G$11,(P56+(P56*'11-Viabilidade'!$H$12)),0) -> 0 | Q57: =IF(B57='11-Viabilidade'!$G$11,'11-Viabilidade'!$G$16,0)*(1+'11-Viabilidade'!$G$12)^((B57-1)/12) -> 0 | R57: =-SUM(O57:Q57) -> 0 | S57: =IF(R57<>0,0,S56+1) -> 50 | T57: =IF($S57<'11-Viabilidade'!$C$24,0,$S57-'11-Viabilidade'!$C$24) -> 44 | U57: =IF(T57>0,'11-Viabilidade'!$K$10,0)*((1+'11-Viabilidade'!$O$10)^(($T57-1)/12)) -> 3573.1362 | V57: =U57*'11-Viabilidade'!$L$12 -> 198.50757 | W57: =U57*'11-Viabilidade'!$K$14 -> 0 | X57: =U57*'11-Viabilidade'!$K$15 -> 178.65681 | Y57: =IF(AND(U57=0,S57=0),0,IF(AND(U57=0,S57<>0),'11-Viabilidade'!$K$16+'11-Viabilidade'!$K$17,('11-Viabilidade'!$L$11)*((1+'11-Viabilidade'!$O$10)^(($C57-1)/12)))) -> 467.15448 | Z57: =IFERROR(VLOOKUP(S57,'12-SAC Viabilidade'!$B$11:$G$430,6,FALSE),0) -> 2261.9463 | AA57: =IFERROR(VLOOKUP(S57,'12-SAC Viabilidade'!$B$11:$H$430,7,FALSE),0) -> 211428.57 | AB57: =(U57-W57)*'11-Viabilidade'!$O$16 -> 535.97044 | AC57: =U57-(V57+W57+X57+Y57+Z57+AB57-R57) -> -69.099395 | AD57: =U57-(V57+W57+X57+Y57+AB57) -> 2192.8469
B58: =IF(AND(B57>0,B57<'11-Viabilidade'!$P$14),B57+1,0) -> 51 | C58: =IF($B58<'11-Viabilidade'!$C$24,0,$B58-'11-Viabilidade'!$C$24) -> 45 | D58: =IF(C58>0,'11-Viabilidade'!$K$10,0)*((1+'11-Viabilidade'!$O$10)^(($C58-1)/12)) -> 3587.6936 | E58: =D58*'11-Viabilidade'!$L$12 -> 199.31631 | F58: =D58*'11-Viabilidade'!$K$14 -> 0 | G58: =D58*'11-Viabilidade'!$K$15 -> 179.38468 | H58: =IF(D58=0,'11-Viabilidade'!$K$16+'11-Viabilidade'!$K$17,('11-Viabilidade'!$L$11)*((1+'11-Viabilidade'!$O$10)^(($C58-1)/12))) -> 469.05772 | I58: ='12-SAC Viabilidade'!G61 -> 2257.3897 | J58: ='12-SAC Viabilidade'!H61 -> 210857.14 | K58: =(D58-F58)*'11-Viabilidade'!$O$16 -> 538.15405 | L58: =D58-(E58+F58+G58+H58+I58+K58) -> -55.608813 | M58: =D58-(E58+F58+G58+H58+K58) -> 2201.7809 | P58: =IF(B58<='11-Viabilidade'!$G$11,(P57+(P57*'11-Viabilidade'!$H$12)),0) -> 0 | Q58: =IF(B58='11-Viabilidade'!$G$11,'11-Viabilidade'!$G$16,0)*(1+'11-Viabilidade'!$G$12)^((B58-1)/12) -> 0 | R58: =-SUM(O58:Q58) -> 0 | S58: =IF(R58<>0,0,S57+1) -> 51 | T58: =IF($S58<'11-Viabilidade'!$C$24,0,$S58-'11-Viabilidade'!$C$24) -> 45 | U58: =IF(T58>0,'11-Viabilidade'!$K$10,0)*((1+'11-Viabilidade'!$O$10)^(($T58-1)/12)) -> 3587.6936 | V58: =U58*'11-Viabilidade'!$L$12 -> 199.31631 | W58: =U58*'11-Viabilidade'!$K$14 -> 0 | X58: =U58*'11-Viabilidade'!$K$15 -> 179.38468 | Y58: =IF(AND(U58=0,S58=0),0,IF(AND(U58=0,S58<>0),'11-Viabilidade'!$K$16+'11-Viabilidade'!$K$17,('11-Viabilidade'!$L$11)*((1+'11-Viabilidade'!$O$10)^(($C58-1)/12)))) -> 469.05772 | Z58: =IFERROR(VLOOKUP(S58,'12-SAC Viabilidade'!$B$11:$G$430,6,FALSE),0) -> 2257.3897 | AA58: =IFERROR(VLOOKUP(S58,'12-SAC Viabilidade'!$B$11:$H$430,7,FALSE),0) -> 210857.14 | AB58: =(U58-W58)*'11-Viabilidade'!$O$16 -> 538.15405 | AC58: =U58-(V58+W58+X58+Y58+Z58+AB58-R58) -> -55.608813 | AD58: =U58-(V58+W58+X58+Y58+AB58) -> 2201.7809
B59: =IF(AND(B58>0,B58<'11-Viabilidade'!$P$14),B58+1,0) -> 52 | C59: =IF($B59<'11-Viabilidade'!$C$24,0,$B59-'11-Viabilidade'!$C$24) -> 46 | D59: =IF(C59>0,'11-Viabilidade'!$K$10,0)*((1+'11-Viabilidade'!$O$10)^(($C59-1)/12)) -> 3602.3104 | E59: =D59*'11-Viabilidade'!$L$12 -> 200.12835 | F59: =D59*'11-Viabilidade'!$K$14 -> 0 | G59: =D59*'11-Viabilidade'!$K$15 -> 180.11552 | H59: =IF(D59=0,'11-Viabilidade'!$K$16+'11-Viabilidade'!$K$17,('11-Viabilidade'!$L$11)*((1+'11-Viabilidade'!$O$10)^(($C59-1)/12))) -> 470.96872 | I59: ='12-SAC Viabilidade'!G62 -> 2252.833 | J59: ='12-SAC Viabilidade'!H62 -> 210285.71 | K59: =(D59-F59)*'11-Viabilidade'!$O$16 -> 540.34655 | L59: =D59-(E59+F59+G59+H59+I59+K59) -> -42.081834 | M59: =D59-(E59+F59+G59+H59+K59) -> 2210.7512 | P59: =IF(B59<='11-Viabilidade'!$G$11,(P58+(P58*'11-Viabilidade'!$H$12)),0) -> 0 | Q59: =IF(B59='11-Viabilidade'!$G$11,'11-Viabilidade'!$G$16,0)*(1+'11-Viabilidade'!$G$12)^((B59-1)/12) -> 0 | R59: =-SUM(O59:Q59) -> 0 | S59: =IF(R59<>0,0,S58+1) -> 52 | T59: =IF($S59<'11-Viabilidade'!$C$24,0,$S59-'11-Viabilidade'!$C$24) -> 46 | U59: =IF(T59>0,'11-Viabilidade'!$K$10,0)*((1+'11-Viabilidade'!$O$10)^(($T59-1)/12)) -> 3602.3104 | V59: =U59*'11-Viabilidade'!$L$12 -> 200.12835 | W59: =U59*'11-Viabilidade'!$K$14 -> 0 | X59: =U59*'11-Viabilidade'!$K$15 -> 180.11552 | Y59: =IF(AND(U59=0,S59=0),0,IF(AND(U59=0,S59<>0),'11-Viabilidade'!$K$16+'11-Viabilidade'!$K$17,('11-Viabilidade'!$L$11)*((1+'11-Viabilidade'!$O$10)^(($C59-1)/12)))) -> 470.96872 | Z59: =IFERROR(VLOOKUP(S59,'12-SAC Viabilidade'!$B$11:$G$430,6,FALSE),0) -> 2252.833 | AA59: =IFERROR(VLOOKUP(S59,'12-SAC Viabilidade'!$B$11:$H$430,7,FALSE),0) -> 210285.71 | AB59: =(U59-W59)*'11-Viabilidade'!$O$16 -> 540.34655 | AC59: =U59-(V59+W59+X59+Y59+Z59+AB59-R59) -> -42.081834 | AD59: =U59-(V59+W59+X59+Y59+AB59) -> 2210.7512
B60: =IF(AND(B59>0,B59<'11-Viabilidade'!$P$14),B59+1,0) -> 53 | C60: =IF($B60<'11-Viabilidade'!$C$24,0,$B60-'11-Viabilidade'!$C$24) -> 47 | D60: =IF(C60>0,'11-Viabilidade'!$K$10,0)*((1+'11-Viabilidade'!$O$10)^(($C60-1)/12)) -> 3616.9866 | E60: =D60*'11-Viabilidade'!$L$12 -> 200.9437 | F60: =D60*'11-Viabilidade'!$K$14 -> 0 | G60: =D60*'11-Viabilidade'!$K$15 -> 180.84933 | H60: =IF(D60=0,'11-Viabilidade'!$K$16+'11-Viabilidade'!$K$17,('11-Viabilidade'!$L$11)*((1+'11-Viabilidade'!$O$10)^(($C60-1)/12))) -> 472.88751 | I60: ='12-SAC Viabilidade'!G63 -> 2248.2764 | J60: ='12-SAC Viabilidade'!H63 -> 209714.29 | K60: =(D60-F60)*'11-Viabilidade'!$O$16 -> 542.54799 | L60: =D60-(E60+F60+G60+H60+I60+K60) -> -28.518308 | M60: =D60-(E60+F60+G60+H60+K60) -> 2219.7581 | P60: =IF(B60<='11-Viabilidade'!$G$11,(P59+(P59*'11-Viabilidade'!$H$12)),0) -> 0 | Q60: =IF(B60='11-Viabilidade'!$G$11,'11-Viabilidade'!$G$16,0)*(1+'11-Viabilidade'!$G$12)^((B60-1)/12) -> 0 | R60: =-SUM(O60:Q60) -> 0 | S60: =IF(R60<>0,0,S59+1) -> 53 | T60: =IF($S60<'11-Viabilidade'!$C$24,0,$S60-'11-Viabilidade'!$C$24) -> 47 | U60: =IF(T60>0,'11-Viabilidade'!$K$10,0)*((1+'11-Viabilidade'!$O$10)^(($T60-1)/12)) -> 3616.9866 | V60: =U60*'11-Viabilidade'!$L$12 -> 200.9437 | W60: =U60*'11-Viabilidade'!$K$14 -> 0 | X60: =U60*'11-Viabilidade'!$K$15 -> 180.84933 | Y60: =IF(AND(U60=0,S60=0),0,IF(AND(U60=0,S60<>0),'11-Viabilidade'!$K$16+'11-Viabilidade'!$K$17,('11-Viabilidade'!$L$11)*((1+'11-Viabilidade'!$O$10)^(($C60-1)/12)))) -> 472.88751 | Z60: =IFERROR(VLOOKUP(S60,'12-SAC Viabilidade'!$B$11:$G$430,6,FALSE),0) -> 2248.2764 | AA60: =IFERROR(VLOOKUP(S60,'12-SAC Viabilidade'!$B$11:$H$430,7,FALSE),0) -> 209714.29 | AB60: =(U60-W60)*'11-Viabilidade'!$O$16 -> 542.54799 | AC60: =U60-(V60+W60+X60+Y60+Z60+AB60-R60) -> -28.518308 | AD60: =U60-(V60+W60+X60+Y60+AB60) -> 2219.7581
B61: =IF(AND(B60>0,B60<'11-Viabilidade'!$P$14),B60+1,0) -> 54 | C61: =IF($B61<'11-Viabilidade'!$C$24,0,$B61-'11-Viabilidade'!$C$24) -> 48 | D61: =IF(C61>0,'11-Viabilidade'!$K$10,0)*((1+'11-Viabilidade'!$O$10)^(($C61-1)/12)) -> 3631.7227 | E61: =D61*'11-Viabilidade'!$L$12 -> 201.76237 | F61: =D61*'11-Viabilidade'!$K$14 -> 0 | G61: =D61*'11-Viabilidade'!$K$15 -> 181.58613 | H61: =IF(D61=0,'11-Viabilidade'!$K$16+'11-Viabilidade'!$K$17,('11-Viabilidade'!$L$11)*((1+'11-Viabilidade'!$O$10)^(($C61-1)/12))) -> 474.81411 | I61: ='12-SAC Viabilidade'!G64 -> 2243.7197 | J61: ='12-SAC Viabilidade'!H64 -> 209142.86 | K61: =(D61-F61)*'11-Viabilidade'!$O$16 -> 544.7584 | L61: =D61-(E61+F61+G61+H61+I61+K61) -> -14.918087 | M61: =D61-(E61+F61+G61+H61+K61) -> 2228.8016 | P61: =IF(B61<='11-Viabilidade'!$G$11,(P60+(P60*'11-Viabilidade'!$H$12)),0) -> 0 | Q61: =IF(B61='11-Viabilidade'!$G$11,'11-Viabilidade'!$G$16,0)*(1+'11-Viabilidade'!$G$12)^((B61-1)/12) -> 0 | R61: =-SUM(O61:Q61) -> 0 | S61: =IF(R61<>0,0,S60+1) -> 54 | T61: =IF($S61<'11-Viabilidade'!$C$24,0,$S61-'11-Viabilidade'!$C$24) -> 48 | U61: =IF(T61>0,'11-Viabilidade'!$K$10,0)*((1+'11-Viabilidade'!$O$10)^(($T61-1)/12)) -> 3631.7227 | V61: =U61*'11-Viabilidade'!$L$12 -> 201.76237 | W61: =U61*'11-Viabilidade'!$K$14 -> 0 | X61: =U61*'11-Viabilidade'!$K$15 -> 181.58613 | Y61: =IF(AND(U61=0,S61=0),0,IF(AND(U61=0,S61<>0),'11-Viabilidade'!$K$16+'11-Viabilidade'!$K$17,('11-Viabilidade'!$L$11)*((1+'11-Viabilidade'!$O$10)^(($C61-1)/12)))) -> 474.81411 | Z61: =IFERROR(VLOOKUP(S61,'12-SAC Viabilidade'!$B$11:$G$430,6,FALSE),0) -> 2243.7197 | AA61: =IFERROR(VLOOKUP(S61,'12-SAC Viabilidade'!$B$11:$H$430,7,FALSE),0) -> 209142.86 | AB61: =(U61-W61)*'11-Viabilidade'!$O$16 -> 544.7584 | AC61: =U61-(V61+W61+X61+Y61+Z61+AB61-R61) -> -14.918087 | AD61: =U61-(V61+W61+X61+Y61+AB61) -> 2228.8016
B62: =IF(AND(B61>0,B61<'11-Viabilidade'!$P$14),B61+1,0) -> 55 | C62: =IF($B62<'11-Viabilidade'!$C$24,0,$B62-'11-Viabilidade'!$C$24) -> 49 | D62: =IF(C62>0,'11-Viabilidade'!$K$10,0)*((1+'11-Viabilidade'!$O$10)^(($C62-1)/12)) -> 3646.5188 | E62: =D62*'11-Viabilidade'!$L$12 -> 202.58437 | F62: =D62*'11-Viabilidade'!$K$14 -> 0 | G62: =D62*'11-Viabilidade'!$K$15 -> 182.32594 | H62: =IF(D62=0,'11-Viabilidade'!$K$16+'11-Viabilidade'!$K$17,('11-Viabilidade'!$L$11)*((1+'11-Viabilidade'!$O$10)^(($C62-1)/12))) -> 476.74856 | I62: ='12-SAC Viabilidade'!G65 -> 2239.1631 | J62: ='12-SAC Viabilidade'!H65 -> 208571.43 | K62: =(D62-F62)*'11-Viabilidade'!$O$16 -> 546.97781 | L62: =D62-(E62+F62+G62+H62+I62+K62) -> -1.2810215 | M62: =D62-(E62+F62+G62+H62+K62) -> 2237.8821 | P62: =IF(B62<='11-Viabilidade'!$G$11,(P61+(P61*'11-Viabilidade'!$H$12)),0) -> 0 | Q62: =IF(B62='11-Viabilidade'!$G$11,'11-Viabilidade'!$G$16,0)*(1+'11-Viabilidade'!$G$12)^((B62-1)/12) -> 0 | R62: =-SUM(O62:Q62) -> 0 | S62: =IF(R62<>0,0,S61+1) -> 55 | T62: =IF($S62<'11-Viabilidade'!$C$24,0,$S62-'11-Viabilidade'!$C$24) -> 49 | U62: =IF(T62>0,'11-Viabilidade'!$K$10,0)*((1+'11-Viabilidade'!$O$10)^(($T62-1)/12)) -> 3646.5188 | V62: =U62*'11-Viabilidade'!$L$12 -> 202.58437 | W62: =U62*'11-Viabilidade'!$K$14 -> 0 | X62: =U62*'11-Viabilidade'!$K$15 -> 182.32594 | Y62: =IF(AND(U62=0,S62=0),0,IF(AND(U62=0,S62<>0),'11-Viabilidade'!$K$16+'11-Viabilidade'!$K$17,('11-Viabilidade'!$L$11)*((1+'11-Viabilidade'!$O$10)^(($C62-1)/12)))) -> 476.74856 | Z62: =IFERROR(VLOOKUP(S62,'12-SAC Viabilidade'!$B$11:$G$430,6,FALSE),0) -> 2239.1631 | AA62: =IFERROR(VLOOKUP(S62,'12-SAC Viabilidade'!$B$11:$H$430,7,FALSE),0) -> 208571.43 | AB62: =(U62-W62)*'11-Viabilidade'!$O$16 -> 546.97781 | AC62: =U62-(V62+W62+X62+Y62+Z62+AB62-R62) -> -1.2810215 | AD62: =U62-(V62+W62+X62+Y62+AB62) -> 2237.8821
B63: =IF(AND(B62>0,B62<'11-Viabilidade'!$P$14),B62+1,0) -> 56 | C63: =IF($B63<'11-Viabilidade'!$C$24,0,$B63-'11-Viabilidade'!$C$24) -> 50 | D63: =IF(C63>0,'11-Viabilidade'!$K$10,0)*((1+'11-Viabilidade'!$O$10)^(($C63-1)/12)) -> 3661.3751 | E63: =D63*'11-Viabilidade'!$L$12 -> 203.40973 | F63: =D63*'11-Viabilidade'!$K$14 -> 0 | G63: =D63*'11-Viabilidade'!$K$15 -> 183.06876 | H63: =IF(D63=0,'11-Viabilidade'!$K$16+'11-Viabilidade'!$K$17,('11-Viabilidade'!$L$11)*((1+'11-Viabilidade'!$O$10)^(($C63-1)/12))) -> 478.6909 | I63: ='12-SAC Viabilidade'!G66 -> 2234.6064 | J63: ='12-SAC Viabilidade'!H66 -> 208000 | K63: =(D63-F63)*'11-Viabilidade'!$O$16 -> 549.20627 | L63: =D63-(E63+F63+G63+H63+I63+K63) -> 12.393039 | M63: =D63-(E63+F63+G63+H63+K63) -> 2246.9995 | P63: =IF(B63<='11-Viabilidade'!$G$11,(P62+(P62*'11-Viabilidade'!$H$12)),0) -> 0 | Q63: =IF(B63='11-Viabilidade'!$G$11,'11-Viabilidade'!$G$16,0)*(1+'11-Viabilidade'!$G$12)^((B63-1)/12) -> 0 | R63: =-SUM(O63:Q63) -> 0 | S63: =IF(R63<>0,0,S62+1) -> 56 | T63: =IF($S63<'11-Viabilidade'!$C$24,0,$S63-'11-Viabilidade'!$C$24) -> 50 | U63: =IF(T63>0,'11-Viabilidade'!$K$10,0)*((1+'11-Viabilidade'!$O$10)^(($T63-1)/12)) -> 3661.3751 | V63: =U63*'11-Viabilidade'!$L$12 -> 203.40973 | W63: =U63*'11-Viabilidade'!$K$14 -> 0 | X63: =U63*'11-Viabilidade'!$K$15 -> 183.06876 | Y63: =IF(AND(U63=0,S63=0),0,IF(AND(U63=0,S63<>0),'11-Viabilidade'!$K$16+'11-Viabilidade'!$K$17,('11-Viabilidade'!$L$11)*((1+'11-Viabilidade'!$O$10)^(($C63-1)/12)))) -> 478.6909 | Z63: =IFERROR(VLOOKUP(S63,'12-SAC Viabilidade'!$B$11:$G$430,6,FALSE),0) -> 2234.6064 | AA63: =IFERROR(VLOOKUP(S63,'12-SAC Viabilidade'!$B$11:$H$430,7,FALSE),0) -> 208000 | AB63: =(U63-W63)*'11-Viabilidade'!$O$16 -> 549.20627 | AC63: =U63-(V63+W63+X63+Y63+Z63+AB63-R63) -> 12.393039 | AD63: =U63-(V63+W63+X63+Y63+AB63) -> 2246.9995
B64: =IF(AND(B63>0,B63<'11-Viabilidade'!$P$14),B63+1,0) -> 57 | C64: =IF($B64<'11-Viabilidade'!$C$24,0,$B64-'11-Viabilidade'!$C$24) -> 51 | D64: =IF(C64>0,'11-Viabilidade'!$K$10,0)*((1+'11-Viabilidade'!$O$10)^(($C64-1)/12)) -> 3676.292 | E64: =D64*'11-Viabilidade'!$L$12 -> 204.23845 | F64: =D64*'11-Viabilidade'!$K$14 -> 0 | G64: =D64*'11-Viabilidade'!$K$15 -> 183.8146 | H64: =IF(D64=0,'11-Viabilidade'!$K$16+'11-Viabilidade'!$K$17,('11-Viabilidade'!$L$11)*((1+'11-Viabilidade'!$O$10)^(($C64-1)/12))) -> 480.64114 | I64: ='12-SAC Viabilidade'!G67 -> 2230.0498 | J64: ='12-SAC Viabilidade'!H67 -> 207428.57 | K64: =(D64-F64)*'11-Viabilidade'!$O$16 -> 551.4438 | L64: =D64-(E64+F64+G64+H64+I64+K64) -> 26.104244 | M64: =D64-(E64+F64+G64+H64+K64) -> 2256.154 | P64: =IF(B64<='11-Viabilidade'!$G$11,(P63+(P63*'11-Viabilidade'!$H$12)),0) -> 0 | Q64: =IF(B64='11-Viabilidade'!$G$11,'11-Viabilidade'!$G$16,0)*(1+'11-Viabilidade'!$G$12)^((B64-1)/12) -> 0 | R64: =-SUM(O64:Q64) -> 0 | S64: =IF(R64<>0,0,S63+1) -> 57 | T64: =IF($S64<'11-Viabilidade'!$C$24,0,$S64-'11-Viabilidade'!$C$24) -> 51 | U64: =IF(T64>0,'11-Viabilidade'!$K$10,0)*((1+'11-Viabilidade'!$O$10)^(($T64-1)/12)) -> 3676.292 | V64: =U64*'11-Viabilidade'!$L$12 -> 204.23845 | W64: =U64*'11-Viabilidade'!$K$14 -> 0 | X64: =U64*'11-Viabilidade'!$K$15 -> 183.8146 | Y64: =IF(AND(U64=0,S64=0),0,IF(AND(U64=0,S64<>0),'11-Viabilidade'!$K$16+'11-Viabilidade'!$K$17,('11-Viabilidade'!$L$11)*((1+'11-Viabilidade'!$O$10)^(($C64-1)/12)))) -> 480.64114 | Z64: =IFERROR(VLOOKUP(S64,'12-SAC Viabilidade'!$B$11:$G$430,6,FALSE),0) -> 2230.0498 | AA64: =IFERROR(VLOOKUP(S64,'12-SAC Viabilidade'!$B$11:$H$430,7,FALSE),0) -> 207428.57 | AB64: =(U64-W64)*'11-Viabilidade'!$O$16 -> 551.4438 | AC64: =U64-(V64+W64+X64+Y64+Z64+AB64-R64) -> 26.104244 | AD64: =U64-(V64+W64+X64+Y64+AB64) -> 2256.154
B65: =IF(AND(B64>0,B64<'11-Viabilidade'!$P$14),B64+1,0) -> 58 | C65: =IF($B65<'11-Viabilidade'!$C$24,0,$B65-'11-Viabilidade'!$C$24) -> 52 | D65: =IF(C65>0,'11-Viabilidade'!$K$10,0)*((1+'11-Viabilidade'!$O$10)^(($C65-1)/12)) -> 3691.2697 | E65: =D65*'11-Viabilidade'!$L$12 -> 205.07054 | F65: =D65*'11-Viabilidade'!$K$14 -> 0 | G65: =D65*'11-Viabilidade'!$K$15 -> 184.56348 | H65: =IF(D65=0,'11-Viabilidade'!$K$16+'11-Viabilidade'!$K$17,('11-Viabilidade'!$L$11)*((1+'11-Viabilidade'!$O$10)^(($C65-1)/12))) -> 482.59933 | I65: ='12-SAC Viabilidade'!G68 -> 2225.4931 | J65: ='12-SAC Viabilidade'!H68 -> 206857.14 | K65: =(D65-F65)*'11-Viabilidade'!$O$16 -> 553.69045 | L65: =D65-(E65+F65+G65+H65+I65+K65) -> 39.852747 | M65: =D65-(E65+F65+G65+H65+K65) -> 2265.3459 | P65: =IF(B65<='11-Viabilidade'!$G$11,(P64+(P64*'11-Viabilidade'!$H$12)),0) -> 0 | Q65: =IF(B65='11-Viabilidade'!$G$11,'11-Viabilidade'!$G$16,0)*(1+'11-Viabilidade'!$G$12)^((B65-1)/12) -> 0 | R65: =-SUM(O65:Q65) -> 0 | S65: =IF(R65<>0,0,S64+1) -> 58 | T65: =IF($S65<'11-Viabilidade'!$C$24,0,$S65-'11-Viabilidade'!$C$24) -> 52 | U65: =IF(T65>0,'11-Viabilidade'!$K$10,0)*((1+'11-Viabilidade'!$O$10)^(($T65-1)/12)) -> 3691.2697 | V65: =U65*'11-Viabilidade'!$L$12 -> 205.07054 | W65: =U65*'11-Viabilidade'!$K$14 -> 0 | X65: =U65*'11-Viabilidade'!$K$15 -> 184.56348 | Y65: =IF(AND(U65=0,S65=0),0,IF(AND(U65=0,S65<>0),'11-Viabilidade'!$K$16+'11-Viabilidade'!$K$17,('11-Viabilidade'!$L$11)*((1+'11-Viabilidade'!$O$10)^(($C65-1)/12)))) -> 482.59933 | Z65: =IFERROR(VLOOKUP(S65,'12-SAC Viabilidade'!$B$11:$G$430,6,FALSE),0) -> 2225.4931 | AA65: =IFERROR(VLOOKUP(S65,'12-SAC Viabilidade'!$B$11:$H$430,7,FALSE),0) -> 206857.14 | AB65: =(U65-W65)*'11-Viabilidade'!$O$16 -> 553.69045 | AC65: =U65-(V65+W65+X65+Y65+Z65+AB65-R65) -> 39.852747 | AD65: =U65-(V65+W65+X65+Y65+AB65) -> 2265.3459
B66: =IF(AND(B65>0,B65<'11-Viabilidade'!$P$14),B65+1,0) -> 59 | C66: =IF($B66<'11-Viabilidade'!$C$24,0,$B66-'11-Viabilidade'!$C$24) -> 53 | D66: =IF(C66>0,'11-Viabilidade'!$K$10,0)*((1+'11-Viabilidade'!$O$10)^(($C66-1)/12)) -> 3706.3084 | E66: =D66*'11-Viabilidade'!$L$12 -> 205.90602 | F66: =D66*'11-Viabilidade'!$K$14 -> 0 | G66: =D66*'11-Viabilidade'!$K$15 -> 185.31542 | H66: =IF(D66=0,'11-Viabilidade'!$K$16+'11-Viabilidade'!$K$17,('11-Viabilidade'!$L$11)*((1+'11-Viabilidade'!$O$10)^(($C66-1)/12))) -> 484.5655 | I66: ='12-SAC Viabilidade'!G69 -> 2220.9365 | J66: ='12-SAC Viabilidade'!H69 -> 206285.71 | K66: =(D66-F66)*'11-Viabilidade'!$O$16 -> 555.94626 | L66: =D66-(E66+F66+G66+H66+I66+K66) -> 53.638698 | M66: =D66-(E66+F66+G66+H66+K66) -> 2274.5752 | P66: =IF(B66<='11-Viabilidade'!$G$11,(P65+(P65*'11-Viabilidade'!$H$12)),0) -> 0 | Q66: =IF(B66='11-Viabilidade'!$G$11,'11-Viabilidade'!$G$16,0)*(1+'11-Viabilidade'!$G$12)^((B66-1)/12) -> 0 | R66: =-SUM(O66:Q66) -> 0 | S66: =IF(R66<>0,0,S65+1) -> 59 | T66: =IF($S66<'11-Viabilidade'!$C$24,0,$S66-'11-Viabilidade'!$C$24) -> 53 | U66: =IF(T66>0,'11-Viabilidade'!$K$10,0)*((1+'11-Viabilidade'!$O$10)^(($T66-1)/12)) -> 3706.3084 | V66: =U66*'11-Viabilidade'!$L$12 -> 205.90602 | W66: =U66*'11-Viabilidade'!$K$14 -> 0 | X66: =U66*'11-Viabilidade'!$K$15 -> 185.31542 | Y66: =IF(AND(U66=0,S66=0),0,IF(AND(U66=0,S66<>0),'11-Viabilidade'!$K$16+'11-Viabilidade'!$K$17,('11-Viabilidade'!$L$11)*((1+'11-Viabilidade'!$O$10)^(($C66-1)/12)))) -> 484.5655 | Z66: =IFERROR(VLOOKUP(S66,'12-SAC Viabilidade'!$B$11:$G$430,6,FALSE),0) -> 2220.9365 | AA66: =IFERROR(VLOOKUP(S66,'12-SAC Viabilidade'!$B$11:$H$430,7,FALSE),0) -> 206285.71 | AB66: =(U66-W66)*'11-Viabilidade'!$O$16 -> 555.94626 | AC66: =U66-(V66+W66+X66+Y66+Z66+AB66-R66) -> 53.638698 | AD66: =U66-(V66+W66+X66+Y66+AB66) -> 2274.5752
A67: 6º Ano | B67: =IF(AND(B66>0,B66<'11-Viabilidade'!$P$14),B66+1,0) -> 60 | C67: =IF($B67<'11-Viabilidade'!$C$24,0,$B67-'11-Viabilidade'!$C$24) -> 54 | D67: =IF(C67>0,'11-Viabilidade'!$K$10,0)*((1+'11-Viabilidade'!$O$10)^(($C67-1)/12)) -> 3721.4083 | E67: =D67*'11-Viabilidade'!$L$12 -> 206.74491 | F67: =D67*'11-Viabilidade'!$K$14 -> 0 | G67: =D67*'11-Viabilidade'!$K$15 -> 186.07042 | H67: =IF(D67=0,'11-Viabilidade'!$K$16+'11-Viabilidade'!$K$17,('11-Viabilidade'!$L$11)*((1+'11-Viabilidade'!$O$10)^(($C67-1)/12))) -> 486.53968 | I67: ='12-SAC Viabilidade'!G70 -> 2216.3798 | J67: ='12-SAC Viabilidade'!H70 -> 205714.29 | K67: =(D67-F67)*'11-Viabilidade'!$O$16 -> 558.21125 | L67: =D67-(E67+F67+G67+H67+I67+K67) -> 67.462251 | M67: =D67-(E67+F67+G67+H67+K67) -> 2283.8421 | P67: =IF(B67<='11-Viabilidade'!$G$11,(P66+(P66*'11-Viabilidade'!$H$12)),0) -> 0 | Q67: =IF(B67='11-Viabilidade'!$G$11,'11-Viabilidade'!$G$16,0)*(1+'11-Viabilidade'!$G$12)^((B67-1)/12) -> 0 | R67: =-SUM(O67:Q67) -> 0 | S67: =IF(R67<>0,0,S66+1) -> 60 | T67: =IF($S67<'11-Viabilidade'!$C$24,0,$S67-'11-Viabilidade'!$C$24) -> 54 | U67: =IF(T67>0,'11-Viabilidade'!$K$10,0)*((1+'11-Viabilidade'!$O$10)^(($T67-1)/12)) -> 3721.4083 | V67: =U67*'11-Viabilidade'!$L$12 -> 206.74491 | W67: =U67*'11-Viabilidade'!$K$14 -> 0 | X67: =U67*'11-Viabilidade'!$K$15 -> 186.07042 | Y67: =IF(AND(U67=0,S67=0),0,IF(AND(U67=0,S67<>0),'11-Viabilidade'!$K$16+'11-Viabilidade'!$K$17,('11-Viabilidade'!$L$11)*((1+'11-Viabilidade'!$O$10)^(($C67-1)/12)))) -> 486.53968 | Z67: =IFERROR(VLOOKUP(S67,'12-SAC Viabilidade'!$B$11:$G$430,6,FALSE),0) -> 2216.3798 | AA67: =IFERROR(VLOOKUP(S67,'12-SAC Viabilidade'!$B$11:$H$430,7,FALSE),0) -> 205714.29 | AB67: =(U67-W67)*'11-Viabilidade'!$O$16 -> 558.21125 | AC67: =U67-(V67+W67+X67+Y67+Z67+AB67-R67) -> 67.462251 | AD67: =U67-(V67+W67+X67+Y67+AB67) -> 2283.8421
B68: =IF(AND(B67>0,B67<'11-Viabilidade'!$P$14),B67+1,0) -> 61 | C68: =IF($B68<'11-Viabilidade'!$C$24,0,$B68-'11-Viabilidade'!$C$24) -> 55 | D68: =IF(C68>0,'11-Viabilidade'!$K$10,0)*((1+'11-Viabilidade'!$O$10)^(($C68-1)/12)) -> 3736.5698 | E68: =D68*'11-Viabilidade'!$L$12 -> 207.58721 | F68: =D68*'11-Viabilidade'!$K$14 -> 0 | G68: =D68*'11-Viabilidade'!$K$15 -> 186.82849 | H68: =IF(D68=0,'11-Viabilidade'!$K$16+'11-Viabilidade'!$K$17,('11-Viabilidade'!$L$11)*((1+'11-Viabilidade'!$O$10)^(($C68-1)/12))) -> 488.5219 | I68: ='12-SAC Viabilidade'!G71 -> 2211.8232 | J68: ='12-SAC Viabilidade'!H71 -> 205142.86 | K68: =(D68-F68)*'11-Viabilidade'!$O$16 -> 560.48547 | L68: =D68-(E68+F68+G68+H68+I68+K68) -> 81.323558 | M68: =D68-(E68+F68+G68+H68+K68) -> 2293.1467 | P68: =IF(B68<='11-Viabilidade'!$G$11,(P67+(P67*'11-Viabilidade'!$H$12)),0) -> 0 | Q68: =IF(B68='11-Viabilidade'!$G$11,'11-Viabilidade'!$G$16,0)*(1+'11-Viabilidade'!$G$12)^((B68-1)/12) -> 0 | R68: =-SUM(O68:Q68) -> 0 | S68: =IF(R68<>0,0,S67+1) -> 61 | T68: =IF($S68<'11-Viabilidade'!$C$24,0,$S68-'11-Viabilidade'!$C$24) -> 55 | U68: =IF(T68>0,'11-Viabilidade'!$K$10,0)*((1+'11-Viabilidade'!$O$10)^(($T68-1)/12)) -> 3736.5698 | V68: =U68*'11-Viabilidade'!$L$12 -> 207.58721 | W68: =U68*'11-Viabilidade'!$K$14 -> 0 | X68: =U68*'11-Viabilidade'!$K$15 -> 186.82849 | Y68: =IF(AND(U68=0,S68=0),0,IF(AND(U68=0,S68<>0),'11-Viabilidade'!$K$16+'11-Viabilidade'!$K$17,('11-Viabilidade'!$L$11)*((1+'11-Viabilidade'!$O$10)^(($C68-1)/12)))) -> 488.5219 | Z68: =IFERROR(VLOOKUP(S68,'12-SAC Viabilidade'!$B$11:$G$430,6,FALSE),0) -> 2211.8232 | AA68: =IFERROR(VLOOKUP(S68,'12-SAC Viabilidade'!$B$11:$H$430,7,FALSE),0) -> 205142.86 | AB68: =(U68-W68)*'11-Viabilidade'!$O$16 -> 560.48547 | AC68: =U68-(V68+W68+X68+Y68+Z68+AB68-R68) -> 81.323558 | AD68: =U68-(V68+W68+X68+Y68+AB68) -> 2293.1467
B69: =IF(AND(B68>0,B68<'11-Viabilidade'!$P$14),B68+1,0) -> 62 | C69: =IF($B69<'11-Viabilidade'!$C$24,0,$B69-'11-Viabilidade'!$C$24) -> 56 | D69: =IF(C69>0,'11-Viabilidade'!$K$10,0)*((1+'11-Viabilidade'!$O$10)^(($C69-1)/12)) -> 3751.7931 | E69: =D69*'11-Viabilidade'!$L$12 -> 208.43295 | F69: =D69*'11-Viabilidade'!$K$14 -> 0 | G69: =D69*'11-Viabilidade'!$K$15 -> 187.58965 | H69: =IF(D69=0,'11-Viabilidade'!$K$16+'11-Viabilidade'!$K$17,('11-Viabilidade'!$L$11)*((1+'11-Viabilidade'!$O$10)^(($C69-1)/12))) -> 490.5122 | I69: ='12-SAC Viabilidade'!G72 -> 2207.2665 | J69: ='12-SAC Viabilidade'!H72 -> 204571.43 | K69: =(D69-F69)*'11-Viabilidade'!$O$16 -> 562.76896 | L69: =D69-(E69+F69+G69+H69+I69+K69) -> 95.222773 | M69: =D69-(E69+F69+G69+H69+K69) -> 2302.4893 | P69: =IF(B69<='11-Viabilidade'!$G$11,(P68+(P68*'11-Viabilidade'!$H$12)),0) -> 0 | Q69: =IF(B69='11-Viabilidade'!$G$11,'11-Viabilidade'!$G$16,0)*(1+'11-Viabilidade'!$G$12)^((B69-1)/12) -> 0 | R69: =-SUM(O69:Q69) -> 0 | S69: =IF(R69<>0,0,S68+1) -> 62 | T69: =IF($S69<'11-Viabilidade'!$C$24,0,$S69-'11-Viabilidade'!$C$24) -> 56 | U69: =IF(T69>0,'11-Viabilidade'!$K$10,0)*((1+'11-Viabilidade'!$O$10)^(($T69-1)/12)) -> 3751.7931 | V69: =U69*'11-Viabilidade'!$L$12 -> 208.43295 | W69: =U69*'11-Viabilidade'!$K$14 -> 0 | X69: =U69*'11-Viabilidade'!$K$15 -> 187.58965 | Y69: =IF(AND(U69=0,S69=0),0,IF(AND(U69=0,S69<>0),'11-Viabilidade'!$K$16+'11-Viabilidade'!$K$17,('11-Viabilidade'!$L$11)*((1+'11-Viabilidade'!$O$10)^(($C69-1)/12)))) -> 490.5122 | Z69: =IFERROR(VLOOKUP(S69,'12-SAC Viabilidade'!$B$11:$G$430,6,FALSE),0) -> 2207.2665 | AA69: =IFERROR(VLOOKUP(S69,'12-SAC Viabilidade'!$B$11:$H$430,7,FALSE),0) -> 204571.43 | AB69: =(U69-W69)*'11-Viabilidade'!$O$16 -> 562.76896 | AC69: =U69-(V69+W69+X69+Y69+Z69+AB69-R69) -> 95.222773 | AD69: =U69-(V69+W69+X69+Y69+AB69) -> 2302.4893
B70: =IF(AND(B69>0,B69<'11-Viabilidade'!$P$14),B69+1,0) -> 63 | C70: =IF($B70<'11-Viabilidade'!$C$24,0,$B70-'11-Viabilidade'!$C$24) -> 57 | D70: =IF(C70>0,'11-Viabilidade'!$K$10,0)*((1+'11-Viabilidade'!$O$10)^(($C70-1)/12)) -> 3767.0783 | E70: =D70*'11-Viabilidade'!$L$12 -> 209.28213 | F70: =D70*'11-Viabilidade'!$K$14 -> 0 | G70: =D70*'11-Viabilidade'!$K$15 -> 188.35392 | H70: =IF(D70=0,'11-Viabilidade'!$K$16+'11-Viabilidade'!$K$17,('11-Viabilidade'!$L$11)*((1+'11-Viabilidade'!$O$10)^(($C70-1)/12))) -> 492.51061 | I70: ='12-SAC Viabilidade'!G73 -> 2202.7099 | J70: ='12-SAC Viabilidade'!H73 -> 204000 | K70: =(D70-F70)*'11-Viabilidade'!$O$16 -> 565.06175 | L70: =D70-(E70+F70+G70+H70+I70+K70) -> 109.16005 | M70: =D70-(E70+F70+G70+H70+K70) -> 2311.8699 | P70: =IF(B70<='11-Viabilidade'!$G$11,(P69+(P69*'11-Viabilidade'!$H$12)),0) -> 0 | Q70: =IF(B70='11-Viabilidade'!$G$11,'11-Viabilidade'!$G$16,0)*(1+'11-Viabilidade'!$G$12)^((B70-1)/12) -> 0 | R70: =-SUM(O70:Q70) -> 0 | S70: =IF(R70<>0,0,S69+1) -> 63 | T70: =IF($S70<'11-Viabilidade'!$C$24,0,$S70-'11-Viabilidade'!$C$24) -> 57 | U70: =IF(T70>0,'11-Viabilidade'!$K$10,0)*((1+'11-Viabilidade'!$O$10)^(($T70-1)/12)) -> 3767.0783 | V70: =U70*'11-Viabilidade'!$L$12 -> 209.28213 | W70: =U70*'11-Viabilidade'!$K$14 -> 0 | X70: =U70*'11-Viabilidade'!$K$15 -> 188.35392 | Y70: =IF(AND(U70=0,S70=0),0,IF(AND(U70=0,S70<>0),'11-Viabilidade'!$K$16+'11-Viabilidade'!$K$17,('11-Viabilidade'!$L$11)*((1+'11-Viabilidade'!$O$10)^(($C70-1)/12)))) -> 492.51061 | Z70: =IFERROR(VLOOKUP(S70,'12-SAC Viabilidade'!$B$11:$G$430,6,FALSE),0) -> 2202.7099 | AA70: =IFERROR(VLOOKUP(S70,'12-SAC Viabilidade'!$B$11:$H$430,7,FALSE),0) -> 204000 | AB70: =(U70-W70)*'11-Viabilidade'!$O$16 -> 565.06175 | AC70: =U70-(V70+W70+X70+Y70+Z70+AB70-R70) -> 109.16005 | AD70: =U70-(V70+W70+X70+Y70+AB70) -> 2311.8699
B71: =IF(AND(B70>0,B70<'11-Viabilidade'!$P$14),B70+1,0) -> 64 | C71: =IF($B71<'11-Viabilidade'!$C$24,0,$B71-'11-Viabilidade'!$C$24) -> 58 | D71: =IF(C71>0,'11-Viabilidade'!$K$10,0)*((1+'11-Viabilidade'!$O$10)^(($C71-1)/12)) -> 3782.4259 | E71: =D71*'11-Viabilidade'!$L$12 -> 210.13477 | F71: =D71*'11-Viabilidade'!$K$14 -> 0 | G71: =D71*'11-Viabilidade'!$K$15 -> 189.12129 | H71: =IF(D71=0,'11-Viabilidade'!$K$16+'11-Viabilidade'!$K$17,('11-Viabilidade'!$L$11)*((1+'11-Viabilidade'!$O$10)^(($C71-1)/12))) -> 494.51716 | I71: ='12-SAC Viabilidade'!G74 -> 2198.1532 | J71: ='12-SAC Viabilidade'!H74 -> 203428.57 | K71: =(D71-F71)*'11-Viabilidade'!$O$16 -> 567.36388 | L71: =D71-(E71+F71+G71+H71+I71+K71) -> 123.13555 | M71: =D71-(E71+F71+G71+H71+K71) -> 2321.2888 | P71: =IF(B71<='11-Viabilidade'!$G$11,(P70+(P70*'11-Viabilidade'!$H$12)),0) -> 0 | Q71: =IF(B71='11-Viabilidade'!$G$11,'11-Viabilidade'!$G$16,0)*(1+'11-Viabilidade'!$G$12)^((B71-1)/12) -> 0 | R71: =-SUM(O71:Q71) -> 0 | S71: =IF(R71<>0,0,S70+1) -> 64 | T71: =IF($S71<'11-Viabilidade'!$C$24,0,$S71-'11-Viabilidade'!$C$24) -> 58 | U71: =IF(T71>0,'11-Viabilidade'!$K$10,0)*((1+'11-Viabilidade'!$O$10)^(($T71-1)/12)) -> 3782.4259 | V71: =U71*'11-Viabilidade'!$L$12 -> 210.13477 | W71: =U71*'11-Viabilidade'!$K$14 -> 0 | X71: =U71*'11-Viabilidade'!$K$15 -> 189.12129 | Y71: =IF(AND(U71=0,S71=0),0,IF(AND(U71=0,S71<>0),'11-Viabilidade'!$K$16+'11-Viabilidade'!$K$17,('11-Viabilidade'!$L$11)*((1+'11-Viabilidade'!$O$10)^(($C71-1)/12)))) -> 494.51716 | Z71: =IFERROR(VLOOKUP(S71,'12-SAC Viabilidade'!$B$11:$G$430,6,FALSE),0) -> 2198.1532 | AA71: =IFERROR(VLOOKUP(S71,'12-SAC Viabilidade'!$B$11:$H$430,7,FALSE),0) -> 203428.57 | AB71: =(U71-W71)*'11-Viabilidade'!$O$16 -> 567.36388 | AC71: =U71-(V71+W71+X71+Y71+Z71+AB71-R71) -> 123.13555 | AD71: =U71-(V71+W71+X71+Y71+AB71) -> 2321.2888
B72: =IF(AND(B71>0,B71<'11-Viabilidade'!$P$14),B71+1,0) -> 65 | C72: =IF($B72<'11-Viabilidade'!$C$24,0,$B72-'11-Viabilidade'!$C$24) -> 59 | D72: =IF(C72>0,'11-Viabilidade'!$K$10,0)*((1+'11-Viabilidade'!$O$10)^(($C72-1)/12)) -> 3797.8359 | E72: =D72*'11-Viabilidade'!$L$12 -> 210.99089 | F72: =D72*'11-Viabilidade'!$K$14 -> 0 | G72: =D72*'11-Viabilidade'!$K$15 -> 189.8918 | H72: =IF(D72=0,'11-Viabilidade'!$K$16+'11-Viabilidade'!$K$17,('11-Viabilidade'!$L$11)*((1+'11-Viabilidade'!$O$10)^(($C72-1)/12))) -> 496.53188 | I72: ='12-SAC Viabilidade'!G75 -> 2193.5966 | J72: ='12-SAC Viabilidade'!H75 -> 202857.14 | K72: =(D72-F72)*'11-Viabilidade'!$O$16 -> 569.67539 | L72: =D72-(E72+F72+G72+H72+I72+K72) -> 137.14942 | M72: =D72-(E72+F72+G72+H72+K72) -> 2330.746 | P72: =IF(B72<='11-Viabilidade'!$G$11,(P71+(P71*'11-Viabilidade'!$H$12)),0) -> 0 | Q72: =IF(B72='11-Viabilidade'!$G$11,'11-Viabilidade'!$G$16,0)*(1+'11-Viabilidade'!$G$12)^((B72-1)/12) -> 0 | R72: =-SUM(O72:Q72) -> 0 | S72: =IF(R72<>0,0,S71+1) -> 65 | T72: =IF($S72<'11-Viabilidade'!$C$24,0,$S72-'11-Viabilidade'!$C$24) -> 59 | U72: =IF(T72>0,'11-Viabilidade'!$K$10,0)*((1+'11-Viabilidade'!$O$10)^(($T72-1)/12)) -> 3797.8359 | V72: =U72*'11-Viabilidade'!$L$12 -> 210.99089 | W72: =U72*'11-Viabilidade'!$K$14 -> 0 | X72: =U72*'11-Viabilidade'!$K$15 -> 189.8918 | Y72: =IF(AND(U72=0,S72=0),0,IF(AND(U72=0,S72<>0),'11-Viabilidade'!$K$16+'11-Viabilidade'!$K$17,('11-Viabilidade'!$L$11)*((1+'11-Viabilidade'!$O$10)^(($C72-1)/12)))) -> 496.53188 | Z72: =IFERROR(VLOOKUP(S72,'12-SAC Viabilidade'!$B$11:$G$430,6,FALSE),0) -> 2193.5966 | AA72: =IFERROR(VLOOKUP(S72,'12-SAC Viabilidade'!$B$11:$H$430,7,FALSE),0) -> 202857.14 | AB72: =(U72-W72)*'11-Viabilidade'!$O$16 -> 569.67539 | AC72: =U72-(V72+W72+X72+Y72+Z72+AB72-R72) -> 137.14942 | AD72: =U72-(V72+W72+X72+Y72+AB72) -> 2330.746
B73: =IF(AND(B72>0,B72<'11-Viabilidade'!$P$14),B72+1,0) -> 66 | C73: =IF($B73<'11-Viabilidade'!$C$24,0,$B73-'11-Viabilidade'!$C$24) -> 60 | D73: =IF(C73>0,'11-Viabilidade'!$K$10,0)*((1+'11-Viabilidade'!$O$10)^(($C73-1)/12)) -> 3813.3088 | E73: =D73*'11-Viabilidade'!$L$12 -> 211.85049 | F73: =D73*'11-Viabilidade'!$K$14 -> 0 | G73: =D73*'11-Viabilidade'!$K$15 -> 190.66544 | H73: =IF(D73=0,'11-Viabilidade'!$K$16+'11-Viabilidade'!$K$17,('11-Viabilidade'!$L$11)*((1+'11-Viabilidade'!$O$10)^(($C73-1)/12))) -> 498.55482 | I73: ='12-SAC Viabilidade'!G76 -> 2189.0399 | J73: ='12-SAC Viabilidade'!H76 -> 202285.71 | K73: =(D73-F73)*'11-Viabilidade'!$O$16 -> 571.99632 | L73: =D73-(E73+F73+G73+H73+I73+K73) -> 151.20182 | M73: =D73-(E73+F73+G73+H73+K73) -> 2340.2417 | P73: =IF(B73<='11-Viabilidade'!$G$11,(P72+(P72*'11-Viabilidade'!$H$12)),0) -> 0 | Q73: =IF(B73='11-Viabilidade'!$G$11,'11-Viabilidade'!$G$16,0)*(1+'11-Viabilidade'!$G$12)^((B73-1)/12) -> 0 | R73: =-SUM(O73:Q73) -> 0 | S73: =IF(R73<>0,0,S72+1) -> 66 | T73: =IF($S73<'11-Viabilidade'!$C$24,0,$S73-'11-Viabilidade'!$C$24) -> 60 | U73: =IF(T73>0,'11-Viabilidade'!$K$10,0)*((1+'11-Viabilidade'!$O$10)^(($T73-1)/12)) -> 3813.3088 | V73: =U73*'11-Viabilidade'!$L$12 -> 211.85049 | W73: =U73*'11-Viabilidade'!$K$14 -> 0 | X73: =U73*'11-Viabilidade'!$K$15 -> 190.66544 | Y73: =IF(AND(U73=0,S73=0),0,IF(AND(U73=0,S73<>0),'11-Viabilidade'!$K$16+'11-Viabilidade'!$K$17,('11-Viabilidade'!$L$11)*((1+'11-Viabilidade'!$O$10)^(($C73-1)/12)))) -> 498.55482 | Z73: =IFERROR(VLOOKUP(S73,'12-SAC Viabilidade'!$B$11:$G$430,6,FALSE),0) -> 2189.0399 | AA73: =IFERROR(VLOOKUP(S73,'12-SAC Viabilidade'!$B$11:$H$430,7,FALSE),0) -> 202285.71 | AB73: =(U73-W73)*'11-Viabilidade'!$O$16 -> 571.99632 | AC73: =U73-(V73+W73+X73+Y73+Z73+AB73-R73) -> 151.20182 | AD73: =U73-(V73+W73+X73+Y73+AB73) -> 2340.2417
B74: =IF(AND(B73>0,B73<'11-Viabilidade'!$P$14),B73+1,0) -> 67 | C74: =IF($B74<'11-Viabilidade'!$C$24,0,$B74-'11-Viabilidade'!$C$24) -> 61 | D74: =IF(C74>0,'11-Viabilidade'!$K$10,0)*((1+'11-Viabilidade'!$O$10)^(($C74-1)/12)) -> 3828.8447 | E74: =D74*'11-Viabilidade'!$L$12 -> 212.71359 | F74: =D74*'11-Viabilidade'!$K$14 -> 0 | G74: =D74*'11-Viabilidade'!$K$15 -> 191.44223 | H74: =IF(D74=0,'11-Viabilidade'!$K$16+'11-Viabilidade'!$K$17,('11-Viabilidade'!$L$11)*((1+'11-Viabilidade'!$O$10)^(($C74-1)/12))) -> 500.58599 | I74: ='12-SAC Viabilidade'!G77 -> 2184.4833 | J74: ='12-SAC Viabilidade'!H77 -> 201714.29 | K74: =(D74-F74)*'11-Viabilidade'!$O$16 -> 574.3267 | L74: =D74-(E74+F74+G74+H74+I74+K74) -> 165.2929 | M74: =D74-(E74+F74+G74+H74+K74) -> 2349.7762 | P74: =IF(B74<='11-Viabilidade'!$G$11,(P73+(P73*'11-Viabilidade'!$H$12)),0) -> 0 | Q74: =IF(B74='11-Viabilidade'!$G$11,'11-Viabilidade'!$G$16,0)*(1+'11-Viabilidade'!$G$12)^((B74-1)/12) -> 0 | R74: =-SUM(O74:Q74) -> 0 | S74: =IF(R74<>0,0,S73+1) -> 67 | T74: =IF($S74<'11-Viabilidade'!$C$24,0,$S74-'11-Viabilidade'!$C$24) -> 61 | U74: =IF(T74>0,'11-Viabilidade'!$K$10,0)*((1+'11-Viabilidade'!$O$10)^(($T74-1)/12)) -> 3828.8447 | V74: =U74*'11-Viabilidade'!$L$12 -> 212.71359 | W74: =U74*'11-Viabilidade'!$K$14 -> 0 | X74: =U74*'11-Viabilidade'!$K$15 -> 191.44223 | Y74: =IF(AND(U74=0,S74=0),0,IF(AND(U74=0,S74<>0),'11-Viabilidade'!$K$16+'11-Viabilidade'!$K$17,('11-Viabilidade'!$L$11)*((1+'11-Viabilidade'!$O$10)^(($C74-1)/12)))) -> 500.58599 | Z74: =IFERROR(VLOOKUP(S74,'12-SAC Viabilidade'!$B$11:$G$430,6,FALSE),0) -> 2184.4833 | AA74: =IFERROR(VLOOKUP(S74,'12-SAC Viabilidade'!$B$11:$H$430,7,FALSE),0) -> 201714.29 | AB74: =(U74-W74)*'11-Viabilidade'!$O$16 -> 574.3267 | AC74: =U74-(V74+W74+X74+Y74+Z74+AB74-R74) -> 165.2929 | AD74: =U74-(V74+W74+X74+Y74+AB74) -> 2349.7762
B75: =IF(AND(B74>0,B74<'11-Viabilidade'!$P$14),B74+1,0) -> 68 | C75: =IF($B75<'11-Viabilidade'!$C$24,0,$B75-'11-Viabilidade'!$C$24) -> 62 | D75: =IF(C75>0,'11-Viabilidade'!$K$10,0)*((1+'11-Viabilidade'!$O$10)^(($C75-1)/12)) -> 3844.4439 | E75: =D75*'11-Viabilidade'!$L$12 -> 213.58022 | F75: =D75*'11-Viabilidade'!$K$14 -> 0 | G75: =D75*'11-Viabilidade'!$K$15 -> 192.22219 | H75: =IF(D75=0,'11-Viabilidade'!$K$16+'11-Viabilidade'!$K$17,('11-Viabilidade'!$L$11)*((1+'11-Viabilidade'!$O$10)^(($C75-1)/12))) -> 502.62544 | I75: ='12-SAC Viabilidade'!G78 -> 2179.9266 | J75: ='12-SAC Viabilidade'!H78 -> 201142.86 | K75: =(D75-F75)*'11-Viabilidade'!$O$16 -> 576.66658 | L75: =D75-(E75+F75+G75+H75+I75+K75) -> 179.42283 | M75: =D75-(E75+F75+G75+H75+K75) -> 2359.3494 | P75: =IF(B75<='11-Viabilidade'!$G$11,(P74+(P74*'11-Viabilidade'!$H$12)),0) -> 0 | Q75: =IF(B75='11-Viabilidade'!$G$11,'11-Viabilidade'!$G$16,0)*(1+'11-Viabilidade'!$G$12)^((B75-1)/12) -> 0 | R75: =-SUM(O75:Q75) -> 0 | S75: =IF(R75<>0,0,S74+1) -> 68 | T75: =IF($S75<'11-Viabilidade'!$C$24,0,$S75-'11-Viabilidade'!$C$24) -> 62 | U75: =IF(T75>0,'11-Viabilidade'!$K$10,0)*((1+'11-Viabilidade'!$O$10)^(($T75-1)/12)) -> 3844.4439 | V75: =U75*'11-Viabilidade'!$L$12 -> 213.58022 | W75: =U75*'11-Viabilidade'!$K$14 -> 0 | X75: =U75*'11-Viabilidade'!$K$15 -> 192.22219 | Y75: =IF(AND(U75=0,S75=0),0,IF(AND(U75=0,S75<>0),'11-Viabilidade'!$K$16+'11-Viabilidade'!$K$17,('11-Viabilidade'!$L$11)*((1+'11-Viabilidade'!$O$10)^(($C75-1)/12)))) -> 502.62544 | Z75: =IFERROR(VLOOKUP(S75,'12-SAC Viabilidade'!$B$11:$G$430,6,FALSE),0) -> 2179.9266 | AA75: =IFERROR(VLOOKUP(S75,'12-SAC Viabilidade'!$B$11:$H$430,7,FALSE),0) -> 201142.86 | AB75: =(U75-W75)*'11-Viabilidade'!$O$16 -> 576.66658 | AC75: =U75-(V75+W75+X75+Y75+Z75+AB75-R75) -> 179.42283 | AD75: =U75-(V75+W75+X75+Y75+AB75) -> 2359.3494
B76: =IF(AND(B75>0,B75<'11-Viabilidade'!$P$14),B75+1,0) -> 69 | C76: =IF($B76<'11-Viabilidade'!$C$24,0,$B76-'11-Viabilidade'!$C$24) -> 63 | D76: =IF(C76>0,'11-Viabilidade'!$K$10,0)*((1+'11-Viabilidade'!$O$10)^(($C76-1)/12)) -> 3860.1066 | E76: =D76*'11-Viabilidade'!$L$12 -> 214.45037 | F76: =D76*'11-Viabilidade'!$K$14 -> 0 | G76: =D76*'11-Viabilidade'!$K$15 -> 193.00533 | H76: =IF(D76=0,'11-Viabilidade'!$K$16+'11-Viabilidade'!$K$17,('11-Viabilidade'!$L$11)*((1+'11-Viabilidade'!$O$10)^(($C76-1)/12))) -> 504.6732 | I76: ='12-SAC Viabilidade'!G79 -> 2175.37 | J76: ='12-SAC Viabilidade'!H79 -> 200571.43 | K76: =(D76-F76)*'11-Viabilidade'!$O$16 -> 579.01599 | L76: =D76-(E76+F76+G76+H76+I76+K76) -> 193.59177 | M76: =D76-(E76+F76+G76+H76+K76) -> 2368.9617 | P76: =IF(B76<='11-Viabilidade'!$G$11,(P75+(P75*'11-Viabilidade'!$H$12)),0) -> 0 | Q76: =IF(B76='11-Viabilidade'!$G$11,'11-Viabilidade'!$G$16,0)*(1+'11-Viabilidade'!$G$12)^((B76-1)/12) -> 0 | R76: =-SUM(O76:Q76) -> 0 | S76: =IF(R76<>0,0,S75+1) -> 69 | T76: =IF($S76<'11-Viabilidade'!$C$24,0,$S76-'11-Viabilidade'!$C$24) -> 63 | U76: =IF(T76>0,'11-Viabilidade'!$K$10,0)*((1+'11-Viabilidade'!$O$10)^(($T76-1)/12)) -> 3860.1066 | V76: =U76*'11-Viabilidade'!$L$12 -> 214.45037 | W76: =U76*'11-Viabilidade'!$K$14 -> 0 | X76: =U76*'11-Viabilidade'!$K$15 -> 193.00533 | Y76: =IF(AND(U76=0,S76=0),0,IF(AND(U76=0,S76<>0),'11-Viabilidade'!$K$16+'11-Viabilidade'!$K$17,('11-Viabilidade'!$L$11)*((1+'11-Viabilidade'!$O$10)^(($C76-1)/12)))) -> 504.6732 | Z76: =IFERROR(VLOOKUP(S76,'12-SAC Viabilidade'!$B$11:$G$430,6,FALSE),0) -> 2175.37 | AA76: =IFERROR(VLOOKUP(S76,'12-SAC Viabilidade'!$B$11:$H$430,7,FALSE),0) -> 200571.43 | AB76: =(U76-W76)*'11-Viabilidade'!$O$16 -> 579.01599 | AC76: =U76-(V76+W76+X76+Y76+Z76+AB76-R76) -> 193.59177 | AD76: =U76-(V76+W76+X76+Y76+AB76) -> 2368.9617
B77: =IF(AND(B76>0,B76<'11-Viabilidade'!$P$14),B76+1,0) -> 70 | C77: =IF($B77<'11-Viabilidade'!$C$24,0,$B77-'11-Viabilidade'!$C$24) -> 64 | D77: =IF(C77>0,'11-Viabilidade'!$K$10,0)*((1+'11-Viabilidade'!$O$10)^(($C77-1)/12)) -> 3875.8332 | E77: =D77*'11-Viabilidade'!$L$12 -> 215.32406 | F77: =D77*'11-Viabilidade'!$K$14 -> 0 | G77: =D77*'11-Viabilidade'!$K$15 -> 193.79166 | H77: =IF(D77=0,'11-Viabilidade'!$K$16+'11-Viabilidade'!$K$17,('11-Viabilidade'!$L$11)*((1+'11-Viabilidade'!$O$10)^(($C77-1)/12))) -> 506.7293 | I77: ='12-SAC Viabilidade'!G80 -> 2170.8133 | J77: ='12-SAC Viabilidade'!H80 -> 200000 | K77: =(D77-F77)*'11-Viabilidade'!$O$16 -> 581.37498 | L77: =D77-(E77+F77+G77+H77+I77+K77) -> 207.79986 | M77: =D77-(E77+F77+G77+H77+K77) -> 2378.6132 | P77: =IF(B77<='11-Viabilidade'!$G$11,(P76+(P76*'11-Viabilidade'!$H$12)),0) -> 0 | Q77: =IF(B77='11-Viabilidade'!$G$11,'11-Viabilidade'!$G$16,0)*(1+'11-Viabilidade'!$G$12)^((B77-1)/12) -> 0 | R77: =-SUM(O77:Q77) -> 0 | S77: =IF(R77<>0,0,S76+1) -> 70 | T77: =IF($S77<'11-Viabilidade'!$C$24,0,$S77-'11-Viabilidade'!$C$24) -> 64 | U77: =IF(T77>0,'11-Viabilidade'!$K$10,0)*((1+'11-Viabilidade'!$O$10)^(($T77-1)/12)) -> 3875.8332 | V77: =U77*'11-Viabilidade'!$L$12 -> 215.32406 | W77: =U77*'11-Viabilidade'!$K$14 -> 0 | X77: =U77*'11-Viabilidade'!$K$15 -> 193.79166 | Y77: =IF(AND(U77=0,S77=0),0,IF(AND(U77=0,S77<>0),'11-Viabilidade'!$K$16+'11-Viabilidade'!$K$17,('11-Viabilidade'!$L$11)*((1+'11-Viabilidade'!$O$10)^(($C77-1)/12)))) -> 506.7293 | Z77: =IFERROR(VLOOKUP(S77,'12-SAC Viabilidade'!$B$11:$G$430,6,FALSE),0) -> 2170.8133 | AA77: =IFERROR(VLOOKUP(S77,'12-SAC Viabilidade'!$B$11:$H$430,7,FALSE),0) -> 200000 | AB77: =(U77-W77)*'11-Viabilidade'!$O$16 -> 581.37498 | AC77: =U77-(V77+W77+X77+Y77+Z77+AB77-R77) -> 207.79986 | AD77: =U77-(V77+W77+X77+Y77+AB77) -> 2378.6132
B78: =IF(AND(B77>0,B77<'11-Viabilidade'!$P$14),B77+1,0) -> 71 | C78: =IF($B78<'11-Viabilidade'!$C$24,0,$B78-'11-Viabilidade'!$C$24) -> 65 | D78: =IF(C78>0,'11-Viabilidade'!$K$10,0)*((1+'11-Viabilidade'!$O$10)^(($C78-1)/12)) -> 3891.6238 | E78: =D78*'11-Viabilidade'!$L$12 -> 216.20132 | F78: =D78*'11-Viabilidade'!$K$14 -> 0 | G78: =D78*'11-Viabilidade'!$K$15 -> 194.58119 | H78: =IF(D78=0,'11-Viabilidade'!$K$16+'11-Viabilidade'!$K$17,('11-Viabilidade'!$L$11)*((1+'11-Viabilidade'!$O$10)^(($C78-1)/12))) -> 508.79378 | I78: ='12-SAC Viabilidade'!G81 -> 2166.2567 | J78: ='12-SAC Viabilidade'!H81 -> 199428.57 | K78: =(D78-F78)*'11-Viabilidade'!$O$16 -> 583.74357 | L78: =D78-(E78+F78+G78+H78+I78+K78) -> 222.04728 | M78: =D78-(E78+F78+G78+H78+K78) -> 2388.3039 | P78: =IF(B78<='11-Viabilidade'!$G$11,(P77+(P77*'11-Viabilidade'!$H$12)),0) -> 0 | Q78: =IF(B78='11-Viabilidade'!$G$11,'11-Viabilidade'!$G$16,0)*(1+'11-Viabilidade'!$G$12)^((B78-1)/12) -> 0 | R78: =-SUM(O78:Q78) -> 0 | S78: =IF(R78<>0,0,S77+1) -> 71 | T78: =IF($S78<'11-Viabilidade'!$C$24,0,$S78-'11-Viabilidade'!$C$24) -> 65 | U78: =IF(T78>0,'11-Viabilidade'!$K$10,0)*((1+'11-Viabilidade'!$O$10)^(($T78-1)/12)) -> 3891.6238 | V78: =U78*'11-Viabilidade'!$L$12 -> 216.20132 | W78: =U78*'11-Viabilidade'!$K$14 -> 0 | X78: =U78*'11-Viabilidade'!$K$15 -> 194.58119 | Y78: =IF(AND(U78=0,S78=0),0,IF(AND(U78=0,S78<>0),'11-Viabilidade'!$K$16+'11-Viabilidade'!$K$17,('11-Viabilidade'!$L$11)*((1+'11-Viabilidade'!$O$10)^(($C78-1)/12)))) -> 508.79378 | Z78: =IFERROR(VLOOKUP(S78,'12-SAC Viabilidade'!$B$11:$G$430,6,FALSE),0) -> 2166.2567 | AA78: =IFERROR(VLOOKUP(S78,'12-SAC Viabilidade'!$B$11:$H$430,7,FALSE),0) -> 199428.57 | AB78: =(U78-W78)*'11-Viabilidade'!$O$16 -> 583.74357 | AC78: =U78-(V78+W78+X78+Y78+Z78+AB78-R78) -> 222.04728 | AD78: =U78-(V78+W78+X78+Y78+AB78) -> 2388.3039
A79: 7º Ano | B79: =IF(AND(B78>0,B78<'11-Viabilidade'!$P$14),B78+1,0) -> 72 | C79: =IF($B79<'11-Viabilidade'!$C$24,0,$B79-'11-Viabilidade'!$C$24) -> 66 | D79: =IF(C79>0,'11-Viabilidade'!$K$10,0)*((1+'11-Viabilidade'!$O$10)^(($C79-1)/12)) -> 3907.4787 | E79: =D79*'11-Viabilidade'!$L$12 -> 217.08215 | F79: =D79*'11-Viabilidade'!$K$14 -> 0 | G79: =D79*'11-Viabilidade'!$K$15 -> 195.37394 | H79: =IF(D79=0,'11-Viabilidade'!$K$16+'11-Viabilidade'!$K$17,('11-Viabilidade'!$L$11)*((1+'11-Viabilidade'!$O$10)^(($C79-1)/12))) -> 510.86667 | I79: ='12-SAC Viabilidade'!G82 -> 2161.7 | J79: ='12-SAC Viabilidade'!H82 -> 198857.14 | K79: =(D79-F79)*'11-Viabilidade'!$O$16 -> 586.12181 | L79: =D79-(E79+F79+G79+H79+I79+K79) -> 236.33417 | M79: =D79-(E79+F79+G79+H79+K79) -> 2398.0342 | P79: =IF(B79<='11-Viabilidade'!$G$11,(P78+(P78*'11-Viabilidade'!$H$12)),0) -> 0 | Q79: =IF(B79='11-Viabilidade'!$G$11,'11-Viabilidade'!$G$16,0)*(1+'11-Viabilidade'!$G$12)^((B79-1)/12) -> 0 | R79: =-SUM(O79:Q79) -> 0 | S79: =IF(R79<>0,0,S78+1) -> 72 | T79: =IF($S79<'11-Viabilidade'!$C$24,0,$S79-'11-Viabilidade'!$C$24) -> 66 | U79: =IF(T79>0,'11-Viabilidade'!$K$10,0)*((1+'11-Viabilidade'!$O$10)^(($T79-1)/12)) -> 3907.4787 | V79: =U79*'11-Viabilidade'!$L$12 -> 217.08215 | W79: =U79*'11-Viabilidade'!$K$14 -> 0 | X79: =U79*'11-Viabilidade'!$K$15 -> 195.37394 | Y79: =IF(AND(U79=0,S79=0),0,IF(AND(U79=0,S79<>0),'11-Viabilidade'!$K$16+'11-Viabilidade'!$K$17,('11-Viabilidade'!$L$11)*((1+'11-Viabilidade'!$O$10)^(($C79-1)/12)))) -> 510.86667 | Z79: =IFERROR(VLOOKUP(S79,'12-SAC Viabilidade'!$B$11:$G$430,6,FALSE),0) -> 2161.7 | AA79: =IFERROR(VLOOKUP(S79,'12-SAC Viabilidade'!$B$11:$H$430,7,FALSE),0) -> 198857.14 | AB79: =(U79-W79)*'11-Viabilidade'!$O$16 -> 586.12181 | AC79: =U79-(V79+W79+X79+Y79+Z79+AB79-R79) -> 236.33417 | AD79: =U79-(V79+W79+X79+Y79+AB79) -> 2398.0342
B80: =IF(AND(B79>0,B79<'11-Viabilidade'!$P$14),B79+1,0) -> 73 | C80: =IF($B80<'11-Viabilidade'!$C$24,0,$B80-'11-Viabilidade'!$C$24) -> 67 | D80: =IF(C80>0,'11-Viabilidade'!$K$10,0)*((1+'11-Viabilidade'!$O$10)^(($C80-1)/12)) -> 3923.3983 | E80: =D80*'11-Viabilidade'!$L$12 -> 217.96657 | F80: =D80*'11-Viabilidade'!$K$14 -> 0 | G80: =D80*'11-Viabilidade'!$K$15 -> 196.16992 | H80: =IF(D80=0,'11-Viabilidade'!$K$16+'11-Viabilidade'!$K$17,('11-Viabilidade'!$L$11)*((1+'11-Viabilidade'!$O$10)^(($C80-1)/12))) -> 512.948 | I80: ='12-SAC Viabilidade'!G83 -> 2157.1434 | J80: ='12-SAC Viabilidade'!H83 -> 198285.71 | K80: =(D80-F80)*'11-Viabilidade'!$O$16 -> 588.50975 | L80: =D80-(E80+F80+G80+H80+I80+K80) -> 250.66071 | M80: =D80-(E80+F80+G80+H80+K80) -> 2407.8041 | P80: =IF(B80<='11-Viabilidade'!$G$11,(P79+(P79*'11-Viabilidade'!$H$12)),0) -> 0 | Q80: =IF(B80='11-Viabilidade'!$G$11,'11-Viabilidade'!$G$16,0)*(1+'11-Viabilidade'!$G$12)^((B80-1)/12) -> 0 | R80: =-SUM(O80:Q80) -> 0 | S80: =IF(R80<>0,0,S79+1) -> 73 | T80: =IF($S80<'11-Viabilidade'!$C$24,0,$S80-'11-Viabilidade'!$C$24) -> 67 | U80: =IF(T80>0,'11-Viabilidade'!$K$10,0)*((1+'11-Viabilidade'!$O$10)^(($T80-1)/12)) -> 3923.3983 | V80: =U80*'11-Viabilidade'!$L$12 -> 217.96657 | W80: =U80*'11-Viabilidade'!$K$14 -> 0 | X80: =U80*'11-Viabilidade'!$K$15 -> 196.16992 | Y80: =IF(AND(U80=0,S80=0),0,IF(AND(U80=0,S80<>0),'11-Viabilidade'!$K$16+'11-Viabilidade'!$K$17,('11-Viabilidade'!$L$11)*((1+'11-Viabilidade'!$O$10)^(($C80-1)/12)))) -> 512.948 | Z80: =IFERROR(VLOOKUP(S80,'12-SAC Viabilidade'!$B$11:$G$430,6,FALSE),0) -> 2157.1434 | AA80: =IFERROR(VLOOKUP(S80,'12-SAC Viabilidade'!$B$11:$H$430,7,FALSE),0) -> 198285.71 | AB80: =(U80-W80)*'11-Viabilidade'!$O$16 -> 588.50975 | AC80: =U80-(V80+W80+X80+Y80+Z80+AB80-R80) -> 250.66071 | AD80: =U80-(V80+W80+X80+Y80+AB80) -> 2407.8041
